Workbook
Name Вознаграждение: #REF!
Name Вознаграждение: #REF!
Name Вознаграждение: #REF!
Name ДатаФиниш: #REF!
Name ДатаФиниш: #REF!
Name ДатаФиниш: #REF!
Name договорная_сумма: #REF!
Name договорная_сумма: #REF!
Name договорная_сумма: #REF!
Name ДС: #REF!
Name ДС: #REF!
Name ДС: #REF!
Name ПВ: #REF!
Name ПВ: #REF!
Name ПВ: #REF!
Name ПВ: #REF!
Name регионы: #REF!
Name регионы: #REF!
Name регионы: #REF!
Name регионы: #REF!
Name Рынок: #REF!
Name Рынок: #REF!
Name Рынок: #REF!
Name Рынок: #REF!
Name состав: #REF!
Name состав: #REF!
Name состав: #REF!
Name состав: #REF!
Name Ставка: #REF!
Name Ставка: #REF!
Name Ставка: #REF!

Sheet для бигтандау
A1: Класс/Комнатность | B1: 1-комнатная | C1: 2-комнатная | D1: 3-комнатная | E1: 4-комнатная | F1: 5-комнатная
A2: стандарт | B2: 65573.77 | C2: 131147.54 | D2: 196721.31 | E2: 262295.08 | F2: 262295.08
A3: комфорт | B3: 65573.77 | C3: 131147.54 | D3: 196721.31 | E3: 262295.08 | F3: 262295.08
A4: комфорт+ | B4: 65573.77 | C4: 131147.54 | D4: 196721.31 | E4: 262295.08 | F4: 262295.08
A5: бизнес | B5: 98360.653 | C5: 163935 | D5: 229508.2 | E5: 295081 | F5: 295081
A6: бизнес+ | B6: 98360.653 | C6: 163935 | D6: 229508.2 | E6: 295081 | F6: 295081
A7: премиум ПД | B7: 98360.653 | C7: 163935 | D7: 229508.2 | E7: 295081 | F7: 295081
A10: Срок | B10: Ставка
A11: 12 | B11: 0.085
A12: 24 | B12: 0.085
A13: 36 | B13: 0.13
A14: 48 | B14: 0.13
A15: 60 | B15: 0.135
A18: Отделка | B18: Мин. ПВ
A19: Чистовая | B19: 0.2
A20: Черновая | B20: 0.3

Sheet Подборщик
A1: Город | B1: Объекты | C1: Тип помещений | F1: Остатки на 10.11.2025 | G1: Вид основания | H1: есть ФГЖС | I1: без доп залога | Y1: доп залог | AF1: готовое жилье
D2: Block_ID | E2: Block_ID тест | I2: Отбасы Банк (Женил), 50/50 | J2: Отбасы Банк Елорда Жастары | K2: FFB (Каскадная ипотека) готовое жилье | L2: FFB (Каскадная ипотека) ДДУ | M2: FFB (Цифровая ипотека) | N2: «Новая ипотека» 36/14 Отбасы Банк | O2: «Новая ипотека» 30/70 Отбасы Банк | P2: «Super ипотека» по БЦК | Q2: «Оңай ипотека (онлайн)» | R2: «Оңай ипотека (офлайн)» | S2: Halyk ипотека | T2: Наурыз/Наурыз жұмыскер Отбасы Банк | U2: KASPI паркинги/кладовые | V2: Рассрочка на паркинги/кладовые МФО FFC (онлайн) | W2: «BIG Tandau» от МФО BI FINANCE | X2: Бизнес Ипотека (на офисы от Алтын Банк) | Y2: Отбасы Банк (Женил под доп залог) 50/50 | Z2: «Новая ипотека» 36/14 Отбасы Банк | AA2: «Новая ипотека» 30/70 Отбасы Банк | AB2: Алтын Банк Стандарт БЦК (Залоговый кредит) | AC2: Зелёная ипотека Отбасы Банк | AD2: Женская ипотека «ҰМАЙ» Отбасы Банк | AE2: Аскери Баспана
A3: Астана | B3: Sezim Qala Orken - 1 | C3: жилые | F3: =VLOOKUP(B3,[3]Лист_1!$A:$E,5,0) -> 6 | G3: ДДУ | L3: да | M3: да | P3: да | Q3: да | S3: да | W3: да 36 | Y3: да, max 891 000 тенге за 1 кв.м. | AA3: да, max 891 000 тенге за 1 кв.м. | AD3: да | AE3: да
A4: Астана | B4: Jetisu. Aqsu - 5 | C4: жилые | F4: =VLOOKUP(B4,[3]Лист_1!$A:$E,5,0) -> 0 | G4: ПД | I4: да, max 600 000 тенге за 1 кв.м. | N4: да, max 600 000 тенге за 1 кв.м. | O4: да, max 600 000 тенге за 1 кв.м. | P4: да офлайн | R4: да | AD4: да | AE4: да | AF4: да
A5: Астана | B5: Jetisu Aqsu 6 | C5: жилые | F5: =VLOOKUP(B5,[3]Лист_1!$A:$E,5,0) -> 3 | G5: ДДУ | L5: да | M5: да | P5: да | Q5: да | S5: да | W5: да 36 | Y5: да, max 700 000 тенге за 1 кв.м. | AA5: да, max 700 000 тенге за 1 кв.м. | AB5: да | AD5: да
A6: Астана | B6: Jetisu Aqsu - 6 - ЧО | C6: жилые | F6: =VLOOKUP(B6,[3]Лист_1!$A:$E,5,0) -> 0 | G6: ДДУ | L6: да | M6: да | Q6: да | S6: да | W6: да 36 | Y6: да, max 700 000 тенге за 1 кв.м. | Z6: да, max 700 000 тенге за 1 кв.м. | AA6: да, max 700 000 тенге за 1 кв.м. | AB6: да | AD6: да
A7: Астана | B7: Jetisu Aspan A | C7: жилые | F7: =VLOOKUP(B7,[3]Лист_1!$A:$E,5,0) -> 30 | G7: ДДУ | L7: да | M7: да | P7: да | Q7: да | W7: да 36 | Y7: да | AD7: да
A8: Астана | B8: Jetisu Aspan A - ЧО | C8: жилые | F8: =VLOOKUP(B8,[3]Лист_1!$A:$E,5,0) -> 23 | G8: ДДУ | L8: да | M8: да | P8: да | Q8: да | W8: да 36 | Y8: да | AD8: да
A9: Астана | B9: Jetisu Kerbez - 2 | C9: жилые | F9: =VLOOKUP(B9,[3]Лист_1!$A:$E,5,0) -> 3 | G9: ДДУ | L9: да | M9: да | P9: да | Q9: да | S9: да | W9: да 36 | Y9: да, max 784 000 тенге за 1 кв.м. | Z9: да, max 700 000 тенге за 1 кв.м. | AA9: да, max 784 000 тенге за 1 кв.м. | AD9: да | AE9: да
A10: Астана | B10: Jetisu Kerbez - 2 - ЧО | C10: жилые | F10: =VLOOKUP(B10,[3]Лист_1!$A:$E,5,0) -> 1 | G10: ДДУ | L10: да | M10: да | P10: да | Q10: да | S10: да | W10: да 36 | Y10: да, max 784 000 тенге за 1 кв.м. | Z10: да, max 784 000 тенге за 1 кв.м. | AA10: да, max 784 000 тенге за 1 кв.м. | AD10: да | AE10: да
A11: Астана | B11: Jetisu Kerbez Comfort - 1 | C11: жилые | F11: =VLOOKUP(B11,[3]Лист_1!$A:$E,5,0) -> 68 | G11: ДДУ | I11: да, max 554 400 тенге за 1 кв.м. | L11: да | M11: да | P11: да | Q11: да | S11: да | T11: да | W11: да 36 | Y11: да | AA11: да, max 810 000 тенге за 1 кв.м. | AD11: да
A12: Астана | B12: Jetisu Kerbez Comfort - 1 - ЧО | C12: жилые | F12: =VLOOKUP(B12,[3]Лист_1!$A:$E,5,0) -> 32 | G12: ДДУ | L12: да | M12: да | P12: да | Q12: да | S12: да | W12: да 36 | Y12: да | AA12: да, max 810 000 тенге за 1 кв.м. | AD12: да
A13: Астана | B13: Jetisu Satti | C13: жилые | F13: =VLOOKUP(B13,[3]Лист_1!$A:$E,5,0) -> 56 | G13: ДДУ | L13: да | M13: да | P13: да | Q13: да | S13: да | W13: да 36 | Y13: да | AD13: да
A14: Астана | B14: AruPark - 1 | C14: жилые | F14: =VLOOKUP(B14,[3]Лист_1!$A:$E,5,0) -> 0 | G14: ПД | I14: да | R14: да | AD14: да | AF14: да
A15: Астана | B15: AruPark - 1 - ЧО | C15: жилые | F15: =VLOOKUP(B15,[3]Лист_1!$A:$E,5,0) -> 0 | G15: ПД | I15: да | R15: да | AD15: да | AF15: да
A16: Астана | B16: AruPark - 2 - 1 | C16: жилые | F16: =VLOOKUP(B16,[3]Лист_1!$A:$E,5,0) -> 0 | G16: ПД | I16: да | R16: да | AD16: да | AF16: да
A17: Астана | B17: AruPark - 2 - 1 - ЧО | C17: жилые | F17: =VLOOKUP(B17,[3]Лист_1!$A:$E,5,0) -> 0 | G17: ПД | I17: да | R17: да | AD17: да | AF17: да
A18: Астана | B18: AruPark 2-2 подъезд 5, 8 | C18: жилые | F18: =VLOOKUP(B18,[3]Лист_1!$A:$E,5,0) -> 0 | G18: ДДУ | L18: да | M18: да | Q18: да | S18: да | W18: да 36 | Y18: да | AD18: да
A19: Астана | B19: AruPark 2 - 2 - ЧО | C19: жилые | F19: =VLOOKUP(B19,[3]Лист_1!$A:$E,5,0) -> 0 | G19: ДДУ | L19: да | M19: да | P19: да | Q19: да | S19: да | W19: да 36 | Y19: да | AD19: да
A20: Астана | B20: AruPark - 3 | C20: жилые | F20: =VLOOKUP(B20,[3]Лист_1!$A:$E,5,0) -> 20 | G20: ДДУ | I20: да, max 530 200 тенге за 1 кв.м. | L20: да | M20: да | P20: да | Q20: да | S20: да | T20: да | W20: да 36 | Y20: да | AD20: да
A21: Астана | B21: AruPark - 3 - ЧО | C21: жилые | F21: =VLOOKUP(B21,[3]Лист_1!$A:$E,5,0) -> 8 | G21: ДДУ | L21: да | M21: да | P21: да | Q21: да | S21: да | W21: да 36 | Y21: да | AD21: да
A22: Астана | B22: Aisar - 1 | C22: жилые | F22: =VLOOKUP(B22,[3]Лист_1!$A:$E,5,0) -> 0 | G22: ПД | I22: да, max 478 000 тенге за 1 кв.м. | K22: да 1 ком.- 537000 тг 2 ком.- 459000 тг 3 ком.- 449000 тг 4 ком.- 437000 тг | N22: да, max 478 000 тенге за 1 кв.м. | O22: да, max 478 000 тенге за 1 кв.м. | R22: да | AD22: да | AF22: да
A23: Астана | B23: Aisar - 2 | C23: жилые | F23: =VLOOKUP(B23,[3]Лист_1!$A:$E,5,0) -> 3 | G23: ДДУ | L23: да | M23: да | Q23: да | S23: да | T23: да | W23: да 36 | Y23: да, max 850 000 тенге за 1 кв.м. | AA23: да, max 850 000 тенге за 1 кв.м. | AD23: да | AE23: да
A24: Астана | B24: Aisar 3 | C24: жилые | F24: =VLOOKUP(B24,[3]Лист_1!$A:$E,5,0) -> 101 | G24: ДДУ | I24: да, max 554 400 тенге за 1 кв.м. | L24: да | M24: да | P24: да | Q24: да | S24: да | T24: да | W24: да 36 | Y24: да | AD24: да
A25: Астана | B25: Aisar - 4 | C25: жилые | F25: =VLOOKUP(B25,[3]Лист_1!$A:$E,5,0) -> 183 | G25: ДДУ | L25: да | M25: да | P25: да | Q25: да | S25: да | W25: да 36 | Y25: да | AD25: да
A26: Астана | B26: Atlant - 6 | C26: жилые | F26: =VLOOKUP(B26,[3]Лист_1!$A:$E,5,0) -> 0 | G26: ПД | I26: да, 1 ком.- 850471 тг 2 ком.- 850471 тг 3 ком.- 841306 тг 4 ком.- 830036 тг 5 ком.- 890458 тг. | N26: да, 1 ком.- 850471 тг 2 ком.- 850471 тг 3 ком.- 841306 тг 4 ком.- 830036 тг 5 ком.- 890458 тг. | O26: да, 1 ком.- 850471 тг 2 ком.- 850471 тг 3 ком.- 841306 тг 4 ком.- 830036 тг 5 ком.- 890458 тг. | R26: да
A27: Астана | B27: Atlant - 6 - 2 | C27: жилые | F27: =VLOOKUP(B27,[3]Лист_1!$A:$E,5,0) -> 20 | G27: ДДУ | L27: да | M27: да | P27: да | Q27: да | W27: да 36 | Y27: да | AD27: да
A28: Астана | B28: Atlant Unique - 5 | C28: жилые | F28: =VLOOKUP(B28,[3]Лист_1!$A:$E,5,0) -> 11 | G28: ДДУ | L28: да | M28: да | P28: да | Q28: да | S28: да | W28: да 36 | Y28: да, max 1 118 750 тенге за 1 кв.м. | Z28: да, max 1 118 750 тенге за 1 кв.м. | AA28: да, max 1 118 750 тенге за 1 кв.м. | AD28: да | AE28: да
A29: Астана | B29: Arena City - 2 | C29: жилые | F29: =VLOOKUP(B29,[3]Лист_1!$A:$E,5,0) -> 0 | G29: ПД | I29: да, max 620 000 тенге за 1 кв.м. | O29: да, max 620 000 тенге за 1 кв.м. | P29: да офлайн | R29: да | W29: да 36 | AD29: да | AE29: да | AF29: да
A30: Алматы | B30: Arena City Balance - A | C30: жилые | F30: 78 | G30: ДДУ | L30: да | M30: да | Q30: да | W30: да 36 | Y30: да | AD30: да
A31: Алматы | B31: Arena City Balance - B | C31: жилые | F31: =VLOOKUP(B31,[3]Лист_1!$A:$E,5,0) -> 175 | G31: ДДУ | L31: да | M31: да | P31: да | Q31: да | S31: да | W31: да 36 | Y31: да | AD31: да
A32: Алматы | B32: Arena City Balance - B Big+ | C32: жилые | F32: 0 | G32: ДДУ | P32: да | W32: да 36
A33: Астана | B33: Arena Garden 1-1 | C33: жилые | F33: =VLOOKUP(B33,[3]Лист_1!$A:$E,5,0) -> 0 | G33: ПД | I33: да, 1 ком.- 590850 тг 2 ком.- 569790 тг 3 ком.- 525330 тг | O33: да, 1 ком.- 590850 тг 2 ком.- 569790 тг 3 ком.- 525330 тг | P33: да офлайн | R33: да | W33: да 36 | AD33: да | AE33: да | AF33: да
A34: Астана | B34: Arena Garden 1-2 | C34: жилые | F34: =VLOOKUP(B34,[3]Лист_1!$A:$E,5,0) -> 0 | G34: ДДУ | L34: да | M34: да | P34: да | Q34: да | S34: да | W34: да 36 | Y34: да, max 650 000 тенге за 1 кв.м. | Z34: да, max 650 000 тенге за 1 кв.м. | AA34: да, max 650 000 тенге за 1 кв.м. | AD34: да | AE34: да
A35: Астана | B35: Arena Towers 2 - 2 | C35: жилые | F35: =VLOOKUP(B35,[3]Лист_1!$A:$E,5,0) -> 3 | G35: ДДУ | L35: да | M35: да | P35: да | Q35: да | W35: да 36 | Y35: да | AD35: да | AE35: да
A36: Астана | B36: Auez Comfort - 1 | C36: жилые | F36: =VLOOKUP(B36,[3]Лист_1!$A:$E,5,0) -> 13 | G36: ДДУ | L36: да | M36: да | P36: да | Q36: да | S36: да | W36: да 36 | Y36: да, max 850 000 тенге за 1 кв.м. | Z36: да, max 850 000 тенге за 1 кв.м. | AA36: да, max 850 000 тенге за 1 кв.м. | AB36: да | AD36: да
A37: Астана | B37: Auez Comfort - 2 | C37: жилые | F37: =VLOOKUP(B37,[3]Лист_1!$A:$E,5,0) -> 14 | G37: ДДУ | L37: да | M37: да | P37: да | Q37: да | S37: да | W37: да 36 | Y37: да, max 850 000 тенге за 1 кв.м. | AA37: да, max 850 000 тенге за 1 кв.м. | AD37: да
A38: Астана | B38: Auez Park | C38: жилые | F38: =VLOOKUP(B38,[3]Лист_1!$A:$E,5,0) -> 86 | G38: ДДУ | L38: да | M38: да | P38: да | Q38: да | S38: да | W38: да 36 | Y38: да | AB38: да | AD38: да
A39: Астана | B39: Darmen - 1 | C39: жилые | F39: =VLOOKUP(B39,[3]Лист_1!$A:$E,5,0) -> 35 | G39: P-S | AB39: да
A40: Астана | B40: GreenLine.Verda - 1 | C40: жилые | F40: =VLOOKUP(B40,[3]Лист_1!$A:$E,5,0) -> 82 | G40: ДДУ | L40: да | M40: да | P40: да | Q40: да | W40: да 36 | Y40: да, max 1 210 300 тенге за 1 кв.м. | AA40: да, max 1 210 300 тенге за 1 кв.м. | AB40: да | AD40: да
A41: Астана | B41: Arena Style - 1 | C41: жилые | F41: =VLOOKUP(B41,[3]Лист_1!$A:$E,5,0) -> 7 | G41: ДДУ | L41: да | M41: да | P41: да | Q41: да | W41: да 36 | Y41: да | AB41: да | AD41: да
A42: Астана | B42: Arena Lite - 1 | C42: жилые | F42: =VLOOKUP(B42,[3]Лист_1!$A:$E,5,0) -> 0 | G42: ПД | P42: да офлайн | R42: да | AD42: да | AF42: да
A43: Астана | B43: Arena Lite - ЧО | C43: жилые | F43: =VLOOKUP(B43,[3]Лист_1!$A:$E,5,0) -> 0 | G43: ПД | P43: да офлайн | R43: да | AD43: да | AF43: да
A44: Астана | B44: Arena Unity - 1 | C44: жилые | D44: 312 | E44: ДДУ | F44: =VLOOKUP(B44,[3]Лист_1!$A:$E,5,0) -> 3 | G44: ДДУ | L44: да | M44: да | P44: да | Q44: да | S44: да | W44: да 36 | Y44: да | AD44: да | AE44: да
A45: Астана | B45: Arena Unity - 2 | C45: жилые | D45: 312 | E45: ДДУ | F45: =VLOOKUP(B45,[3]Лист_1!$A:$E,5,0) -> 16 | G45: ДДУ | L45: да | M45: да | P45: да | Q45: да | S45: да | W45: да 36 | Y45: да, max 840 000 тенге за 1 кв.м. | AA45: да, max 840 000 тенге за 1 кв.м. | AD45: да
A46: Астана | B46: AQJUREK - 1 подъезд 1, 4 | C46: жилые | D46: 312 | E46: ДДУ | F46: 0 | G46: P-S | AB46: да
A47: Астана | B47: AQJUREK - 1 - ЧО | C47: жилые | D47: 312 | E47: ДДУ | F47: 0 | G47: P-S | AB47: да
A48: Астана | B48: Family Gardens | C48: жилые | D48: 312 | E48: ДДУ | F48: =VLOOKUP(B48,[3]Лист_1!$A:$E,5,0) -> 71 | G48: ДДУ | L48: да | M48: да | Q48: да | S48: да | W48: да 36 | Y48: да | AB48: да | AD48: да
A49: Астана | B49: PARKLAND - 1 - 2 | C49: жилые | F49: =VLOOKUP(B49,[3]Лист_1!$A:$E,5,0) -> 8 | G49: ДДУ | L49: да | M49: да | P49: да | Q49: да | S49: да | W49: да 36 | Y49: да | AD49: да
A50: Астана | B50: PARKLAND - 1 -2 - ЧО | C50: жилые | F50: =VLOOKUP(B50,[3]Лист_1!$A:$E,5,0) -> 3 | G50: ДДУ | L50: да | M50: да | P50: да | Q50: да | S50: да | W50: да 36 | Y50: да | AD50: да
A51: Астана | B51: PARKLAND - 1 4, 6 подъезд | C51: жилые | F51: =VLOOKUP(B51,[3]Лист_1!$A:$E,5,0) -> 5 | G51: ДДУ | L51: да | M51: да | P51: да | Q51: да | S51: да | W51: да 36 | Y51: да | AB51: да | AD51: да
A52: Астана | B52: PARKLAND - 1 - ЧО | C52: жилые | F52: =VLOOKUP(B52,[3]Лист_1!$A:$E,5,0) -> 9 | G52: ДДУ | L52: да | M52: да | P52: да | Q52: да | S52: да | W52: да 36 | Y52: да | AB52: да | AD52: да
A53: Астана | B53: PARKLAND 2 | C53: жилые | F53: =VLOOKUP(B53,[3]Лист_1!$A:$E,5,0) -> 10 | G53: ДДУ | L53: да | M53: да | P53: да | Q53: да | S53: да | W53: да 36 | Y53: да | AB53: да | AD53: да
A54: Астана | B54: PARKLAND 2 - ЧО | C54: жилые | F54: =VLOOKUP(B54,[3]Лист_1!$A:$E,5,0) -> 9 | G54: ДДУ | L54: да | M54: да | P54: да | Q54: да | S54: да | W54: да 36 | Y54: да | AB54: да | AD54: да
A55: Астана | B55: Space 1 - 1 | C55: жилые | F55: =VLOOKUP(B55,[3]Лист_1!$A:$E,5,0) -> 4 | G55: ДДУ | L55: да | M55: да | P55: да | Q55: да | W55: да 36 | Y55: да | AB55: да | AD55: да
A56: Астана | B56: Space 1 - 1 - ЧО | C56: жилые | F56: =VLOOKUP(B56,[3]Лист_1!$A:$E,5,0) -> 2 | G56: ДДУ | L56: да | M56: да | P56: да | Q56: да | W56: да 36 | Y56: да | AB56: да | AD56: да
A57: Астана | B57: Space 1 - 2 - ЧО | C57: жилые | F57: =VLOOKUP(B57,[3]Лист_1!$A:$E,5,0) -> 1 | G57: ДДУ | L57: да | M57: да | P57: да | Q57: да | W57: да 36 | Y57: да | AD57: да
A58: Астана | B58: Space 1 - 3 | C58: жилые | F58: =VLOOKUP(B58,[3]Лист_1!$A:$E,5,0) -> 3 | G58: ДДУ | L58: да | M58: да | P58: да | Q58: да | W58: да 36 | Y58: да | AD58: да
A59: Астана | B59: Space PLUS | C59: жилые | F59: =VLOOKUP(B59,[3]Лист_1!$A:$E,5,0) -> 16 | G59: ДДУ | L59: да | M59: да | P59: да | Q59: да | S59: да | T59: да | W59: да 36 | Y59: да | AD59: да
A60: Астана | B60: Space PLUS - ЧО | C60: жилые | F60: =VLOOKUP(B60,[3]Лист_1!$A:$E,5,0) -> 2 | G60: ДДУ | L60: да | M60: да | P60: да | Q60: да | S60: да | T60: да | W60: да 36 | Y60: да | AD60: да
A61: Астана | B61: Abyroi | C61: жилые | D61: 73b334c6-9ac3-11ec-a820-001dd8b72708 | F61: =VLOOKUP(B61,[3]Лист_1!$A:$E,5,0) -> 53 | G61: ДДУ | L61: да | M61: да | P61: да | Q61: да | W61: да 36 | Y61: да | AB61: да | AD61: да
A62: Астана | B62: Capital Park. Light 3B - 1 | C62: жилые | F62: =VLOOKUP(B62,[3]Лист_1!$A:$E,5,0) -> 0 | G62: ПД | I62: да, 1 ком.- 680500 тг 2 ком.- 762450 тг 3 ком.- 658950 тг 4 ком.- 709550 тг | J62: да | K62: да 630 000 тг - 1 ком; 560 000 тг - 2 ком; 540 000 тг - 3 ком; | N62: да, 1 ком.- 680500 тг 2 ком.- 762450 тг 3 ком.- 658950 тг 4 ком.- 709550 тг | O62: да, 1 ком.- 680500 тг 2 ком.- 762450 тг 3 ком.- 658950 тг 4 ком.- 709550 тг | P62: да офлайн | R62: да | AD62: да | AE62: да | AF62: да
A63: Астана | B63: Capital Park. Light 3B - 2 | C63: жилые | F63: =VLOOKUP(B63,[3]Лист_1!$A:$E,5,0) -> 0 | G63: ПД | I63: да, max 662 000 тг - 1 ком; 672 000 тг - 2 ком; 799 250 тг - 3 ком; 765 900 тг - 4 ком. | O63: да, max 662 000 тг - 1 ком; 672 000 тг - 2 ком; 799 250 тг - 3 ком; 765 900 тг - 4 ком. | P63: да офлайн | R63: да | AD63: да | AE63: да | AF63: да
A64: Астана | B64: Capital Park Emotions - 1 | C64: жилые | F64: =VLOOKUP(B64,[3]Лист_1!$A:$E,5,0) -> 6 | G64: ДДУ | L64: да | M64: да | Q64: да | S64: да | W64: да 36 | Y64: да | AD64: да | AE64: да
A65: Астана | B65: Capital Park Emotions - 2 | C65: жилые | F65: =VLOOKUP(B65,[3]Лист_1!$A:$E,5,0) -> 21 | G65: ДДУ | L65: да | M65: да | Q65: да | S65: да | W65: да 36 | Y65: да, max 850 000 тенге за 1 кв.м. | Z65: да, max 850 000 тенге за 1 кв.м. | AA65: да, max 850 000 тенге за 1 кв.м. | AD65: да
A66: Астана | B66: Capital Park Emotions - 2 - ЧО | C66: жилые | F66: 0 | G66: ДДУ | L66: да | M66: да | Q66: да | S66: да | W66: да 36 | Y66: да, max 850 000 тенге за 1 кв.м. | Z66: да, max 850 000 тенге за 1 кв.м. | AA66: да, max 850 000 тенге за 1 кв.м. | AD66: да
A67: Астана | B67: Capital Park Melody - 1 | C67: жилые | F67: =VLOOKUP(B67,[3]Лист_1!$A:$E,5,0) -> 66 | G67: ДДУ | L67: да | M67: да | P67: да | Q67: да | S67: да | W67: да 36 | Y67: да | AD67: да
A68: Астана | B68: Capital Park Melody - 1 - ЧО | C68: жилые | F68: 0 | G68: ДДУ | L68: да | M68: да | P68: да | Q68: да | S68: да | W68: да 36 | Y68: да | AD68: да
A69: Астана | B69: Capital Park. Sky | C69: жилые | F69: =VLOOKUP(B69,[3]Лист_1!$A:$E,5,0) -> 2 | G69: ДДУ | L69: да | M69: да | Q69: да | S69: да | W69: да 36 | Y69: да | AD69: да | AE69: да
A70: Астана | B70: Capital Park Art - 1 | C70: жилые | F70: =VLOOKUP(B70,[3]Лист_1!$A:$E,5,0) -> 122 | G70: ДДУ | L70: да | M70: да | P70: да | Q70: да | S70: да | W70: да 36 | Y70: да | AD70: да
A71: Астана | B71: Capital Park Art - 2 | C71: жилые | F71: =VLOOKUP(B71,[3]Лист_1!$A:$E,5,0) -> 162 | G71: ДДУ | L71: да | M71: да | P71: да | Q71: да | S71: да | W71: да 36 | Y71: да | AD71: да
A72: Астана | B72: Capital Park Art - 2-ЧО | C72: жилые | F72: 0 | G72: ДДУ | L72: да | M72: да | Q72: да | S72: да | W72: да 36 | Y72: да | AD72: да
A73: Астана | B73: GreenLine.4YOU - 1 | C73: жилые | F73: =VLOOKUP(B73,[3]Лист_1!$A:$E,5,0) -> 44 | G73: ДДУ | L73: да | M73: да | P73: да | Q73: да | S73: да | W73: да 36 | Y73: да, max 1 271 400 тенге за 1 кв.м. | Z73: да, max 850 000 тенге за 1 кв.м. | AA73: да, max 1 271 400 тенге за 1 кв.м. | AD73: да
A74: Астана | B74: GreenLine 4YOU - 2 | C74: жилые | F74: =VLOOKUP(B74,[3]Лист_1!$A:$E,5,0) -> 98 | G74: ДДУ | I74: да, 2 ком.- 788 100 тг 3 ком.- 689 500 тг 4 ком.- 689 300 тг | L74: да | M74: да | P74: да | Q74: да | W74: да 36 | Y74: да, max 1 209 000 тенге за 1 кв.м. | Z74: да, max 850 000 тенге за 1 кв.м. | AA74: да, max 1 209 000 тенге за 1 кв.м. | AD74: да
A75: Астана | B75: GreenLine.Flora - 2 | C75: жилые | F75: =VLOOKUP(B75,[3]Лист_1!$A:$E,5,0) -> 0 | G75: ПД | P75: да офлайн | R75: да | AD75: да | AE75: да | AF75: да
A76: Астана | B76: GreenLine.Garden 1 - 1 | C76: жилые | F76: =VLOOKUP(B76,[3]Лист_1!$A:$E,5,0) -> 48 | G76: ДДУ | I76: да, 1 ком.- 737 900 тг 2 ком.- 724 900 тг 3 ком.- 640 500 тг 4 ком.- 636 000 тг | L76: да | M76: да | P76: да | Q76: да | S76: да | W76: да 36 | Y76: да | AA76: да, max 1 099 800 тенге за 1 кв.м. | AD76: да
A77: Астана | B77: GreenLine.Garden 1-2 | C77: жилые | F77: =VLOOKUP(B77,[3]Лист_1!$A:$E,5,0) -> 128 | G77: ДДУ | L77: да | M77: да | P77: да | Q77: да | S77: да | W77: да 36 | Y77: да | AA77: да | AD77: да
A78: Астана | B78: GreenLine.Headliner Exclusive - 2 | C78: жилые | F78: =VLOOKUP(B78,[3]Лист_1!$A:$E,5,0) -> 24 | G78: ДДУ | L78: да | M78: да | P78: да | Q78: да | S78: да | W78: да 36 | Y78: да | AD78: да
A79: Астана | B79: GreenLine.Headliner Exclusive - 1 | C79: жилые | F79: =VLOOKUP(B79,[3]Лист_1!$A:$E,5,0) -> 1 | G79: ПД | I79: да, 1 ком.- 834325 тг 2 ком.- 825700 тг 3 ком.- 794650 тг 4 ком.- 771650 тг | N79: да, 1 ком.- 834325 тг 2 ком.- 825700 тг 3 ком.- 794650 тг 4 ком.- 771650 тг | O79: да, 1 ком.- 834325 тг 2 ком.- 825700 тг 3 ком.- 794650 тг 4 ком.- 771650 тг | P79: да офлайн | R79: да | AD79: да | AE79: да | AF79: да
A80: Астана | B80: GreenLine.Headliner Exclusive - 3 | C80: жилые | F80: =VLOOKUP(B80,[3]Лист_1!$A:$E,5,0) -> 0 | G80: ПД | I80: да | R80: да | AD80: да | AE80: да | AF80: да
A81: Астана | B81: GreenLine. Astra 1-1 | C81: жилые | F81: =VLOOKUP(B81,[3]Лист_1!$A:$E,5,0) -> 0 | G81: ДДУ | L81: да | M81: да | P81: да | Q81: да | S81: да | Y81: да | AD81: да | AE81: да
A82: Астана | B82: GreenLine. Astra 1-2 | C82: жилые | F82: =VLOOKUP(B82,[3]Лист_1!$A:$E,5,0) -> 0 | G82: ДДУ | L82: да | M82: да | P82: да | Q82: да | S82: да | Y82: да | AD82: да | AE82: да
A83: Астана | B83: GreenLine.Silva - 1 | C83: жилые | F83: =VLOOKUP(B83,[3]Лист_1!$A:$E,5,0) -> 0 | G83: ПД | P83: да офлайн | R83: да | AD83: да | AE83: да | AF83: да
A84: Астана | B84: GreenLine.Sakura - 1 | C84: жилые | F84: =VLOOKUP(B84,[3]Лист_1!$A:$E,5,0) -> 9 | G84: ДДУ | L84: да | M84: да | P84: да | Q84: да | W84: да 36 | Y84: да | AD84: да
A85: Астана | B85: GreenLine.Aurora - 1 | C85: жилые | F85: =VLOOKUP(B85,[3]Лист_1!$A:$E,5,0) -> 5 | G85: ДДУ | L85: да | M85: да | P85: да | Q85: да | S85: да | W85: да 36 | Y85: да, max 1 092 000 тенге за 1 кв.м. | Z85: да, max 1 209 000 тенге за 1 кв.м. | AA85: да, max 1 092 000 тенге за 1 кв.м. | AD85: да
A86: Астана | B86: GreenLine.Aurora - 2 | C86: жилые | F86: =VLOOKUP(B86,[3]Лист_1!$A:$E,5,0) -> 57 | G86: ДДУ | L86: да | M86: да | P86: да | Q86: да | S86: да | W86: да 36 | Y86: да | AD86: да
A87: Шымкент | B87: Grand Park Vita 1 | C87: жилые | F87: =VLOOKUP(B87,[3]Лист_1!$A:$E,5,0) -> 55 | G87: ДДУ | L87: да | M87: да | P87: да | Q87: да | S87: да | W87: да 36 | Y87: да | AA87: да, max 648 000 тенге за 1 кв.м. | AD87: да
A88: Шымкент | B88: Grand Park Vita - чистовая отделка | C88: жилые | F88: =VLOOKUP(B88,[3]Лист_1!$A:$E,5,0) -> 6 | G88: ДДУ | L88: да | M88: да | P88: да | Q88: да | S88: да | W88: да 36 | Y88: да | AA88: да, max 774 000 тенге за 1 кв.м. | AD88: да
A89: Астана | B89: GreenLine.Velora | C89: жилые | F89: =VLOOKUP(B89,[3]Лист_1!$A:$E,5,0) -> 147 | G89: ДДУ | L89: да | M89: да | P89: да | Q89: да | S89: да | W89: да 36 | Y89: да | AD89: да
A90: Астана | B90: Qasteev - 2 | C90: жилые | F90: =VLOOKUP(B90,[3]Лист_1!$A:$E,5,0) -> 47 | G90: ДДУ | L90: да | M90: да | P90: да | Q90: да | S90: да | W90: да 36 | Y90: да | AD90: да
A91: Астана | B91: Qasteev - 1 | C91: жилые | F91: 0 | G91: ДДУ | L91: да | M91: да | Q91: да | S91: да | W91: да 36 | Y91: да | AB91: да | AD91: да
A92: Астана | B92: UIA. DARYN-B | C92: жилые | F92: =VLOOKUP(B92,[3]Лист_1!$A:$E,5,0) -> 4 | G92: ДДУ | L92: да | M92: да | P92: да | Q92: да | S92: да | W92: да 36 | Y92: да | AD92: да
A93: Астана | B93: UIA. DARYN-B - ЧО | C93: жилые | F93: =VLOOKUP(B93,[3]Лист_1!$A:$E,5,0) -> 0 | G93: ДДУ | L93: да | M93: да | P93: да | Q93: да | S93: да | W93: да 36 | Y93: да | AD93: да
A94: Астана | B94: UIA.DARYN - D | C94: жилые | F94: =VLOOKUP(B94,[3]Лист_1!$A:$E,5,0) -> 65 | G94: ДДУ | L94: да | M94: да | P94: да | Q94: да | S94: да | W94: да 36 | Y94: да | AD94: да
A95: Астана | B95: UIA. DARYN-D - ЧО | C95: жилые | F95: 0 | G95: ДДУ | L95: да | M95: да | P95: да | Q95: да | S95: да | W95: да 36 | Y95: да | AD95: да
A96: Астана | B96: IZBASAR | C96: жилые | F96: =VLOOKUP(B96,[3]Лист_1!$A:$E,5,0) -> 66 | G96: ДДУ | L96: да | M96: да | P96: да | Q96: да | S96: да | W96: да 36 | Y96: да | AD96: да
A97: Астана | B97: Jetisu Nauryz | C97: жилые | F97: =VLOOKUP(B97,[3]Лист_1!$A:$E,5,0) -> 20 | G97: ДДУ | L97: да | M97: да | P97: да | Q97: да | S97: да | W97: да 36 | Y97: да | AD97: да
A98: Астана | B98: Nexpo Trend 1 - 1 | C98: жилые | F98: =VLOOKUP(B98,[3]Лист_1!$A:$E,5,0) -> 0 | G98: ПД | I98: да, 2 ком.- 772800 тг 3 ком.- 738300 тг 4 ком.- 606050 тг | O98: да, 2 ком.- 772800 тг 3 ком.- 738300 тг 4 ком.- 606050 тг | P98: да офлайн | R98: да | AD98: да
A99: Астана | B99: Nexpo Trend - 2 | C99: жилые | F99: =VLOOKUP(B99,[3]Лист_1!$A:$E,5,0) -> 8 | G99: ДДУ | L99: да | M99: да | P99: да | Q99: да | S99: да | Y99: да max 900 000 тг за 1 кв.м. | Z99: да max 900 000 тг за 1 кв.м. | AA99: да max 900 000 тг за 1 кв.м. | AD99: да | AE99: да
A100: Астана | B100: Nexpo Classic - 2 | C100: жилые | D100: жилые | E100: жилые | F100: =VLOOKUP(B100,[3]Лист_1!$A:$E,5,0) -> 0 | G100: ПД | I100: да, 1 ком.- 768200 тг 2 ком.- 759575 тг 3 ком.- 750375 тг 4 ком.- 612950 тг | N100: да, 1 ком.- 768200 тг 2 ком.- 759575 тг 3 ком.- 750375 тг 4 ком.- 612950 тг | O100: да, 1 ком.- 768200 тг 2 ком.- 759575 тг 3 ком.- 750375 тг 4 ком.- 612950 тг | R100: да | AD100: да | AF100: да
...

Sheet Калькулятор для ОП
A1: С подтверждением дохода | F1: Отбасы Банк
B2: БЦК | C2: Алтын | D2: Фридом | E2: Халык | F2: 30/70 | H2: 50/50
A3: Стоимость недвижимости | B3: 25973880
A4: Стоимость в ипотеку | B4: =B3*1.05 -> 27272574 | C4: =B3*1.05 -> 27272574 | D4: =B3*1.05 -> 27272574 | E4: =B3*1.05 -> 27272574 | F4: =B3*1.05 -> 27272574 | H4: =B3 -> 25973880
A5: Первоначальный взнос, % | B5: 0.21 | F5: 0.3 | H5: 0.5
A6: Первоначальный взнос в тенге | B6: =B4*$B$5 -> 5727240.5 | C6: =C4*$B$5 -> 5727240.5 | D6: =D4*$B$5 -> 5727240.5 | E6: =E4*$B$5 -> 5727240.5 | F6: =F5*F4 -> 8181772.2 | H6: =H5*H4 -> 12986940
A7: Сумма Займа | B7: =B4-B6 -> 21545333 | C7: =C4-C6 -> 21545333 | D7: =D4-D6 -> 21545333 | E7: =E4-E6 -> 21545333 | F7: =F4-F6 -> 19090802 | H7: =H4-H6 -> 12986940
A8: Срок кредита | B8: 35 | C8: 35 | D8: 120 | E8: 120 | F8: ="первые "& '[2]Sheet 1'!$B$15 &" года" -> первые 3 года | G8: ="оставшиеся "& '[2]Sheet 1'!$B$16 &" лет" -> оставшиеся 9 лет | H8: ="первые "& '[2]Sheet 1'!$B$15 &" года" -> первые 3 года | I8: ="оставшиеся "& '[2]Sheet 1'!$B$16 &" лет" -> оставшиеся 9 лет
A9: Ставка вознагражд годовая | B9: =IF(B8<=12, IF(B5>=70%,'БЦК - Super ипотека'!D24, IF(B5>=50%,'БЦК - Super ипотека'!C24, IF(B5>=20%,'БЦК - Super ипотека'!B24,""))), IF(B8<=24, IF(B5>=70%,'БЦК - Super ипотека'!D25, IF(B5>=50%,'БЦК - Super ипотека'!C25, IF(B5>=20%,'БЦК - Super ипотека'!B25,""))), IF(B8<=36, IF(B5>=70%,'БЦК - Super ипотека'!D26, IF(B5>=50%,'БЦК - Super ипотека'!C26, IF(B5>=20%,'БЦК - Super ипотека'!B26,""))), IF(B8<=60, IF(B5>=70%,'БЦК - Super ипотека'!D27, IF(B5>=50%,'БЦК - Super ипотека'!C27, IF(B5>=20%,'БЦК - Super ипотека'!B27,""))), IF(B8<=120, IF(B5>=70%,'БЦК - Super ипотека'!D28, IF(B5>=50%,'БЦК - Super ипотека'!C28, IF(B5>=20%,'БЦК - Super ипотека'!B28,""))), IF(B8<=180, IF(B5>=70%,'БЦК - Super ипотека'!D29, IF(B5>=50%,'БЦК - Super ипотека'!C29, IF(B5>=20%,'БЦК - Super ипотека'!B29,""))))))))) -> 0.115 | C9: =(IF(C8<=12, IF(B5<20%,'Алтын Банк - Онай'!B24, IF(B5<30%,'Алтын Банк - Онай'!C24, IF(B5<40%,'Алтын Банк - Онай'!C24, IF(B5<50%,'Алтын Банк - Онай'!C24, IF(B5<60%,'Алтын Банк - Онай'!C24,'Алтын Банк - Онай'!C24))))), IF(C8<=24, IF(B5<20%,'Алтын Банк - Онай'!C25, IF(B5<30%,'Алтын Банк - Онай'!C25, IF(B5<40%,'Алтын Банк - Онай'!D25, IF(B5<50%,'Алтын Банк - Онай'!E25, IF(B5<60%,'Алтын Банк - Онай'!F25,'Алтын Банк - Онай'!G25))))), IF(C8<=36, IF(B5<20%,'Алтын Банк - Онай'!B26, IF(B5<30%,'Алтын Банк - Онай'!C26, IF(B5<40%,'Алтын Банк - Онай'!D26, IF(B5<50%,'Алтын Банк - Онай'!E26, IF(B5<60%,'Алтын Банк - Онай'!F26,'Алтын Банк - Онай'!G26))))), IF(C8<=60, IF(B5<20%,'Алтын Банк - Онай'!B27, IF(B5<30%,'Алтын Банк - Онай'!C27, IF(B5<40%,'Алтын Банк - Онай'!D27, IF(B5<50%,'Алтын Банк - Онай'!E27, IF(B5<60%,'Алтын Банк - Онай'!F27,'Алтын Банк - Онай'!G27))))), IF(C8<=120, IF(B5<20%,'Алтын Банк - Онай'!B28, IF(B5<30%,'Алтын Банк - Онай'!C28, IF(B5<40%,'Алтын Банк - Онай'!D28, IF(B5<50%,'Алтын Банк - Онай'!E28, IF(B5<60%,'Алтын Банк - Онай'!F28,'Алтын Банк - Онай'!G28))))), IF(C8<=180, IF(B5<20%,'Алтын Банк - Онай'!B29, IF(B5<30%,'Алтын Банк - Онай'!C29, IF(B5<40%,'Алтын Банк - Онай'!D29, IF(B5<50%,'Алтын Банк - Онай'!E29, IF(B5<60%,'Алтын Банк - Онай'!F29,'Алтын Банк - Онай'!G29))))), IF(C8<=240, IF(B5<20%,'Алтын Банк - Онай'!B30, IF(B5<30%,'Алтын Банк - Онай'!C30, IF(B5<40%,'Алтын Банк - Онай'!D30, IF(B5<50%,'Алтын Банк - Онай'!E30, IF(B5<60%,'Алтын Банк - Онай'!F30,'Алтын Банк - Онай'!G30)))))))))))))*1% -> 0.12 | D9: =(IF(D8<=12, IF(B5<30%,'ФридБанк ДДУ'!G23, IF(B5<40%,'ФридБанк ДДУ'!F23, IF(B5<50%,'ФридБанк ДДУ'!E23, IF(B5<60%,'ФридБанк ДДУ'!D23, IF(B5<70%,'ФридБанк ДДУ'!C23,'ФридБанк ДДУ'!B23))))), IF(D8<=24, IF(B5<30%,'ФридБанк ДДУ'!G24, IF(B5<40%,'ФридБанк ДДУ'!F24, IF(B5<50%,'ФридБанк ДДУ'!E24, IF(B5<60%,'ФридБанк ДДУ'!D24, IF(B5<70%,'ФридБанк ДДУ'!C24,'ФридБанк ДДУ'!B24))))), IF(D8<=36, IF(B5<30%,'ФридБанк ДДУ'!G25, IF(B5<40%,'ФридБанк ДДУ'!F25, IF(B5<50%,'ФридБанк ДДУ'!E25, IF(B5<60%,'ФридБанк ДДУ'!D25, IF(B5<70%,'ФридБанк ДДУ'!C25,'ФридБанк ДДУ'!B25))))), IF(D8<=60, IF(B5<30%,'ФридБанк ДДУ'!G26, IF(B5<40%,'ФридБанк ДДУ'!F26, IF(B5<50%,'ФридБанк ДДУ'!E26, IF(B5<60%,'ФридБанк ДДУ'!D26, IF(B5<70%,'ФридБанк ДДУ'!C26,'ФридБанк ДДУ'!B26))))), IF(D8<=120, IF(B5<30%,'ФридБанк ДДУ'!G27, IF(B5<40%,'ФридБанк ДДУ'!F27, IF(B5<50%,'ФридБанк ДДУ'!E27, IF(B5<60%,'ФридБанк ДДУ'!D27, IF(B5<70%,'ФридБанк ДДУ'!C27,'ФридБанк ДДУ'!B27))))), IF(D8<=180, IF(B5<30%,'ФридБанк ДДУ'!G28, IF(B5<40%,'ФридБанк ДДУ'!F28, IF(B5<50%,'ФридБанк ДДУ'!E28, IF(B5<60%,'ФридБанк ДДУ'!D28, IF(B5<70%,'ФридБанк ДДУ'!C28,'ФридБанк ДДУ'!B28))))), IF(D8<=240, IF(B5<30%,'ФридБанк ДДУ'!G30, IF(B5<40%,'ФридБанк ДДУ'!F29, IF(B5<50%,'ФридБанк ДДУ'!E29, IF(B5<60%,'ФридБанк ДДУ'!D29, IF(B5<70%,'ФридБанк ДДУ'!C29,'ФридБанк ДДУ'!B29)))))))))))))*1% -> 0.19 | E9: =IF(E8<=12, IF(B5>=50%,'Народный банк-Halyk ипотека'!C24,'Народный банк-Halyk ипотека'!B24), IF(E8<=24, IF(B5>=50%,'Народный банк-Halyk ипотека'!C25,'Народный банк-Halyk ипотека'!B25), IF(E8<=36, IF(B5>=50%,'Народный банк-Halyk ипотека'!C26,'Народный банк-Halyk ипотека'!B26), IF(E8<=60, IF(B5>=50%,'Народный банк-Halyk ипотека'!C27,'Народный банк-Halyk ипотека'!B27), IF(E8<=120, IF(B5>=50%,'Народный банк-Halyk ипотека'!C28,'Народный банк-Halyk ипотека'!B28), IF(E8<=180, IF(B5>=50%,'Народный банк-Halyk ипотека'!C29,'Народный банк-Halyk ипотека'!B29), IF(E8<=240, IF(B5>=50%,'Народный банк-Halyk ипотека'!C30,'Народный банк-Halyk ипотека'!B30)))))))) -> 0.17 | F9: 0.08 | G9: 0.042 | H9: 0.085 | I9: 0.042
A10: Ежемесячное погашение | B10: =IFERROR(ROUND(POWER((1+B9/12),B8)*B9/12/(POWER((1+B9/12),B8)-1)*B7,0)," ") -> 727497 | C10: =IFERROR(ROUND(POWER((1+C9/12),C8)*C9/12/(POWER((1+C9/12),C8)-1)*C7,0)," ") -> 732621 | D10: =IFERROR(ROUND(POWER((1+D9/12),D8)*D9/12/(POWER((1+D9/12),D8)-1)*D7,0)," ") -> 402192 | E10: =IFERROR(ROUND(POWER((1+E9/12),E8)*E9/12/(POWER((1+E9/12),E8)-1)*E7,0)," ") -> 374453 | F10: =F4*8%/12 + F4*20%*7%/12 -> 213635.16 | G10: =F4*0.56% + F4*20%*0.56% -> 183271.7 | H10: =H4*H9/12 -> 183981.65 | I10: =H4*0.56% -> 145453.73
A11: Переплата за весь срок | B11: =IFERROR(B10*B8-B7, " ") -> 3917061.5 | C11: =IFERROR(C10*C8-C7, " ") -> 4096401.5 | D11: =IFERROR(D10*D8-D7, " ") -> 26717707 | E11: =IFERROR(E10*E8-E7, " ") -> 23389027 | F11: =F10*'[2]Sheet 1'!$B$15*12+G10*'[2]Sheet 1'!$B$16*12-F7/2 -> 17938808 | H11: =H10*'[2]Sheet 1'!$B$15*12+I10*'[2]Sheet 1'!$B$16*12-H7/2 -> 15838872
A12: Комиссия за оформление МАХ сумма | B12: 0 | C12: 0 | D12: 30000 | E12: 0 | F12: 200000 | H12: 115000
A14: *Расчеты предоставлены приблизительно
A15: *По Отбасы Банку без учета накоплений и условий по депозиту

Sheet Калькулятор
C3: Сумма займа | E3: =#REF! -> #REF!
C4: Срок займа | E4: =#REF! -> #REF!
C5: сумма аннуитета | E5: =-PMT(E10%/12,E4,E3) -> #REF!
C6: Дата Выдачи | E6: 45047
C7: Ставки
C8: срок 1-3 | E8: =#REF! -> #REF!
C9: срок 4-5 | E9: =#REF! -> #REF!
C10: свыше 5 | E10: =#REF! -> #REF!
C11: ГЭСВ | E11: =XIRR(OFFSET(L15,0,0,E4+1,1),OFFSET(B15,0,0,E4+1,1)) -> #REF!
A14: № п/п/ № р/н | B14: Дата платежа/ Төлем күні | C14: Ежем. платеж | D14: Платеж | E14: ОД | F14: % | G14: % | H14: Остаток ОД | K14: % под новые ставки | L14: Новый еж.платеж
B15: 44953 | C15: =-E3 -> #REF! | D15: =-E3 -> #REF! | H15: =E3 -> #REF! | L15: =D15 -> #REF!
A16: 1 | B16: =DATE(YEAR(E6),MONTH(E6)+1,DAY(E6)) -> 45078 | C16: =L16 -> #REF! | D16: =E5 -> #REF! | E16: =D16-F16 -> #REF! | F16: =H15*$E$10%/12 -> #REF! | G16: =K16 -> #REF! | H16: =H15-E16 -> #REF! | J16: =$E$8 -> #REF! | K16: =H15*J16%/12 -> #REF! | L16: =E16+K16 -> #REF!
A17: 2 | B17: =DATE(YEAR(B16),MONTH(B16)+1,DAY(B16)) -> 45108 | C17: =L17 -> #REF! | D17: =D16 -> #REF! | E17: =D17-F17 -> #REF! | F17: =H16*$E$10%/12 -> #REF! | G17: =K17 -> #REF! | H17: =H16-E17 -> #REF! | J17: =$E$8 -> #REF! | K17: =H16*J17%/12 -> #REF! | L17: =E17+K17 -> #REF!
A18: 3 | B18: =DATE(YEAR(B17),MONTH(B17)+1,DAY(B17)) -> 45139 | C18: =L18 -> #REF! | D18: =D17 -> #REF! | E18: =D18-F18 -> #REF! | F18: =H17*$E$10%/12 -> #REF! | G18: =K18 -> #REF! | H18: =H17-E18 -> #REF! | J18: =$E$8 -> #REF! | K18: =H17*J18%/12 -> #REF! | L18: =E18+K18 -> #REF!
A19: 4 | B19: =DATE(YEAR(B18),MONTH(B18)+1,DAY(B18)) -> 45170 | C19: =L19 -> #REF! | D19: =D18 -> #REF! | E19: =D19-F19 -> #REF! | F19: =H18*$E$10%/12 -> #REF! | G19: =K19 -> #REF! | H19: =H18-E19 -> #REF! | J19: =$E$8 -> #REF! | K19: =H18*J19%/12 -> #REF! | L19: =E19+K19 -> #REF!
A20: 5 | B20: =DATE(YEAR(B19),MONTH(B19)+1,DAY(B19)) -> 45200 | C20: =L20 -> #REF! | D20: =D19 -> #REF! | E20: =D20-F20 -> #REF! | F20: =H19*$E$10%/12 -> #REF! | G20: =K20 -> #REF! | H20: =H19-E20 -> #REF! | J20: =$E$8 -> #REF! | K20: =H19*J20%/12 -> #REF! | L20: =E20+K20 -> #REF!
A21: 6 | B21: =DATE(YEAR(B20),MONTH(B20)+1,DAY(B20)) -> 45231 | C21: =L21 -> #REF! | D21: =D20 -> #REF! | E21: =D21-F21 -> #REF! | F21: =H20*$E$10%/12 -> #REF! | G21: =K21 -> #REF! | H21: =H20-E21 -> #REF! | J21: =$E$8 -> #REF! | K21: =H20*J21%/12 -> #REF! | L21: =E21+K21 -> #REF!
A22: 7 | B22: =DATE(YEAR(B21),MONTH(B21)+1,DAY(B21)) -> 45261 | C22: =L22 -> #REF! | D22: =D21 -> #REF! | E22: =D22-F22 -> #REF! | F22: =H21*$E$10%/12 -> #REF! | G22: =K22 -> #REF! | H22: =H21-E22 -> #REF! | J22: =$E$8 -> #REF! | K22: =H21*J22%/12 -> #REF! | L22: =E22+K22 -> #REF!
A23: 8 | B23: =DATE(YEAR(B22),MONTH(B22)+1,DAY(B22)) -> 45292 | C23: =L23 -> #REF! | D23: =D22 -> #REF! | E23: =D23-F23 -> #REF! | F23: =H22*$E$10%/12 -> #REF! | G23: =K23 -> #REF! | H23: =H22-E23 -> #REF! | J23: =$E$8 -> #REF! | K23: =H22*J23%/12 -> #REF! | L23: =E23+K23 -> #REF!
A24: 9 | B24: =DATE(YEAR(B23),MONTH(B23)+1,DAY(B23)) -> 45323 | C24: =L24 -> #REF! | D24: =D23 -> #REF! | E24: =D24-F24 -> #REF! | F24: =H23*$E$10%/12 -> #REF! | G24: =K24 -> #REF! | H24: =H23-E24 -> #REF! | J24: =$E$8 -> #REF! | K24: =H23*J24%/12 -> #REF! | L24: =E24+K24 -> #REF!
A25: 10 | B25: =DATE(YEAR(B24),MONTH(B24)+1,DAY(B24)) -> 45352 | C25: =L25 -> #REF! | D25: =D24 -> #REF! | E25: =D25-F25 -> #REF! | F25: =H24*$E$10%/12 -> #REF! | G25: =K25 -> #REF! | H25: =H24-E25 -> #REF! | J25: =$E$8 -> #REF! | K25: =H24*J25%/12 -> #REF! | L25: =E25+K25 -> #REF!
A26: 11 | B26: =DATE(YEAR(B25),MONTH(B25)+1,DAY(B25)) -> 45383 | C26: =L26 -> #REF! | D26: =D25 -> #REF! | E26: =D26-F26 -> #REF! | F26: =H25*$E$10%/12 -> #REF! | G26: =K26 -> #REF! | H26: =H25-E26 -> #REF! | J26: =$E$8 -> #REF! | K26: =H25*J26%/12 -> #REF! | L26: =E26+K26 -> #REF!
A27: 12 | B27: =DATE(YEAR(B26),MONTH(B26)+1,DAY(B26)) -> 45413 | C27: =L27 -> #REF! | D27: =D26 -> #REF! | E27: =D27-F27 -> #REF! | F27: =H26*$E$10%/12 -> #REF! | G27: =K27 -> #REF! | H27: =H26-E27 -> #REF! | J27: =$E$8 -> #REF! | K27: =H26*J27%/12 -> #REF! | L27: =E27+K27 -> #REF!
A28: 13 | B28: =DATE(YEAR(B27),MONTH(B27)+1,DAY(B27)) -> 45444 | C28: =L28 -> #REF! | D28: =D27 -> #REF! | E28: =D28-F28 -> #REF! | F28: =H27*$E$10%/12 -> #REF! | G28: =K28 -> #REF! | H28: =H27-E28 -> #REF! | J28: =$E$8 -> #REF! | K28: =H27*J28%/12 -> #REF! | L28: =E28+K28 -> #REF!
... A51: 36 | B51: =DATE(YEAR(B50),MONTH(B50)+1,DAY(B50)) -> 46143 | C51: =L51 -> #REF! | D51: =D50 -> #REF! | E51: =D51-F51 -> #REF! | F51: =H50*$E$10%/12 -> #REF! | G51: =K51 -> #REF! | H51: =H50-E51 -> #REF! | J51: =$E$8 -> #REF! | K51: =H50*J51%/12 -> #REF! | L51: =E51+K51 -> #REF!
A52: 37 | B52: =DATE(YEAR(B51),MONTH(B51)+1,DAY(B51)) -> 46174 | C52: =L52 -> #REF! | D52: =D51 -> #REF! | E52: =D52-F52 -> #REF! | F52: =H51*$E$10%/12 -> #REF! | G52: =K52 -> #REF! | H52: =H51-E52 -> #REF! | J52: =$E$9 -> #REF! | K52: =H51*J52%/12 -> #REF! | L52: =E52+K52 -> #REF!
A53: 38 | B53: =DATE(YEAR(B52),MONTH(B52)+1,DAY(B52)) -> 46204 | C53: =L53 -> #REF! | D53: =D52 -> #REF! | E53: =D53-F53 -> #REF! | F53: =H52*$E$10%/12 -> #REF! | G53: =K53 -> #REF! | H53: =H52-E53 -> #REF! | J53: =$E$9 -> #REF! | K53: =H52*J53%/12 -> #REF! | L53: =E53+K53 -> #REF!
A54: 39 | B54: =DATE(YEAR(B53),MONTH(B53)+1,DAY(B53)) -> 46235 | C54: =L54 -> #REF! | D54: =D53 -> #REF! | E54: =D54-F54 -> #REF! | F54: =H53*$E$10%/12 -> #REF! | G54: =K54 -> #REF! | H54: =H53-E54 -> #REF! | J54: =$E$9 -> #REF! | K54: =H53*J54%/12 -> #REF! | L54: =E54+K54 -> #REF!
A55: 40 | B55: =DATE(YEAR(B54),MONTH(B54)+1,DAY(B54)) -> 46266 | C55: =L55 -> #REF! | D55: =D54 -> #REF! | E55: =D55-F55 -> #REF! | F55: =H54*$E$10%/12 -> #REF! | G55: =K55 -> #REF! | H55: =H54-E55 -> #REF! | J55: =$E$9 -> #REF! | K55: =H54*J55%/12 -> #REF! | L55: =E55+K55 -> #REF!
A56: 41 | B56: =DATE(YEAR(B55),MONTH(B55)+1,DAY(B55)) -> 46296 | C56: =L56 -> #REF! | D56: =D55 -> #REF! | E56: =D56-F56 -> #REF! | F56: =H55*$E$10%/12 -> #REF! | G56: =K56 -> #REF! | H56: =H55-E56 -> #REF! | J56: =$E$9 -> #REF! | K56: =H55*J56%/12 -> #REF! | L56: =E56+K56 -> #REF!
A57: 42 | B57: =DATE(YEAR(B56),MONTH(B56)+1,DAY(B56)) -> 46327 | C57: =L57 -> #REF! | D57: =D56 -> #REF! | E57: =D57-F57 -> #REF! | F57: =H56*$E$10%/12 -> #REF! | G57: =K57 -> #REF! | H57: =H56-E57 -> #REF! | J57: =$E$9 -> #REF! | K57: =H56*J57%/12 -> #REF! | L57: =E57+K57 -> #REF!
A58: 43 | B58: =DATE(YEAR(B57),MONTH(B57)+1,DAY(B57)) -> 46357 | C58: =L58 -> #REF! | D58: =D57 -> #REF! | E58: =D58-F58 -> #REF! | F58: =H57*$E$10%/12 -> #REF! | G58: =K58 -> #REF! | H58: =H57-E58 -> #REF! | J58: =$E$9 -> #REF! | K58: =H57*J58%/12 -> #REF! | L58: =E58+K58 -> #REF!
A59: 44 | B59: =DATE(YEAR(B58),MONTH(B58)+1,DAY(B58)) -> 46388 | C59: =L59 -> #REF! | D59: =D58 -> #REF! | E59: =D59-F59 -> #REF! | F59: =H58*$E$10%/12 -> #REF! | G59: =K59 -> #REF! | H59: =H58-E59 -> #REF! | J59: =$E$9 -> #REF! | K59: =H58*J59%/12 -> #REF! | L59: =E59+K59 -> #REF!
A60: 45 | B60: =DATE(YEAR(B59),MONTH(B59)+1,DAY(B59)) -> 46419 | C60: =L60 -> #REF! | D60: =D59 -> #REF! | E60: =D60-F60 -> #REF! | F60: =H59*$E$10%/12 -> #REF! | G60: =K60 -> #REF! | H60: =H59-E60 -> #REF! | J60: =$E$9 -> #REF! | K60: =H59*J60%/12 -> #REF! | L60: =E60+K60 -> #REF!
A61: 46 | B61: =DATE(YEAR(B60),MONTH(B60)+1,DAY(B60)) -> 46447 | C61: =L61 -> #REF! | D61: =D60 -> #REF! | E61: =D61-F61 -> #REF! | F61: =H60*$E$10%/12 -> #REF! | G61: =K61 -> #REF! | H61: =H60-E61 -> #REF! | J61: =$E$9 -> #REF! | K61: =H60*J61%/12 -> #REF! | L61: =E61+K61 -> #REF!
A62: 47 | B62: =DATE(YEAR(B61),MONTH(B61)+1,DAY(B61)) -> 46478 | C62: =L62 -> #REF! | D62: =D61 -> #REF! | E62: =D62-F62 -> #REF! | F62: =H61*$E$10%/12 -> #REF! | G62: =K62 -> #REF! | H62: =H61-E62 -> #REF! | J62: =$E$9 -> #REF! | K62: =H61*J62%/12 -> #REF! | L62: =E62+K62 -> #REF!
A63: 48 | B63: =DATE(YEAR(B62),MONTH(B62)+1,DAY(B62)) -> 46508 | C63: =L63 -> #REF! | D63: =D62 -> #REF! | E63: =D63-F63 -> #REF! | F63: =H62*$E$10%/12 -> #REF! | G63: =K63 -> #REF! | H63: =H62-E63 -> #REF! | J63: =$E$9 -> #REF! | K63: =H62*J63%/12 -> #REF! | L63: =E63+K63 -> #REF!
... A75: 60 | B75: =DATE(YEAR(B74),MONTH(B74)+1,DAY(B74)) -> 46874 | C75: =L75 -> #REF! | D75: =D74 -> #REF! | E75: =D75-F75 -> #REF! | F75: =H74*$E$10%/12 -> #REF! | G75: =K75 -> #REF! | H75: =H74-E75 -> #REF! | J75: =$E$9 -> #REF! | K75: =H74*J75%/12 -> #REF! | L75: =E75+K75 -> #REF!
A76: 61 | B76: =DATE(YEAR(B75),MONTH(B75)+1,DAY(B75)) -> 46905 | C76: =L76 -> #REF! | D76: =D75 -> #REF! | E76: =D76-F76 -> #REF! | F76: =H75*$E$10%/12 -> #REF! | G76: =K76 -> #REF! | H76: =H75-E76 -> #REF! | J76: =$E$10 -> #REF! | K76: =H75*J76%/12 -> #REF! | L76: =E76+K76 -> #REF!
A77: 62 | B77: =DATE(YEAR(B76),MONTH(B76)+1,DAY(B76)) -> 46935 | C77: =L77 -> #REF! | D77: =D76 -> #REF! | E77: =D77-F77 -> #REF! | F77: =H76*$E$10%/12 -> #REF! | G77: =K77 -> #REF! | H77: =H76-E77 -> #REF! | J77: =$E$10 -> #REF! | K77: =H76*J77%/12 -> #REF! | L77: =E77+K77 -> #REF!
A78: 63 | B78: =DATE(YEAR(B77),MONTH(B77)+1,DAY(B77)) -> 46966 | C78: =L78 -> #REF! | D78: =D77 -> #REF! | E78: =D78-F78 -> #REF! | F78: =H77*$E$10%/12 -> #REF! | G78: =K78 -> #REF! | H78: =H77-E78 -> #REF! | J78: =$E$10 -> #REF! | K78: =H77*J78%/12 -> #REF! | L78: =E78+K78 -> #REF!
A79: 64 | B79: =DATE(YEAR(B78),MONTH(B78)+1,DAY(B78)) -> 46997 | C79: =L79 -> #REF! | D79: =D78 -> #REF! | E79: =D79-F79 -> #REF! | F79: =H78*$E$10%/12 -> #REF! | G79: =K79 -> #REF! | H79: =H78-E79 -> #REF! | J79: =$E$10 -> #REF! | K79: =H78*J79%/12 -> #REF! | L79: =E79+K79 -> #REF!
A80: 65 | B80: =DATE(YEAR(B79),MONTH(B79)+1,DAY(B79)) -> 47027 | C80: =L80 -> #REF! | D80: =D79 -> #REF! | E80: =D80-F80 -> #REF! | F80: =H79*$E$10%/12 -> #REF! | G80: =K80 -> #REF! | H80: =H79-E80 -> #REF! | J80: =$E$10 -> #REF! | K80: =H79*J80%/12 -> #REF! | L80: =E80+K80 -> #REF!
A81: 66 | B81: =DATE(YEAR(B80),MONTH(B80)+1,DAY(B80)) -> 47058 | C81: =L81 -> #REF! | D81: =D80 -> #REF! | E81: =D81-F81 -> #REF! | F81: =H80*$E$10%/12 -> #REF! | G81: =K81 -> #REF! | H81: =H80-E81 -> #REF! | J81: =$E$10 -> #REF! | K81: =H80*J81%/12 -> #REF! | L81: =E81+K81 -> #REF!
A82: 67 | B82: =DATE(YEAR(B81),MONTH(B81)+1,DAY(B81)) -> 47088 | C82: =L82 -> #REF! | D82: =D81 -> #REF! | E82: =D82-F82 -> #REF! | F82: =H81*$E$10%/12 -> #REF! | G82: =K82 -> #REF! | H82: =H81-E82 -> #REF! | J82: =$E$10 -> #REF! | K82: =H81*J82%/12 -> #REF! | L82: =E82+K82 -> #REF!
A83: 68 | B83: =DATE(YEAR(B82),MONTH(B82)+1,DAY(B82)) -> 47119 | C83: =L83 -> #REF! | D83: =D82 -> #REF! | E83: =D83-F83 -> #REF! | F83: =H82*$E$10%/12 -> #REF! | G83: =K83 -> #REF! | H83: =H82-E83 -> #REF! | J83: =$E$10 -> #REF! | K83: =H82*J83%/12 -> #REF! | L83: =E83+K83 -> #REF!
A84: 69 | B84: =DATE(YEAR(B83),MONTH(B83)+1,DAY(B83)) -> 47150 | C84: =L84 -> #REF! | D84: =D83 -> #REF! | E84: =D84-F84 -> #REF! | F84: =H83*$E$10%/12 -> #REF! | G84: =K84 -> #REF! | H84: =H83-E84 -> #REF! | J84: =$E$10 -> #REF! | K84: =H83*J84%/12 -> #REF! | L84: =E84+K84 -> #REF!
A85: 70 | B85: =DATE(YEAR(B84),MONTH(B84)+1,DAY(B84)) -> 47178 | C85: =L85 -> #REF! | D85: =D84 -> #REF! | E85: =D85-F85 -> #REF! | F85: =H84*$E$10%/12 -> #REF! | G85: =K85 -> #REF! | H85: =H84-E85 -> #REF! | J85: =$E$10 -> #REF! | K85: =H84*J85%/12 -> #REF! | L85: =E85+K85 -> #REF!
A86: 71 | B86: =DATE(YEAR(B85),MONTH(B85)+1,DAY(B85)) -> 47209 | C86: =L86 -> #REF! | D86: =D85 -> #REF! | E86: =D86-F86 -> #REF! | F86: =H85*$E$10%/12 -> #REF! | G86: =K86 -> #REF! | H86: =H85-E86 -> #REF! | J86: =$E$10 -> #REF! | K86: =H85*J86%/12 -> #REF! | L86: =E86+K86 -> #REF!
A87: 72 | B87: =DATE(YEAR(B86),MONTH(B86)+1,DAY(B86)) -> 47239 | C87: =L87 -> #REF! | D87: =D86 -> #REF! | E87: =D87-F87 -> #REF! | F87: =H86*$E$10%/12 -> #REF! | G87: =K87 -> #REF! | H87: =H86-E87 -> #REF! | J87: =$E$10 -> #REF! | K87: =H86*J87%/12 -> #REF! | L87: =E87+K87 -> #REF!
... A255: 240 | B255: =DATE(YEAR(B254),MONTH(B254)+1,DAY(B254)) -> 52352 | C255: =L255 -> #REF! | D255: =D254 -> #REF! | E255: =D255-F255 -> #REF! | F255: =H254*$E$10%/12 -> #REF! | G255: =K255 -> #REF! | H255: =H254-E255 -> #REF! | J255: =$E$10 -> #REF! | K255: =H254*J255%/12 -> #REF! | L255: =E255+K255 -> #REF!
A256: Итого/Барлығы: | D256: =SUM(D16:D255) -> #REF! | E256: =SUM(E16:E255) -> #REF! | F256: =SUM(F16:F255) -> #REF!
A259: Настоящим Заёмщик подтверждает, что Банк предложил ему производить погашение займа
A260: методами дифференцированных платежей или аннуитетных платежей.
A261: Заёмщик выбрал _____________(указать дифференцированный или аннуитетный) метод погашения суммы займа.
A262: Қарыз алушы осымен Банк оған қарызды дифференцирленген төлем немесе аннуитеттік төлем әдістерімен
A263: өтеу жүргізуді ұсынғанын растайды.
A264: Қарыз алушы қарыз сомасын өтеудің _____________ әдісін таңдады (дифференцирленген немесе аннуитеттік көрсету).
A267: Банк/Банк:
A269: __________________________
A270: АО «Банк Kassa Nova» (ДБ АО «ForteBank»)
A271: Курмангожин Алмаз Муратбекович
A274: м.п./м.о.

Sheet проекты Алтын
A2: Город | B2: Объекты | C2: Тип помещений | D2: Остатки на 18/08/2023 | E2: Вид основания | F2: Программа
F15: ё

Sheet БИЗНЕС ИПОТЕКА (Алтын банк)
B2: БИЗНЕС ИПОТЕКА (на офисы от Алтын Банк)
B3: Условия продукта:
B4: Срок от 1 года до 10 лет. Мах. сумма займа 200 млн. (мах стоимость помещения 400 млн.) Целевая группа: Граждане РК, жители РК с Видом на Жительства НЕЛЬЗЯ. Первоначальный взнос от 50%. Ставки вознаграждения от 0,1% до 17%. Возраст от 21 года до 65 лет. Созаемщик не участвует. Подтверждение доходов с выписками банков второго уровня на ИП (не более 5 выписок) или Kaspi pay.
B7: Кто может кредитоваться?
B8: ИП, действующее не менее 12 мес. ИП, работающие по упрощенной форме или патент.
B10: Преимущества программы:
B11: Кредитование офисов без доп. залогов на этапе строительства. Процесс оформления онлайн. Возможность оформления с косвенным подтверждением дохода. Без подтверждения ОКЭД и действий бизнеса Любая деятельность ИП (ЧСИ, нотариус не участвуют).
B16: Перечень документов:
B17: Свидетельство ИП. Декларация 910ф. за 12 мес. Патент (при наличии) Выписка со счета ИП (с интернет банкинга) Выписка с Kaspi Pay.
B20: Срок/первоначальный взнос | D20: от 50% | F20: от 60% | G20: от 70%
B21: 12 мес. | D21: 0,5 | F21: 0,1 | G21: 0.1
B22: 13-24 мес. | D22: 2 | F22: 0,5 | G22: 0.1
B23: 25-36 мес. | D23: 8,5 | F23: 5 | G23: 3
B24: 37-60 мес. | D24: 14 | F24: 11 | G24: 8.5
B25: 61-120 мес. | D25: 17 | F25: 15,5 | G25: 13.5
B29: Стоимость офиса | D29: 25000000
B30: Стоимость офиса в ипотеку | D30: =D29*1.05 -> 26250000
B31: Первоначальный взнос, % | D31: 0.5
B32: Первоначальный взнос | D32: =D30*D31 -> 13125000
B33: Сумма Займа | D33: =D30-D32 -> 13125000
B34: Ставка вознагражд годовая | D34: 0.17
B35: Срок кредита | D35: 120
B36: Ежемесячное погашение | D36: =ROUND(POWER((1+D34/12),D35)*D34/12/(POWER((1+D34/12),D35)-1)*D33,0) -> 228109
B37: Переплата за весь срок | D37: =D36*D35-D33 -> 14248080

Sheet BIG Tandau
A2: Программа «BIG Tandau» от МФО BI FINANCE | I2: Да 36/60
A3: Размер первоначального взноса | D3: Срок / Взнос | I3: Квартиры с черновой/чистовой отделкой
A4: Первоначальный взнос Черновая | D4: от 30% | I4: первоначальный взнос от 30 % | J4: ставка вознаграждения %
A5: Первоначальный взнос Чистовая | D5: от 30% | I5: 12 | J5: 8,5%
A6: Целевая группа | D6: Физические лица. Граждане РК, жители РК с Видом на Жительства до срока окончания | I6: 24 | J6: 8,5%
A7: Сумма кредита | D7: Минимум 2 млн – максимум 78 млн | I7: 36 | J7: 13%
A8: Cрок кредитования | D8: 12 мес, 24 мес, 36 мес,48 мес,60 мес | I8: 48 | J8: 13%
A9: Возраст Заемщика | D9: От 21 года до 63 лет на момент завершения срока кредита | I9: 60 | J9: 13,5%
A11: Подтверждение доходов | D11: Рассматриваются любые варианты подтверждения доходов! | I11: Да 36/60 ПВ 30%
A12: РАСХОДЫ, СВЯЗАННЫЕ С ОФОРМЛЕНИЕМ КРЕДИТА | I12: Квартиры с чистовой отделкой
A13: Комиссия за рассмотрения кредитной заявки | D13: 0 тенге | I13: первоначальный взнос от 30% | J13: ставка вознаграждения %
A14: Комиссия за предоставление займа | D14: 0 тенге | I14: 12 | J14: 8,5%
A15: Возможно доп расходы клиента: | D15: Согласие супруга 5 000 -7 000 тенге. | I15: 24 | J15: 8,5%
A16: Досрочное погашение | D16: 0 тенге | I16: 36 | J16: 13%
I17: 48 | J17: 13%
I18: 60 | J18: 13,5%
Q20: Аннуитет
Q23: Метод погашения | R23: аннуитет | T23: Расчет КДН | U23: Вводные данные | V23: Мин доход должен быть
A24: Продукт "BIG Tandau" | F24: 12 Мес | I24: 48 Мес | M24: ручной ввод | Q24: Стоимость жилья | R24: 30223000 | T24: Доход | U24: 2850389 | V24: =(U25+U29+(U30/12))/V27 -> 1772394
F25: Ежемесячное погашение | G25: =E55 -> 148852.46 | I25: Ежемесячное погашение | J25: =AA55 -> 201967.21 | M25: выпадающий список | Q25: Стоимость квартиры в ипотеку | R25: =R24*1.05 -> 31734150 | T25: Ежемесячный платеж по действующим займам | U25: 868473.05
A26: 1 транш (ежемесячные платежи) | B26: =$B$28*$B$39 -> 7868852.4 | F26: 1 транш (годовые платежи) | G26: =E46 -> 23436563 | I26: 1 транш (годовые платежи) | J26: =AA46 -> 6132142.6 | M26: расчетный результат | Q26: ПВ | R26: 0.3 | T26: Планируемый ежемесячный платеж по BIGT | U26: =R30 -> 1009748
A27: 2 транш (годовые платежи) | B27: =B37-B26 -> 14353873 | F27: Общая переплата (если 12 мес) | G27: =D47+D67 -> 2902690.8 | I27: 2 транш (годовые платежи) | J27: =AA47 -> 5594584.6 | M27: сумма ниже минимального (ПВ) | Q27: Сумма микрокредита | R27: =R25-(R25*R26) -> 22213905 | T27: КДН | U27: =(U25+U26)/U24 -> 0.65893501 | V27: 0.49
A28: Платеж из справочника | B28: =VLOOKUP('BIG Tandau'!B31,'для бигтандау'!$A$2:$F$7,MATCH('BIG Tandau'!B30,'для бигтандау'!$A$1:$F$1,0),FALSE) -> 131147.54 | I28: 3 транш (годовые платежи) | J28: =AA48 -> 5057026.7 | Q28: Срок | R28: 24
F29: 24 Мес | I29: 4 транш (годовые платежи) | J29: =AA49 -> 4519468.7 | Q29: Ставка | R29: =_xlfn.IFS('BIG Tandau'!R28='для бигтандау'!A11,'для бигтандау'!B11,'BIG Tandau'!R28='для бигтандау'!A12,'для бигтандау'!B12,'BIG Tandau'!R28='для бигтандау'!A13,'для бигтандау'!B13,'BIG Tandau'!R28='для бигтандау'!A14,'для бигтандау'!B14,'BIG Tandau'!R28='для бигтандау'!A15,'для бигтандау'!B15) -> 0.085
A30: Комнатность жилья | B30: 2-комнатная | F30: Ежемесячное погашение | G30: =L55 -> 166557.38 | I30: Общая переплата (если 48 мес) | J30: =Z50+Z103 -> 7110661.5 | M30: Расчет КДН | N30: Вводные данные | O30: Мин доход должен быть | Q30: Ежемесячный платеж | R30: =_xlfn.IFS(R28=AL43,AP45,R28=AS43,AW45,R28=AZ43,BD45,R28=BG43,BK45,R28=BN43,BR45) -> 1009748
A31: Уровень жилья | B31: стандарт | F31: 1 транш (годовые платежи) | G31: =L46 -> 12112742 | M31: Доход | N31: 2850389 | O31: =(N32+N36+(N37/12))/O34 -> 3271221.5 | Q31: Переплата | R31: =_xlfn.IFS(R28=AL43,AO57,R28=AS43,AV69,R28=AZ43,BC81,R28=BG43,BJ93,R28=BN43,BQ105) -> 2020048
A32: Отделка | B32: Черновая | F32: 2 транш (годовые платежи) | G32: =L47 -> 10825167 | M32: Ежемесячный платеж по действующим займам | N32: 868473.05 | Q32: Периодичность погашения | R32: ежемесячно
A33: Стоимость жилья | B33: 30235000 | F33: Общая переплата (если 24 мес) | G33: =K48+K79 -> 4305347.7 | I33: 60 Мес | M33: Планируемый ежемесячный платеж по BIGT (сумма ежемесячного платежа+(сумма первого платежа по годовому траншу/12)) | N33: =N36+(N37/12) -> 767137.7
A34: Стоимость квартиры в ипотеку | B34: =B33*1.05 -> 31746750 | I34: Ежемесячное погашение | J34: =AH55 -> 219672.13 | M34: КДН | N34: =(N32+N33)/N31 -> 0.57382019 | O34: 0.5
A35: Первоначальный взнос - % | B35: 0.3 | C35: мин. ПВ % | D35: =_xlfn.IFS(B32='для бигтандау'!A19,'для бигтандау'!B19,'BIG Tandau'!B32='для бигтандау'!A20,'для бигтандау'!B20) -> 0.3 | F35: 36 Мес | I35: 1 транш (годовые платежи) | J35: =AH46 -> 4808547.3
A36: Первоначальный взнос (ПВ) | B36: =B34*B35 -> 9524025 | C36: мин. ПВ | D36: =B34*D35 -> 9524025 | F36: Ежемесячное погашение | G36: =S55 -> 184262.29 | I36: 2 транш (годовые платежи) | J36: =AH47 -> 4420992.8 | M36: Ежемесячное погашение | N36: 255737.7 | O36: Необходимо менять значения в зависимости от срока, комнатности и класса
A37: Сумма займа | B37: =B34-B36 -> 22222725 | F37: 1 транш (годовые платежи) | G37: =S46 -> 8196495.4 | I37: 3 транш (годовые платежи) | J37: =AH48 -> 4033438.2 | M37: 1 транш (годовые платежи) | N37: 6136799.9
A38: ставка займа | B38: =VLOOKUP(B39, I5:J9, 2, FALSE) -> 13,5% | F38: 2 транш (годовые платежи) | G38: =S47 -> 7408931.7 | I38: 4 транш (годовые платежи) | J38: =AH49 -> 3645883.6
A39: срок займа | B39: 60 | F39: 3 транш (годовые платежи) | G39: =S48 -> 6621368.1 | I39: 5 транш (годовые платежи) | J39: =AH50 -> 3258329.1
F40: Общая переплата (если 36 мес) | G40: =R49+R91 -> 5708004.6 | I40: Общая переплата (если 60 мес) | J40: =AG51+AG115 -> 8513318.4
A43: 12 | B43: мес | H43: 24 | I43: мес | O43: 36 | P43: мес | W43: 48 | X43: мес | AD43: 60 | AE43: мес | AL43: 12 | AM43: мес | AS43: 24 | AT43: мес | AZ43: 36 | BA43: мес | BG43: 48 | BH43: мес | BN43: 60 | BO43: мес
A44: =A43/12 -> 1 | H44: =H43/12 -> 2 | O44: =O43/12 -> 3 | W44: =W43/12 -> 4 | AD44: =AD43/12 -> 5 | AL44: № | AM44: сумма на начало | AN44: ОД | AO44: вознаграждение | AP44: платеж | AQ44: сумма на конец | AS44: № | AT44: сумма на начало | AU44: ОД | AV44: вознаграждение | AW44: платеж | AX44: сумма на конец | AZ44: № | BA44: сумма на начало | BB44: ОД | BC44: вознаграждение | BD44: платеж | BE44: сумма на конец | BG44: № | BH44: сумма на начало | BI44: ОД | BJ44: вознаграждение | BK44: платеж | BL44: сумма на конец | BN44: № | BO44: сумма на начало | BP44: ОД | BQ44: вознаграждение | BR44: платеж | BS44: сумма на конец
A45: № | B45: сумма на начало | C45: ОД | D45: вознаграждение | E45: платеж | F45: сумма на конец | H45: № | I45: сумма на начало | J45: ОД | K45: вознаграждение | L45: платеж | M45: сумма на конец | O45: № | P45: сумма на начало | Q45: ОД | R45: вознаграждение | S45: платеж | T45: сумма на конец | W45: № | X45: сумма на начало | Y45: ОД | Z45: вознаграждение | AA45: платеж | AB45: сумма на конец | AD45: № | AE45: сумма на начало | AF45: ОД | AG45: вознаграждение | AH45: платеж | AI45: сумма на конец | AL45: 1 | AM45: =R27 -> 22213905 | AN45: =AP45-AO45 -> 1780143.5 | AO45: =AM45*(($R$29*30)/360) -> 157348.49 | AP45: =PMT($R$29/12,$AL$43,AM45)*-1 -> 1937492 | AQ45: =AM45-AN45 -> 20433762 | AS45: 1 | AT45: =R27 -> 22213905 | AU45: =AW45-AV45 -> 852399.55 | AV45: =AT45*(($R$29*30)/360) -> 157348.49 | AW45: =PMT($R$29/12,$AS$43,AT45)*-1 -> 1009748 | AX45: =AT45-AU45 -> 21361505 | AZ45: 1 | BA45: =R27 -> 22213905 | BB45: =BD45-BC45 -> 543889.78 | BC45: =BA45*(($R$29*30)/360) -> 157348.49 | BD45: =PMT($R$29/12,$AZ$43,BA45)*-1 -> 701238.28 | BE45: =BA45-BB45 -> 21670015 | BG45: 1 | BH45: =R27 -> 22213905 | BI45: =BK45-BJ45 -> 390186.58 | BJ45: =BH45*(($R$29*30)/360) -> 157348.49 | BK45: =PMT($R$29/12,$BG$43,BH45)*-1 -> 547535.07 | BL45: =BH45-BI45 -> 21823718 | BN45: 1 | BO45: =R27 -> 22213905 | BP45: =BR45-BQ45 -> 298403.78 | BQ45: =BO45*(($R$29*30)/360) -> 157348.49 | BR45: =PMT($R$29/12,$BN$43,BO45)*-1 -> 455752.28 | BS45: =BO45-BP45 -> 21915501
A46: 1 | B46: =B37-(B28*12) -> 20648955 | C46: =B46/A44 -> 20648955 | D46: =B46*((B38*360)/360) -> 2787608.9 | E46: =C46+D46 -> 23436563 | F46: =B46-C46 -> 0 | H46: 1 | I46: =B37-(B28*24) -> 19075184 | J46: =I46/H44 -> 9537592 | K46: =I46*((B38*360)/360) -> 2575149.8 | L46: =J46+K46 -> 12112742 | M46: =I46-J46 -> 9537592 | O46: 1 | P46: =B37-(B28*36) -> 17501414 | Q46: =P46/O44 -> 5833804.5 | R46: =P46*((B38*360)/360) -> 2362690.8 | S46: =Q46+R46 -> 8196495.4 | T46: =P46-Q46 -> 11667609 | W46: 1 | X46: =B37-(B28*48) -> 15927643 | Y46: =X46/W44 -> 3981910.8 | Z46: =X46*(($B$38*360)/360) -> 2150231.8 | AA46: =Y46+Z46 -> 6132142.6 | AB46: =X46-Y46 -> 11945732 | AD46: 1 | AE46: =B37-(B28*60) -> 14353873 | AF46: =AE46/AD44 -> 2870774.5 | AG46: =AE46*(($B$38*360)/360) -> 1937772.8 | AH46: =AF46+AG46 -> 4808547.3 | AI46: =AE46-AF46 -> 11483098 | AL46: 2 | AM46: =AQ45 -> 20433762 | AN46: =AP46-AO46 -> 1792752.8 | AO46: =AM46*(($R$29*30)/360) -> 144739.14 | AP46: =AP45 -> 1937492 | AQ46: =AM46-AN46 -> 18641009 | AS46: 2 | AT46: =AX45 -> 21361505 | AU46: =AW46-AV46 -> 858437.38 | AV46: =AT46*(($R$29*30)/360) -> 151310.66 | AW46: =AW45 -> 1009748 | AX46: =AT46-AU46 -> 20503068 | AZ46: 2 | BA46: =BE45 -> 21670015 | BB46: =BD46-BC46 -> 547742.34 | BC46: =BA46*(($R$29*30)/360) -> 153495.94 | BD46: =BD45 -> 701238.28 | BE46: =BA46-BB46 -> 21122273 | BG46: 2 | BH46: =BL45 -> 21823718 | BI46: =BK46-BJ46 -> 392950.4 | BJ46: =BH46*(($R$29*30)/360) -> 154584.67 | BK46: =BK45 -> 547535.07 | BL46: =BH46-BI46 -> 21430768 | BN46: 2 | BO46: =BS45 -> 21915501 | BP46: =BR46-BQ46 -> 300517.48 | BQ46: =BO46*(($R$29*30)/360) -> 155234.8 | BR46: =BR45 -> 455752.28 | BS46: =BO46-BP46 -> 21614984
A47: итого: | C47: =SUM(C46) -> 20648955 | D47: =SUM(D46) -> 2787608.9 | H47: 2 | I47: =M46 -> 9537592 | J47: =I46/H44 -> 9537592 | K47: =I47*((B38*360)/360) -> 1287574.9 | L47: =J47+K47 -> 10825167 | M47: =I47-J47 -> 0 | O47: 2 | P47: =T46 -> 11667609 | Q47: =P46/O44 -> 5833804.5 | R47: =P47*((B38*360)/360) -> 1575127.2 | S47: =Q47+R47 -> 7408931.7 | T47: =P47-Q47 -> 5833804.5 | W47: 2 | X47: =AB46 -> 11945732 | Y47: =X46/W44 -> 3981910.8 | Z47: =X47*(($B$38*360)/360) -> 1612673.9 | AA47: =Y47+Z47 -> 5594584.6 | AB47: =X47-Y47 -> 7963821.5 | AD47: 2 | AE47: =AI46 -> 11483098 | AF47: =AE46/AD44 -> 2870774.5 | AG47: =AE47*(($B$38*360)/360) -> 1550218.2 | AH47: =AF47+AG47 -> 4420992.8 | AI47: =AE47-AF47 -> 8612323.6 | AL47: 3 | AM47: =AQ46 -> 18641009 | AN47: =AP47-AO47 -> 1805451.5 | AO47: =AM47*(($R$29*30)/360) -> 132040.48 | AP47: =AP46 -> 1937492 | AQ47: =AM47-AN47 -> 16835557 | AS47: 3 | AT47: =AX46 -> 20503068 | AU47: =AW47-AV47 -> 864517.98 | AV47: =AT47*(($R$29*30)/360) -> 145230.07 | AW47: =AW46 -> 1009748 | AX47: =AT47-AU47 -> 19638550 | AZ47: 3 | BA47: =BE46 -> 21122273 | BB47: =BD47-BC47 -> 551622.18 | BC47: =BA47*(($R$29*30)/360) -> 149616.1 | BD47: =BD46 -> 701238.28 | BE47: =BA47-BB47 -> 20570651 | BG47: 3 | BH47: =BL46 -> 21430768 | BI47: =BK47-BJ47 -> 395733.8 | BJ47: =BH47*(($R$29*30)/360) -> 151801.27 | BK47: =BK46 -> 547535.07 | BL47: =BH47-BI47 -> 21035034 | BN47: 3 | BO47: =BS46 -> 21614984 | BP47: =BR47-BQ47 -> 302646.14 | BQ47: =BO47*(($R$29*30)/360) -> 153106.13 | BR47: =BR46 -> 455752.28 | BS47: =BO47-BP47 -> 21312338
H48: итого: | J48: =SUM(J46:J47) -> 19075184 | K48: =SUM(K46:K47) -> 3862724.8 | L48: =J48+K48 -> 22937909 | O48: 3 | P48: =T47 -> 5833804.5 | Q48: =P46/O44 -> 5833804.5 | R48: =P48*((B38*360)/360) -> 787563.61 | S48: =Q48+R48 -> 6621368.1 | T48: =P48-Q48 -> 0 | W48: 3 | X48: =AB47 -> 7963821.5 | Y48: =X46/W44 -> 3981910.8 | Z48: =X48*(($B$38*360)/360) -> 1075115.9 | AA48: =Y48+Z48 -> 5057026.7 | AB48: =X48-Y48 -> 3981910.8 | AD48: 3 | AE48: =AI47 -> 8612323.6 | AF48: =AE46/AD44 -> 2870774.5 | AG48: =AE48*(($B$38*360)/360) -> 1162663.7 | AH48: =AF48+AG48 -> 4033438.2 | AI48: =AE48-AF48 -> 5741549 | AL48: 4 | AM48: =AQ47 -> 16835557 | AN48: =AP48-AO48 -> 1818240.1 | AO48: =AM48*(($R$29*30)/360) -> 119251.86 | AP48: =AP47 -> 1937492 | AQ48: =AM48-AN48 -> 15017317 | AS48: 4 | AT48: =AX47 -> 19638550 | AU48: =AW48-AV48 -> 870641.65 | AV48: =AT48*(($R$29*30)/360) -> 139106.4 | AW48: =AW47 -> 1009748 | AX48: =AT48-AU48 -> 18767908 | AZ48: 4 | BA48: =BE47 -> 20570651 | BB48: =BD48-BC48 -> 555529.5 | BC48: =BA48*(($R$29*30)/360) -> 145708.78 | BD48: =BD47 -> 701238.28 | BE48: =BA48-BB48 -> 20015121 | BG48: 4 | BH48: =BL47 -> 21035034 | BI48: =BK48-BJ48 -> 398536.91 | BJ48: =BH48*(($R$29*30)/360) -> 148998.16 | BK48: =BK47 -> 547535.07 | BL48: =BH48-BI48 -> 20636497 | BN48: 4 | BO48: =BS47 -> 21312338 | BP48: =BR48-BQ48 -> 304789.89 | BQ48: =BO48*(($R$29*30)/360) -> 150962.39 | BR48: =BR47 -> 455752.28 | BS48: =BO48-BP48 -> 21007548
O49: итого: | Q49: =SUM(Q46:Q48) -> 17501414 | R49: =SUM(R46:R48) -> 4725381.7 | S49: =Q49+R49 -> 22226795 | W49: 4 | X49: =AB48 -> 3981910.8 | Y49: =X46/W44 -> 3981910.8 | Z49: =X49*(($B$38*360)/360) -> 537557.95 | AA49: =Y49+Z49 -> 4519468.7 | AB49: =X49-Y49 -> 0 | AD49: 4 | AE49: =AI48 -> 5741549 | AF49: =AE46/AD44 -> 2870774.5 | AG49: =AE49*(($B$38*360)/360) -> 775109.12 | AH49: =AF49+AG49 -> 3645883.6 | AI49: =AE49-AF49 -> 2870774.5 | AL49: 5 | AM49: =AQ48 -> 15017317 | AN49: =AP49-AO49 -> 1831119.3 | AO49: =AM49*(($R$29*30)/360) -> 106372.66 | AP49: =AP48 -> 1937492 | AQ49: =AM49-AN49 -> 13186198 | AS49: 5 | AT49: =AX48 -> 18767908 | AU49: =AW49-AV49 -> 876808.69 | AV49: =AT49*(($R$29*30)/360) -> 132939.35 | AW49: =AW48 -> 1009748 | AX49: =AT49-AU49 -> 17891100 | AZ49: 5 | BA49: =BE48 -> 20015121 | BB49: =BD49-BC49 -> 559464.5 | BC49: =BA49*(($R$29*30)/360) -> 141773.78 | BD49: =BD48 -> 701238.28 | BE49: =BA49-BB49 -> 19455657 | BG49: 5 | BH49: =BL48 -> 20636497 | BI49: =BK49-BJ49 -> 401359.88 | BJ49: =BH49*(($R$29*30)/360) -> 146175.19 | BK49: =BK48 -> 547535.07 | BL49: =BH49-BI49 -> 20235137 | BN49: 5 | BO49: =BS48 -> 21007548 | BP49: =BR49-BQ49 -> 306948.81 | BQ49: =BO49*(($R$29*30)/360) -> 148803.46 | BR49: =BR48 -> 455752.28 | BS49: =BO49-BP49 -> 20700599
W50: итого: | Y50: =SUM(Y46:Y49) -> 15927643 | Z50: =SUM(Z46:Z49) -> 5375579.5 | AA50: =Y50+Z50 -> 21303223 | AD50: 5 | AE50: =AI49 -> 2870774.5 | AF50: =AE46/AD44 -> 2870774.5 | AG50: =AE50*(($B$38*360)/360) -> 387554.56 | AH50: =AF50+AG50 -> 3258329.1 | AI50: =AE50-AF50 -> 0 | AL50: 6 | AM50: =AQ49 -> 13186198 | AN50: =AP50-AO50 -> 1844089.7 | AO50: =AM50*(($R$29*30)/360) -> 93402.235 | AP50: =AP49 -> 1937492 | AQ50: =AM50-AN50 -> 11342108 | AS50: 6 | AT50: =AX49 -> 17891100 | AU50: =AW50-AV50 -> 883019.42 | AV50: =AT50*(($R$29*30)/360) -> 126728.62 | AW50: =AW49 -> 1009748 | AX50: =AT50-AU50 -> 17008080 | AZ50: 6 | BA50: =BE49 -> 19455657 | BB50: =BD50-BC50 -> 563427.38 | BC50: =BA50*(($R$29*30)/360) -> 137810.9 | BD50: =BD49 -> 701238.28 | BE50: =BA50-BB50 -> 18892229 | BG50: 6 | BH50: =BL49 -> 20235137 | BI50: =BK50-BJ50 -> 404202.85 | BJ50: =BH50*(($R$29*30)/360) -> 143332.22 | BK50: =BK49 -> 547535.07 | BL50: =BH50-BI50 -> 19830935 | BN50: 6 | BO50: =BS49 -> 20700599 | BP50: =BR50-BQ50 -> 309123.04 | BQ50: =BO50*(($R$29*30)/360) -> 146629.24 | BR50: =BR49 -> 455752.28 | BS50: =BO50-BP50 -> 20391476
AD51: итого: | AF51: =SUM(AF46:AF50) -> 14353873 | AG51: =SUM(AG46:AG50) -> 5813318.4 | AH51: =AF51+AG51 -> 20167191 | AL51: 7 | AM51: =AQ50 -> 11342108 | AN51: =AP51-AO51 -> 1857152 | AO51: =AM51*(($R$29*30)/360) -> 80339.932 | AP51: =AP50 -> 1937492 | AQ51: =AM51-AN51 -> 9484956.1 | AS51: 7 | AT51: =AX50 -> 17008080 | AU51: =AW51-AV51 -> 889274.14 | AV51: =AT51*(($R$29*30)/360) -> 120473.9 | AW51: =AW50 -> 1009748 | AX51: =AT51-AU51 -> 16118806 | AZ51: 7 | BA51: =BE50 -> 18892229 | BB51: =BD51-BC51 -> 567418.32 | BC51: =BA51*(($R$29*30)/360) -> 133819.96 | BD51: =BD50 -> 701238.28 | BE51: =BA51-BB51 -> 18324811 | BG51: 7 | BH51: =BL50 -> 19830935 | BI51: =BK51-BJ51 -> 407065.95 | BJ51: =BH51*(($R$29*30)/360) -> 140469.12 | BK51: =BK50 -> 547535.07 | BL51: =BH51-BI51 -> 19423869 | BN51: 7 | BO51: =BS50 -> 20391476 | BP51: =BR51-BQ51 -> 311312.66 | BQ51: =BO51*(($R$29*30)/360) -> 144439.62 | BR51: =BR50 -> 455752.28 | BS51: =BO51-BP51 -> 20080163
AL52: 8 | AM52: =AQ51 -> 9484956.1 | AN52: =AP52-AO52 -> 1870306.9 | AO52: =AM52*(($R$29*30)/360) -> 67185.106 | AP52: =AP51 -> 1937492 | AQ52: =AM52-AN52 -> 7614649.2 | AS52: 8 | AT52: =AX51 -> 16118806 | AU52: =AW52-AV52 -> 895573.17 | AV52: =AT52*(($R$29*30)/360) -> 114174.88 | AW52: =AW51 -> 1009748 | AX52: =AT52-AU52 -> 15223233 | AZ52: 8 | BA52: =BE51 -> 18324811 | BB52: =BD52-BC52 -> 571437.53 | BC52: =BA52*(($R$29*30)/360) -> 129800.74 | BD52: =BD51 -> 701238.28 | BE52: =BA52-BB52 -> 17753373 | BG52: 8 | BH52: =BL51 -> 19423869 | BI52: =BK52-BJ52 -> 409949.33 | BJ52: =BH52*(($R$29*30)/360) -> 137585.74 | BK52: =BK51 -> 547535.07 | BL52: =BH52-BI52 -> 19013919 | BN52: 8 | BO52: =BS51 -> 20080163 | BP52: =BR52-BQ52 -> 313517.79 | BQ52: =BO52*(($R$29*30)/360) -> 142234.49 | BR52: =BR51 -> 455752.28 | BS52: =BO52-BP52 -> 19766645
A53: 12 | B53: мес | H53: 24 | I53: мес | O53: 36 | P53: мес | W53: 48 | X53: мес | AD53: 60 | AE53: мес | AL53: 9 | AM53: =AQ52 -> 7614649.2 | AN53: =AP53-AO53 -> 1883554.9 | AO53: =AM53*(($R$29*30)/360) -> 53937.099 | AP53: =AP52 -> 1937492 | AQ53: =AM53-AN53 -> 5731094.4 | AS53: 9 | AT53: =AX52 -> 15223233 | AU53: =AW53-AV53 -> 901916.81 | AV53: =AT53*(($R$29*30)/360) -> 107831.23 | AW53: =AW52 -> 1009748 | AX53: =AT53-AU53 -> 14321316 | AZ53: 9 | BA53: =BE52 -> 17753373 | BB53: =BD53-BC53 -> 575485.22 | BC53: =BA53*(($R$29*30)/360) -> 125753.06 | BD53: =BD52 -> 701238.28 | BE53: =BA53-BB53 -> 17177888 | BG53: 9 | BH53: =BL52 -> 19013919 | BI53: =BK53-BJ53 -> 412853.14 | BJ53: =BH53*(($R$29*30)/360) -> 134681.93 | BK53: =BK52 -> 547535.07 | BL53: =BH53-BI53 -> 18601066 | BN53: 9 | BO53: =BS52 -> 19766645 | BP53: =BR53-BQ53 -> 315738.54 | BQ53: =BO53*(($R$29*30)/360) -> 140013.74 | BR53: =BR52 -> 455752.28 | BS53: =BO53-BP53 -> 19450907
A54: № | B54: сумма на начало | C54: ОД | D54: вознаграждение | E54: платеж | F54: сумма на конец | H54: № | I54: сумма на начало | J54: ОД | K54: вознаграждение | L54: платеж | M54: сумма на конец | O54: № | P54: сумма на начало | Q54: ОД | R54: вознаграждение | S54: платеж | T54: сумма на конец | W54: № | X54: сумма на начало | Y54: ОД | Z54: вознаграждение | AA54: платеж | AB54: сумма на конец | AD54: № | AE54: сумма на начало | AF54: ОД | AG54: вознаграждение | AH54: платеж | AI54: сумма на конец | AL54: 10 | AM54: =AQ53 -> 5731094.4 | AN54: =AP54-AO54 -> 1896896.7 | AO54: =AM54*(($R$29*30)/360) -> 40595.252 | AP54: =AP53 -> 1937492 | AQ54: =AM54-AN54 -> 3834197.6 | AS54: 10 | AT54: =AX53 -> 14321316 | AU54: =AW54-AV54 -> 908305.39 | AV54: =AT54*(($R$29*30)/360) -> 101442.66 | AW54: =AW53 -> 1009748 | AX54: =AT54-AU54 -> 13413011 | AZ54: 10 | BA54: =BE53 -> 17177888 | BB54: =BD54-BC54 -> 579561.57 | BC54: =BA54*(($R$29*30)/360) -> 121676.71 | BD54: =BD53 -> 701238.28 | BE54: =BA54-BB54 -> 16598327 | BG54: 10 | BH54: =BL53 -> 18601066 | BI54: =BK54-BJ54 -> 415777.52 | BJ54: =BH54*(($R$29*30)/360) -> 131757.55 | BK54: =BK53 -> 547535.07 | BL54: =BH54-BI54 -> 18185289 | BN54: 10 | BO54: =BS53 -> 19450907 | BP54: =BR54-BQ54 -> 317975.02 | BQ54: =BO54*(($R$29*30)/360) -> 137777.26 | BR54: =BR53 -> 455752.28 | BS54: =BO54-BP54 -> 19132932
A55: 1 | B55: =B28*12 -> 1573770.5 | C55: =B55/A53 -> 131147.54 | D55: =B55*(($B$38*30)/360) -> 17704.918 | E55: =C55+D55 -> 148852.46 | F55: =B55-C55 -> 1442622.9 | H55: 1 | I55: =B28*24 -> 3147541 | J55: =I55/H53 -> 131147.54 | K55: =I55*(($B$38*30)/360) -> 35409.836 | L55: =J55+K55 -> 166557.38 | M55: =I55-J55 -> 3016393.4 | O55: 1 | P55: =B28*36 -> 4721311.4 | Q55: =P55/O53 -> 131147.54 | R55: =P55*(($B$38*30)/360) -> 53114.754 | S55: =Q55+R55 -> 184262.29 | T55: =P55-Q55 -> 4590163.9 | W55: 1 | X55: =B28*48 -> 6295081.9 | Y55: =$X$55/$W$53 -> 131147.54 | Z55: =X55*(($B$38*30)/360) -> 70819.672 | AA55: =Y55+Z55 -> 201967.21 | AB55: =X55-Y55 -> 6163934.4 | AD55: 1 | AE55: =B28*60 -> 7868852.4 | AF55: =$AE$55/$AD$53 -> 131147.54 | AG55: =AE55*(($B$38*30)/360) -> 88524.59 | AH55: =AF55+AG55 -> 219672.13 | AI55: =AE55-AF55 -> 7737704.9 | AL55: 11 | AM55: =AQ54 -> 3834197.6 | AN55: =AP55-AO55 -> 1910333.1 | AO55: =AM55*(($R$29*30)/360) -> 27158.9 | AP55: =AP54 -> 1937492 | AQ55: =AM55-AN55 -> 1923864.6 | AS55: 11 | AT55: =AX54 -> 13413011 | AU55: =AW55-AV55 -> 914739.22 | AV55: =AT55*(($R$29*30)/360) -> 95008.827 | AW55: =AW54 -> 1009748 | AX55: =AT55-AU55 -> 12498272 | AZ55: 11 | BA55: =BE54 -> 16598327 | BB55: =BD55-BC55 -> 583666.8 | BC55: =BA55*(($R$29*30)/360) -> 117571.48 | BD55: =BD54 -> 701238.28 | BE55: =BA55-BB55 -> 16014660 | BG55: 11 | BH55: =BL54 -> 18185289 | BI55: =BK55-BJ55 -> 418722.61 | BJ55: =BH55*(($R$29*30)/360) -> 128812.46 | BK55: =BK54 -> 547535.07 | BL55: =BH55-BI55 -> 17766566 | BN55: 11 | BO55: =BS54 -> 19132932 | BP55: =BR55-BQ55 -> 320227.34 | BQ55: =BO55*(($R$29*30)/360) -> 135524.93 | BR55: =BR54 -> 455752.28 | BS55: =BO55-BP55 -> 18812705
A56: 2 | B56: =F55 -> 1442622.9 | C56: =B55/A53 -> 131147.54 | D56: =B56*(($B$38*30)/360) -> 16229.508 | E56: =C56+D56 -> 147377.05 | F56: =B56-C56 -> 1311475.4 | H56: 2 | I56: =M55 -> 3016393.4 | J56: =I55/H53 -> 131147.54 | K56: =I56*(($B$38*30)/360) -> 33934.426 | L56: =J56+K56 -> 165081.97 | M56: =I56-J56 -> 2885245.9 | O56: 2 | P56: =T55 -> 4590163.9 | Q56: =P55/O53 -> 131147.54 | R56: =P56*(($B$38*30)/360) -> 51639.344 | S56: =Q56+R56 -> 182786.88 | T56: =P56-Q56 -> 4459016.4 | W56: 2 | X56: =AB55 -> 6163934.4 | Y56: =$X$55/$W$53 -> 131147.54 | Z56: =X56*(($B$38*30)/360) -> 69344.262 | AA56: =Y56+Z56 -> 200491.8 | AB56: =X56-Y56 -> 6032786.8 | AD56: 2 | AE56: =AI55 -> 7737704.9 | AF56: =$X$55/$W$53 -> 131147.54 | AG56: =AE56*(($B$38*30)/360) -> 87049.18 | AH56: =AF56+AG56 -> 218196.72 | AI56: =AE56-AF56 -> 7606557.3 | AL56: 12 | AM56: =AQ55 -> 1923864.6 | AN56: =AP56-AO56 -> 1923864.6 | AO56: =AM56*(($R$29*30)/360) -> 13627.374 | AP56: =AP55 -> 1937492 | AQ56: =AM56-AN56 -> -1.8626451e-09 | AS56: 12 | AT56: =AX55 -> 12498272 | AU56: =AW56-AV56 -> 921218.62 | AV56: =AT56*(($R$29*30)/360) -> 88529.424 | AW56: =AW55 -> 1009748 | AX56: =AT56-AU56 -> 11577053 | AZ56: 12 | BA56: =BE55 -> 16014660 | BB56: =BD56-BC56 -> 587801.1 | BC56: =BA56*(($R$29*30)/360) -> 113437.17 | BD56: =BD55 -> 701238.28 | BE56: =BA56-BB56 -> 15426859 | BG56: 12 | BH56: =BL55 -> 17766566 | BI56: =BK56-BJ56 -> 421688.56 | BJ56: =BH56*(($R$29*30)/360) -> 125846.51 | BK56: =BK55 -> 547535.07 | BL56: =BH56-BI56 -> 17344877 | BN56: 12 | BO56: =BS55 -> 18812705 | BP56: =BR56-BQ56 -> 322495.62 | BQ56: =BO56*(($R$29*30)/360) -> 133256.66 | BR56: =BR55 -> 455752.28 | BS56: =BO56-BP56 -> 18490209
A57: 3 | B57: =F56 -> 1311475.4 | C57: =B55/A53 -> 131147.54 | D57: =B57*(($B$38*30)/360) -> 14754.098 | E57: =C57+D57 -> 145901.64 | F57: =B57-C57 -> 1180327.9 | H57: 3 | I57: =M56 -> 2885245.9 | J57: =I55/H53 -> 131147.54 | K57: =I57*(($B$38*30)/360) -> 32459.016 | L57: =J57+K57 -> 163606.56 | M57: =I57-J57 -> 2754098.3 | O57: 3 | P57: =T56 -> 4459016.4 | Q57: =P55/O53 -> 131147.54 | R57: =P57*(($B$38*30)/360) -> 50163.934 | S57: =Q57+R57 -> 181311.47 | T57: =P57-Q57 -> 4327868.8 | W57: 3 | X57: =AB56 -> 6032786.8 | Y57: =$X$55/$W$53 -> 131147.54 | Z57: =X57*(($B$38*30)/360) -> 67868.852 | AA57: =Y57+Z57 -> 199016.39 | AB57: =X57-Y57 -> 5901639.3 | AD57: 3 | AE57: =AI56 -> 7606557.3 | AF57: =$X$55/$W$53 -> 131147.54 | AG57: =AE57*(($B$38*30)/360) -> 85573.77 | AH57: =AF57+AG57 -> 216721.31 | AI57: =AE57-AF57 -> 7475409.8 | AL57: итого: | AN57: =SUM(AN45:AN56) -> 22213905 | AO57: =SUM(AO45:AO56) -> 1035998.5 | AS57: 13 | AT57: =AX56 -> 11577053 | AU57: =AW57-AV57 -> 927743.92 | AV57: =AT57*(($R$29*30)/360) -> 82004.125 | AW57: =AW56 -> 1009748 | AX57: =AT57-AU57 -> 10649309 | AZ57: 13 | BA57: =BE56 -> 15426859 | BB57: =BD57-BC57 -> 591964.69 | BC57: =BA57*(($R$29*30)/360) -> 109273.58 | BD57: =BD56 -> 701238.28 | BE57: =BA57-BB57 -> 14834894 | BG57: 13 | BH57: =BL56 -> 17344877 | BI57: =BK57-BJ57 -> 424675.52 | BJ57: =BH57*(($R$29*30)/360) -> 122859.55 | BK57: =BK56 -> 547535.07 | BL57: =BH57-BI57 -> 16920202 | BN57: 13 | BO57: =BS56 -> 18490209 | BP57: =BR57-BQ57 -> 324779.96 | BQ57: =BO57*(($R$29*30)/360) -> 130972.31 | BR57: =BR56 -> 455752.28 | BS57: =BO57-BP57 -> 18165429
A58: 4 | B58: =F57 -> 1180327.9 | C58: =B55/A53 -> 131147.54 | D58: =B58*(($B$38*30)/360) -> 13278.688 | E58: =C58+D58 -> 144426.23 | F58: =B58-C58 -> 1049180.3 | H58: 4 | I58: =M57 -> 2754098.3 | J58: =I55/H53 -> 131147.54 | K58: =I58*(($B$38*30)/360) -> 30983.606 | L58: =J58+K58 -> 162131.15 | M58: =I58-J58 -> 2622950.8 | O58: 4 | P58: =T57 -> 4327868.8 | Q58: =P55/O53 -> 131147.54 | R58: =P58*(($B$38*30)/360) -> 48688.524 | S58: =Q58+R58 -> 179836.06 | T58: =P58-Q58 -> 4196721.3 | W58: 4 | X58: =AB57 -> 5901639.3 | Y58: =$X$55/$W$53 -> 131147.54 | Z58: =X58*(($B$38*30)/360) -> 66393.442 | AA58: =Y58+Z58 -> 197540.98 | AB58: =X58-Y58 -> 5770491.8 | AD58: 4 | AE58: =AI57 -> 7475409.8 | AF58: =$X$55/$W$53 -> 131147.54 | AG58: =AE58*(($B$38*30)/360) -> 84098.36 | AH58: =AF58+AG58 -> 215245.9 | AI58: =AE58-AF58 -> 7344262.2 | AS58: 14 | AT58: =AX57 -> 10649309 | AU58: =AW58-AV58 -> 934315.44 | AV58: =AT58*(($R$29*30)/360) -> 75432.606 | AW58: =AW57 -> 1009748 | AX58: =AT58-AU58 -> 9714993.6 | AZ58: 14 | BA58: =BE57 -> 14834894 | BB58: =BD58-BC58 -> 596157.78 | BC58: =BA58*(($R$29*30)/360) -> 105080.5 | BD58: =BD57 -> 701238.28 | BE58: =BA58-BB58 -> 14238736 | BG58: 14 | BH58: =BL57 -> 16920202 | BI58: =BK58-BJ58 -> 427683.64 | BJ58: =BH58*(($R$29*30)/360) -> 119851.43 | BK58: =BK57 -> 547535.07 | BL58: =BH58-BI58 -> 16492518 | BN58: 14 | BO58: =BS57 -> 18165429 | BP58: =BR58-BQ58 -> 327080.49 | BQ58: =BO58*(($R$29*30)/360) -> 128671.79 | BR58: =BR57 -> 455752.28 | BS58: =BO58-BP58 -> 17838348
A59: 5 | B59: =F58 -> 1049180.3 | C59: =B55/A53 -> 131147.54 | D59: =B59*(($B$38*30)/360) -> 11803.279 | E59: =C59+D59 -> 142950.82 | F59: =B59-C59 -> 918032.78 | H59: 5 | I59: =M58 -> 2622950.8 | J59: =I55/H53 -> 131147.54 | K59: =I59*(($B$38*30)/360) -> 29508.197 | L59: =J59+K59 -> 160655.74 | M59: =I59-J59 -> 2491803.3 | O59: 5 | P59: =T58 -> 4196721.3 | Q59: =P55/O53 -> 131147.54 | R59: =P59*(($B$38*30)/360) -> 47213.114 | S59: =Q59+R59 -> 178360.65 | T59: =P59-Q59 -> 4065573.7 | W59: 5 | X59: =AB58 -> 5770491.8 | Y59: =$X$55/$W$53 -> 131147.54 | Z59: =X59*(($B$38*30)/360) -> 64918.032 | AA59: =Y59+Z59 -> 196065.57 | AB59: =X59-Y59 -> 5639344.2 | AD59: 5 | AE59: =AI58 -> 7344262.2 | AF59: =$X$55/$W$53 -> 131147.54 | AG59: =AE59*(($B$38*30)/360) -> 82622.95 | AH59: =AF59+AG59 -> 213770.49 | AI59: =AE59-AF59 -> 7213114.7 | AS59: 15 | AT59: =AX58 -> 9714993.6 | AU59: =AW59-AV59 -> 940933.51 | AV59: =AT59*(($R$29*30)/360) -> 68814.538 | AW59: =AW58 -> 1009748 | AX59: =AT59-AU59 -> 8774060.1 | AZ59: 15 | BA59: =BE58 -> 14238736 | BB59: =BD59-BC59 -> 600380.56 | BC59: =BA59*(($R$29*30)/360) -> 100857.72 | BD59: =BD58 -> 701238.28 | BE59: =BA59-BB59 -> 13638356 | BG59: 15 | BH59: =BL58 -> 16492518 | BI59: =BK59-BJ59 -> 430713.06 | BJ59: =BH59*(($R$29*30)/360) -> 116822 | BK59: =BK58 -> 547535.07 | BL59: =BH59-BI59 -> 16061805 | BN59: 15 | BO59: =BS58 -> 17838348 | BP59: =BR59-BQ59 -> 329397.31 | BQ59: =BO59*(($R$29*30)/360) -> 126354.97 | BR59: =BR58 -> 455752.28 | BS59: =BO59-BP59 -> 17508951
A60: 6 | B60: =F59 -> 918032.78 | C60: =B55/A53 -> 131147.54 | D60: =B60*(($B$38*30)/360) -> 10327.869 | E60: =C60+D60 -> 141475.41 | F60: =B60-C60 -> 786885.24 | H60: 6 | I60: =M59 -> 2491803.3 | J60: =I55/H53 -> 131147.54 | K60: =I60*(($B$38*30)/360) -> 28032.787 | L60: =J60+K60 -> 159180.33 | M60: =I60-J60 -> 2360655.7 | O60: 6 | P60: =T59 -> 4065573.7 | Q60: =P55/O53 -> 131147.54 | R60: =P60*(($B$38*30)/360) -> 45737.705 | S60: =Q60+R60 -> 176885.24 | T60: =P60-Q60 -> 3934426.2 | W60: 6 | X60: =AB59 -> 5639344.2 | Y60: =$X$55/$W$53 -> 131147.54 | Z60: =X60*(($B$38*30)/360) -> 63442.622 | AA60: =Y60+Z60 -> 194590.16 | AB60: =X60-Y60 -> 5508196.7 | AD60: 6 | AE60: =AI59 -> 7213114.7 | AF60: =$X$55/$W$53 -> 131147.54 | AG60: =AE60*(($B$38*30)/360) -> 81147.54 | AH60: =AF60+AG60 -> 212295.08 | AI60: =AE60-AF60 -> 7081967.2 | AS60: 16 | AT60: =AX59 -> 8774060.1 | AU60: =AW60-AV60 -> 947598.45 | AV60: =AT60*(($R$29*30)/360) -> 62149.593 | AW60: =AW59 -> 1009748 | AX60: =AT60-AU60 -> 7826461.7 | AZ60: 16 | BA60: =BE59 -> 13638356 | BB60: =BD60-BC60 -> 604633.26 | BC60: =BA60*(($R$29*30)/360) -> 96605.02 | BD60: =BD59 -> 701238.28 | BE60: =BA60-BB60 -> 13033722 | BG60: 16 | BH60: =BL59 -> 16061805 | BI60: =BK60-BJ60 -> 433763.95 | BJ60: =BH60*(($R$29*30)/360) -> 113771.12 | BK60: =BK59 -> 547535.07 | BL60: =BH60-BI60 -> 15628041 | BN60: 16 | BO60: =BS59 -> 17508951 | BP60: =BR60-BQ60 -> 331730.54 | BQ60: =BO60*(($R$29*30)/360) -> 124021.74 | BR60: =BR59 -> 455752.28 | BS60: =BO60-BP60 -> 17177221
A61: 7 | B61: =F60 -> 786885.24 | C61: =B55/A53 -> 131147.54 | D61: =B61*(($B$38*30)/360) -> 8852.4589 | E61: =C61+D61 -> 140000 | F61: =B61-C61 -> 655737.7 | H61: 7 | I61: =M60 -> 2360655.7 | J61: =I55/H53 -> 131147.54 | K61: =I61*(($B$38*30)/360) -> 26557.377 | L61: =J61+K61 -> 157704.92 | M61: =I61-J61 -> 2229508.2 | O61: 7 | P61: =T60 -> 3934426.2 | Q61: =P55/O53 -> 131147.54 | R61: =P61*(($B$38*30)/360) -> 44262.295 | S61: =Q61+R61 -> 175409.83 | T61: =P61-Q61 -> 3803278.7 | W61: 7 | X61: =AB60 -> 5508196.7 | Y61: =$X$55/$W$53 -> 131147.54 | Z61: =X61*(($B$38*30)/360) -> 61967.213 | AA61: =Y61+Z61 -> 193114.75 | AB61: =X61-Y61 -> 5377049.1 | AD61: 7 | AE61: =AI60 -> 7081967.2 | AF61: =$X$55/$W$53 -> 131147.54 | AG61: =AE61*(($B$38*30)/360) -> 79672.131 | AH61: =AF61+AG61 -> 210819.67 | AI61: =AE61-AF61 -> 6950819.6 | AS61: 17 | AT61: =AX60 -> 7826461.7 | AU61: =AW61-AV61 -> 954310.61 | AV61: =AT61*(($R$29*30)/360) -> 55437.437 | AW61: =AW60 -> 1009748 | AX61: =AT61-AU61 -> 6872151.1 | AZ61: 17 | BA61: =BE60 -> 13033722 | BB61: =BD61-BC61 -> 608916.08 | BC61: =BA61*(($R$29*30)/360) -> 92322.201 | BD61: =BD60 -> 701238.28 | BE61: =BA61-BB61 -> 12424806 | BG61: 17 | BH61: =BL60 -> 15628041 | BI61: =BK61-BJ61 -> 436836.44 | BJ61: =BH61*(($R$29*30)/360) -> 110698.63 | BK61: =BK60 -> 547535.07 | BL61: =BH61-BI61 -> 15191205 | BN61: 17 | BO61: =BS60 -> 17177221 | BP61: =BR61-BQ61 -> 334080.3 | BQ61: =BO61*(($R$29*30)/360) -> 121671.98 | BR61: =BR60 -> 455752.28 | BS61: =BO61-BP61 -> 16843140
A62: 8 | B62: =F61 -> 655737.7 | C62: =B55/A53 -> 131147.54 | D62: =B62*(($B$38*30)/360) -> 7377.0491 | E62: =C62+D62 -> 138524.59 | F62: =B62-C62 -> 524590.16 | H62: 8 | I62: =M61 -> 2229508.2 | J62: =I55/H53 -> 131147.54 | K62: =I62*(($B$38*30)/360) -> 25081.967 | L62: =J62+K62 -> 156229.51 | M62: =I62-J62 -> 2098360.6 | O62: 8 | P62: =T61 -> 3803278.7 | Q62: =P55/O53 -> 131147.54 | R62: =P62*(($B$38*30)/360) -> 42786.885 | S62: =Q62+R62 -> 173934.42 | T62: =P62-Q62 -> 3672131.1 | W62: 8 | X62: =AB61 -> 5377049.1 | Y62: =$X$55/$W$53 -> 131147.54 | Z62: =X62*(($B$38*30)/360) -> 60491.803 | AA62: =Y62+Z62 -> 191639.34 | AB62: =X62-Y62 -> 5245901.6 | AD62: 8 | AE62: =AI61 -> 6950819.6 | AF62: =$X$55/$W$53 -> 131147.54 | AG62: =AE62*(($B$38*30)/360) -> 78196.721 | AH62: =AF62+AG62 -> 209344.26 | AI62: =AE62-AF62 -> 6819672.1 | AS62: 18 | AT62: =AX61 -> 6872151.1 | AU62: =AW62-AV62 -> 961070.31 | AV62: =AT62*(($R$29*30)/360) -> 48677.737 | AW62: =AW61 -> 1009748 | AX62: =AT62-AU62 -> 5911080.8 | AZ62: 18 | BA62: =BE61 -> 12424806 | BB62: =BD62-BC62 -> 613229.23 | BC62: =BA62*(($R$29*30)/360) -> 88009.045 | BD62: =BD61 -> 701238.28 | BE62: =BA62-BB62 -> 11811577 | BG62: 18 | BH62: =BL61 -> 15191205 | BI62: =BK62-BJ62 -> 439930.7 | BJ62: =BH62*(($R$29*30)/360) -> 107604.37 | BK62: =BK61 -> 547535.07 | BL62: =BH62-BI62 -> 14751274 | BN62: 18 | BO62: =BS61 -> 16843140 | BP62: =BR62-BQ62 -> 336446.7 | BQ62: =BO62*(($R$29*30)/360) -> 119305.58 | BR62: =BR61 -> 455752.28 | BS62: =BO62-BP62 -> 16506694
A63: 9 | B63: =F62 -> 524590.16 | C63: =B55/A53 -> 131147.54 | D63: =B63*(($B$38*30)/360) -> 5901.6393 | E63: =C63+D63 -> 137049.18 | F63: =B63-C63 -> 393442.62 | H63: 9 | I63: =M62 -> 2098360.6 | J63: =I55/H53 -> 131147.54 | K63: =I63*(($B$38*30)/360) -> 23606.557 | L63: =J63+K63 -> 154754.1 | M63: =I63-J63 -> 1967213.1 | O63: 9 | P63: =T62 -> 3672131.1 | Q63: =P55/O53 -> 131147.54 | R63: =P63*(($B$38*30)/360) -> 41311.475 | S63: =Q63+R63 -> 172459.02 | T63: =P63-Q63 -> 3540983.6 | W63: 9 | X63: =AB62 -> 5245901.6 | Y63: =$X$55/$W$53 -> 131147.54 | Z63: =X63*(($B$38*30)/360) -> 59016.393 | AA63: =Y63+Z63 -> 190163.93 | AB63: =X63-Y63 -> 5114754.1 | AD63: 9 | AE63: =AI62 -> 6819672.1 | AF63: =$X$55/$W$53 -> 131147.54 | AG63: =AE63*(($B$38*30)/360) -> 76721.311 | AH63: =AF63+AG63 -> 207868.85 | AI63: =AE63-AF63 -> 6688524.5 | AS63: 19 | AT63: =AX62 -> 5911080.8 | AU63: =AW63-AV63 -> 967877.89 | AV63: =AT63*(($R$29*30)/360) -> 41870.155 | AW63: =AW62 -> 1009748 | AX63: =AT63-AU63 -> 4943202.9 | AZ63: 19 | BA63: =BE62 -> 11811577 | BB63: =BD63-BC63 -> 617572.94 | BC63: =BA63*(($R$29*30)/360) -> 83665.338 | BD63: =BD62 -> 701238.28 | BE63: =BA63-BB63 -> 11194004 | BG63: 19 | BH63: =BL62 -> 14751274 | BI63: =BK63-BJ63 -> 443046.88 | BJ63: =BH63*(($R$29*30)/360) -> 104488.19 | BK63: =BK62 -> 547535.07 | BL63: =BH63-BI63 -> 14308227 | BN63: 19 | BO63: =BS62 -> 16506694 | BP63: =BR63-BQ63 -> 338829.86 | BQ63: =BO63*(($R$29*30)/360) -> 116922.41 | BR63: =BR62 -> 455752.28 | BS63: =BO63-BP63 -> 16167864
A64: 10 | B64: =F63 -> 393442.62 | C64: =B55/A53 -> 131147.54 | D64: =B64*(($B$38*30)/360) -> 4426.2295 | E64: =C64+D64 -> 135573.77 | F64: =B64-C64 -> 262295.08 | H64: 10 | I64: =M63 -> 1967213.1 | J64: =I55/H53 -> 131147.54 | K64: =I64*(($B$38*30)/360) -> 22131.147 | L64: =J64+K64 -> 153278.69 | M64: =I64-J64 -> 1836065.6 | O64: 10 | P64: =T63 -> 3540983.6 | Q64: =P55/O53 -> 131147.54 | R64: =P64*(($B$38*30)/360) -> 39836.065 | S64: =Q64+R64 -> 170983.61 | T64: =P64-Q64 -> 3409836 | W64: 10 | X64: =AB63 -> 5114754.1 | Y64: =$X$55/$W$53 -> 131147.54 | Z64: =X64*(($B$38*30)/360) -> 57540.983 | AA64: =Y64+Z64 -> 188688.52 | AB64: =X64-Y64 -> 4983606.5 | AD64: 10 | AE64: =AI63 -> 6688524.5 | AF64: =$X$55/$W$53 -> 131147.54 | AG64: =AE64*(($B$38*30)/360) -> 75245.901 | AH64: =AF64+AG64 -> 206393.44 | AI64: =AE64-AF64 -> 6557377 | AS64: 20 | AT64: =AX63 -> 4943202.9 | AU64: =AW64-AV64 -> 974733.69 | AV64: =AT64*(($R$29*30)/360) -> 35014.354 | AW64: =AW63 -> 1009748 | AX64: =AT64-AU64 -> 3968469.2 | AZ64: 20 | BA64: =BE63 -> 11194004 | BB64: =BD64-BC64 -> 621947.41 | BC64: =BA64*(($R$29*30)/360) -> 79290.863 | BD64: =BD63 -> 701238.28 | BE64: =BA64-BB64 -> 10572057 | BG64: 20 | BH64: =BL63 -> 14308227 | BI64: =BK64-BJ64 -> 446185.13 | BJ64: =BH64*(($R$29*30)/360) -> 101349.94 | BK64: =BK63 -> 547535.07 | BL64: =BH64-BI64 -> 13862042 | BN64: 20 | BO64: =BS63 -> 16167864 | BP64: =BR64-BQ64 -> 341229.91 | BQ64: =BO64*(($R$29*30)/360) -> 114522.37 | BR64: =BR63 -> 455752.28 | BS64: =BO64-BP64 -> 15826634
A65: 11 | B65: =F64 -> 262295.08 | C65: =B55/A53 -> 131147.54 | D65: =B65*(($B$38*30)/360) -> 2950.8196 | E65: =C65+D65 -> 134098.36 | F65: =B65-C65 -> 131147.54 | H65: 11 | I65: =M64 -> 1836065.6 | J65: =I55/H53 -> 131147.54 | K65: =I65*(($B$38*30)/360) -> 20655.738 | L65: =J65+K65 -> 151803.28 | M65: =I65-J65 -> 1704918 | O65: 11 | P65: =T64 -> 3409836 | Q65: =P55/O53 -> 131147.54 | R65: =P65*(($B$38*30)/360) -> 38360.655 | S65: =Q65+R65 -> 169508.2 | T65: =P65-Q65 -> 3278688.5 | W65: 11 | X65: =AB64 -> 4983606.5 | Y65: =$X$55/$W$53 -> 131147.54 | Z65: =X65*(($B$38*30)/360) -> 56065.573 | AA65: =Y65+Z65 -> 187213.11 | AB65: =X65-Y65 -> 4852459 | AD65: 11 | AE65: =AI64 -> 6557377 | AF65: =$X$55/$W$53 -> 131147.54 | AG65: =AE65*(($B$38*30)/360) -> 73770.491 | AH65: =AF65+AG65 -> 204918.03 | AI65: =AE65-AF65 -> 6426229.5 | AS65: 21 | AT65: =AX64 -> 3968469.2 | AU65: =AW65-AV65 -> 981638.05 | AV65: =AT65*(($R$29*30)/360) -> 28109.99 | AW65: =AW64 -> 1009748 | AX65: =AT65-AU65 -> 2986831.1 | AZ65: 21 | BA65: =BE64 -> 10572057 | BB65: =BD65-BC65 -> 626352.87 | BC65: =BA65*(($R$29*30)/360) -> 74885.403 | BD65: =BD64 -> 701238.28 | BE65: =BA65-BB65 -> 9945704 | BG65: 21 | BH65: =BL64 -> 13862042 | BI65: =BK65-BJ65 -> 449345.6 | BJ65: =BH65*(($R$29*30)/360) -> 98189.465 | BK65: =BK64 -> 547535.07 | BL65: =BH65-BI65 -> 13412697 | BN65: 21 | BO65: =BS64 -> 15826634 | BP65: =BR65-BQ65 -> 343646.96 | BQ65: =BO65*(($R$29*30)/360) -> 112105.32 | BR65: =BR64 -> 455752.28 | BS65: =BO65-BP65 -> 15482987
A66: 12 | B66: =F65 -> 131147.54 | C66: =B55/A53 -> 131147.54 | D66: =B66*(($B$38*30)/360) -> 1475.4098 | E66: =C66+D66 -> 132622.95 | F66: =B66-C66 -> -4.0745363e-10 | H66: 12 | I66: =M65 -> 1704918 | J66: =I55/H53 -> 131147.54 | K66: =I66*(($B$38*30)/360) -> 19180.328 | L66: =J66+K66 -> 150327.87 | M66: =I66-J66 -> 1573770.5 | O66: 12 | P66: =T65 -> 3278688.5 | Q66: =P55/O53 -> 131147.54 | R66: =P66*(($B$38*30)/360) -> 36885.246 | S66: =Q66+R66 -> 168032.79 | T66: =P66-Q66 -> 3147541 | W66: 12 | X66: =AB65 -> 4852459 | Y66: =$X$55/$W$53 -> 131147.54 | Z66: =X66*(($B$38*30)/360) -> 54590.164 | AA66: =Y66+Z66 -> 185737.7 | AB66: =X66-Y66 -> 4721311.4 | AD66: 12 | AE66: =AI65 -> 6426229.5 | AF66: =$X$55/$W$53 -> 131147.54 | AG66: =AE66*(($B$38*30)/360) -> 72295.081 | AH66: =AF66+AG66 -> 203442.62 | AI66: =AE66-AF66 -> 6295081.9 | AS66: 22 | AT66: =AX65 -> 2986831.1 | AU66: =AW66-AV66 -> 988591.32 | AV66: =AT66*(($R$29*30)/360) -> 21156.721 | AW66: =AW65 -> 1009748 | AX66: =AT66-AU66 -> 1998239.8 | AZ66: 22 | BA66: =BE65 -> 9945704 | BB66: =BD66-BC66 -> 630789.54 | BC66: =BA66*(($R$29*30)/360) -> 70448.736 | BD66: =BD65 -> 701238.28 | BE66: =BA66-BB66 -> 9314914.4 | BG66: 22 | BH66: =BL65 -> 13412697 | BI66: =BK66-BJ66 -> 452528.47 | BJ66: =BH66*(($R$29*30)/360) -> 95006.601 | BK66: =BK65 -> 547535.07 | BL66: =BH66-BI66 -> 12960168 | BN66: 22 | BO66: =BS65 -> 15482987 | BP66: =BR66-BQ66 -> 346081.12 | BQ66: =BO66*(($R$29*30)/360) -> 109671.16 | BR66: =BR65 -> 455752.28 | BS66: =BO66-BP66 -> 15136906
A67: итого: | C67: =SUM(C55:C66) -> 1573770.5 | D67: =SUM(D55:D66) -> 115081.97 | H67: 13 | I67: =M66 -> 1573770.5 | J67: =I55/H53 -> 131147.54 | K67: =I67*(($B$38*30)/360) -> 17704.918 | L67: =J67+K67 -> 148852.46 | M67: =I67-J67 -> 1442622.9 | O67: 13 | P67: =T66 -> 3147541 | Q67: =P55/O53 -> 131147.54 | R67: =P67*(($B$38*30)/360) -> 35409.836 | S67: =Q67+R67 -> 166557.38 | T67: =P67-Q67 -> 3016393.4 | W67: 13 | X67: =AB66 -> 4721311.4 | Y67: =$X$55/$W$53 -> 131147.54 | Z67: =X67*(($B$38*30)/360) -> 53114.754 | AA67: =Y67+Z67 -> 184262.29 | AB67: =X67-Y67 -> 4590163.9 | AD67: 13 | AE67: =AI66 -> 6295081.9 | AF67: =$X$55/$W$53 -> 131147.54 | AG67: =AE67*(($B$38*30)/360) -> 70819.672 | AH67: =AF67+AG67 -> 201967.21 | AI67: =AE67-AF67 -> 6163934.4 | AS67: 23 | AT67: =AX66 -> 1998239.8 | AU67: =AW67-AV67 -> 995593.84 | AV67: =AT67*(($R$29*30)/360) -> 14154.199 | AW67: =AW66 -> 1009748 | AX67: =AT67-AU67 -> 1002646 | AZ67: 23 | BA67: =BE66 -> 9314914.4 | BB67: =BD67-BC67 -> 635257.63 | BC67: =BA67*(($R$29*30)/360) -> 65980.644 | BD67: =BD66 -> 701238.28 | BE67: =BA67-BB67 -> 8679656.8 | BG67: 23 | BH67: =BL66 -> 12960168 | BI67: =BK67-BJ67 -> 455733.88 | BJ67: =BH67*(($R$29*30)/360) -> 91801.191 | BK67: =BK66 -> 547535.07 | BL67: =BH67-BI67 -> 12504434 | BN67: 23 | BO67: =BS66 -> 15136906 | BP67: =BR67-BQ67 -> 348532.53 | BQ67: =BO67*(($R$29*30)/360) -> 107219.75 | BR67: =BR66 -> 455752.28 | BS67: =BO67-BP67 -> 14788373
H68: 14 | I68: =M67 -> 1442622.9 | J68: =I55/H53 -> 131147.54 | K68: =I68*(($B$38*30)/360) -> 16229.508 | L68: =J68+K68 -> 147377.05 | M68: =I68-J68 -> 1311475.4 | O68: 14 | P68: =T67 -> 3016393.4 | Q68: =P55/O53 -> 131147.54 | R68: =P68*(($B$38*30)/360) -> 33934.426 | S68: =Q68+R68 -> 165081.97 | T68: =P68-Q68 -> 2885245.9 | W68: 14 | X68: =AB67 -> 4590163.9 | Y68: =$X$55/$W$53 -> 131147.54 | Z68: =X68*(($B$38*30)/360) -> 51639.344 | AA68: =Y68+Z68 -> 182786.88 | AB68: =X68-Y68 -> 4459016.4 | AD68: 14 | AE68: =AI67 -> 6163934.4 | AF68: =$X$55/$W$53 -> 131147.54 | AG68: =AE68*(($B$38*30)/360) -> 69344.262 | AH68: =AF68+AG68 -> 200491.8 | AI68: =AE68-AF68 -> 6032786.8 | AS68: 24 | AT68: =AX67 -> 1002646 | AU68: =AW68-AV68 -> 1002646 | AV68: =AT68*(($R$29*30)/360) -> 7102.0756 | AW68: =AW67 -> 1009748 | AX68: =AT68-AU68 -> -2.7939677e-09 | AZ68: 24 | BA68: =BE67 -> 8679656.8 | BB68: =BD68-BC68 -> 639757.38 | BC68: =BA68*(($R$29*30)/360) -> 61480.902 | BD68: =BD67 -> 701238.28 | BE68: =BA68-BB68 -> 8039899.4 | BG68: 24 | BH68: =BL67 -> 12504434 | BI68: =BK68-BJ68 -> 458961.99 | BJ68: =BH68*(($R$29*30)/360) -> 88573.076 | BK68: =BK67 -> 547535.07 | BL68: =BH68-BI68 -> 12045472 | BN68: 24 | BO68: =BS67 -> 14788373 | BP68: =BR68-BQ68 -> 351001.3 | BQ68: =BO68*(($R$29*30)/360) -> 104750.98 | BR68: =BR67 -> 455752.28 | BS68: =BO68-BP68 -> 14437372
H69: 15 | I69: =M68 -> 1311475.4 | J69: =I55/H53 -> 131147.54 | K69: =I69*(($B$38*30)/360) -> 14754.098 | L69: =J69+K69 -> 145901.64 | M69: =I69-J69 -> 1180327.9 | O69: 15 | P69: =T68 -> 2885245.9 | Q69: =P55/O53 -> 131147.54 | R69: =P69*(($B$38*30)/360) -> 32459.016 | S69: =Q69+R69 -> 163606.56 | T69: =P69-Q69 -> 2754098.3 | W69: 15 | X69: =AB68 -> 4459016.4 | Y69: =$X$55/$W$53 -> 131147.54 | Z69: =X69*(($B$38*30)/360) -> 50163.934 | AA69: =Y69+Z69 -> 181311.47 | AB69: =X69-Y69 -> 4327868.8 | AD69: 15 | AE69: =AI68 -> 6032786.8 | AF69: =$X$55/$W$53 -> 131147.54 | AG69: =AE69*(($B$38*30)/360) -> 67868.852 | AH69: =AF69+AG69 -> 199016.39 | AI69: =AE69-AF69 -> 5901639.3 | AS69: итого: | AU69: =SUM(AU45:AU68) -> 22213905 | AV69: =SUM(AV45:AV68) -> 2020048 | AZ69: 25 | BA69: =BE68 -> 8039899.4 | BB69: =BD69-BC69 -> 644288.99 | BC69: =BA69*(($R$29*30)/360) -> 56949.287 | BD69: =BD68 -> 701238.28 | BE69: =BA69-BB69 -> 7395610.4 | BG69: 25 | BH69: =BL68 -> 12045472 | BI69: =BK69-BJ69 -> 462212.97 | BJ69: =BH69*(($R$29*30)/360) -> 85322.095 | BK69: =BK68 -> 547535.07 | BL69: =BH69-BI69 -> 11583259 | BN69: 25 | BO69: =BS68 -> 14437372 | BP69: =BR69-BQ69 -> 353487.56 | BQ69: =BO69*(($R$29*30)/360) -> 102264.72 | BR69: =BR68 -> 455752.28 | BS69: =BO69-BP69 -> 14083884
H70: 16 | I70: =M69 -> 1180327.9 | J70: =I55/H53 -> 131147.54 | K70: =I70*(($B$38*30)/360) -> 13278.688 | L70: =J70+K70 -> 144426.23 | M70: =I70-J70 -> 1049180.3 | O70: 16 | P70: =T69 -> 2754098.3 | Q70: =P55/O53 -> 131147.54 | R70: =P70*(($B$38*30)/360) -> 30983.606 | S70: =Q70+R70 -> 162131.15 | T70: =P70-Q70 -> 2622950.8 | W70: 16 | X70: =AB69 -> 4327868.8 | Y70: =$X$55/$W$53 -> 131147.54 | Z70: =X70*(($B$38*30)/360) -> 48688.524 | AA70: =Y70+Z70 -> 179836.06 | AB70: =X70-Y70 -> 4196721.3 | AD70: 16 | AE70: =AI69 -> 5901639.3 | AF70: =$X$55/$W$53 -> 131147.54 | AG70: =AE70*(($B$38*30)/360) -> 66393.442 | AH70: =AF70+AG70 -> 197540.98 | AI70: =AE70-AF70 -> 5770491.8 | AZ70: 26 | BA70: =BE69 -> 7395610.4 | BB70: =BD70-BC70 -> 648852.7 | BC70: =BA70*(($R$29*30)/360) -> 52385.574 | BD70: =BD69 -> 701238.28 | BE70: =BA70-BB70 -> 6746757.7 | BG70: 26 | BH70: =BL69 -> 11583259 | BI70: =BK70-BJ70 -> 465486.98 | BJ70: =BH70*(($R$29*30)/360) -> 82048.086 | BK70: =BK69 -> 547535.07 | BL70: =BH70-BI70 -> 11117772 | BN70: 26 | BO70: =BS69 -> 14083884 | BP70: =BR70-BQ70 -> 355991.43 | BQ70: =BO70*(($R$29*30)/360) -> 99760.847 | BR70: =BR69 -> 455752.28 | BS70: =BO70-BP70 -> 13727893
H71: 17 | I71: =M70 -> 1049180.3 | J71: =I55/H53 -> 131147.54 | K71: =I71*(($B$38*30)/360) -> 11803.279 | L71: =J71+K71 -> 142950.82 | M71: =I71-J71 -> 918032.78 | O71: 17 | P71: =T70 -> 2622950.8 | Q71: =P55/O53 -> 131147.54 | R71: =P71*(($B$38*30)/360) -> 29508.197 | S71: =Q71+R71 -> 160655.74 | T71: =P71-Q71 -> 2491803.3 | W71: 17 | X71: =AB70 -> 4196721.3 | Y71: =$X$55/$W$53 -> 131147.54 | Z71: =X71*(($B$38*30)/360) -> 47213.114 | AA71: =Y71+Z71 -> 178360.65 | AB71: =X71-Y71 -> 4065573.7 | AD71: 17 | AE71: =AI70 -> 5770491.8 | AF71: =$X$55/$W$53 -> 131147.54 | AG71: =AE71*(($B$38*30)/360) -> 64918.032 | AH71: =AF71+AG71 -> 196065.57 | AI71: =AE71-AF71 -> 5639344.2 | AZ71: 27 | BA71: =BE70 -> 6746757.7 | BB71: =BD71-BC71 -> 653448.74 | BC71: =BA71*(($R$29*30)/360) -> 47789.534 | BD71: =BD70 -> 701238.28 | BE71: =BA71-BB71 -> 6093309 | BG71: 27 | BH71: =BL70 -> 11117772 | BI71: =BK71-BJ71 -> 468784.18 | BJ71: =BH71*(($R$29*30)/360) -> 78750.887 | BK71: =BK70 -> 547535.07 | BL71: =BH71-BI71 -> 10648988 | BN71: 27 | BO71: =BS70 -> 13727893 | BP71: =BR71-BQ71 -> 358513.04 | BQ71: =BO71*(($R$29*30)/360) -> 97239.241 | BR71: =BR70 -> 455752.28 | BS71: =BO71-BP71 -> 13369380
H72: 18 | I72: =M71 -> 918032.78 | J72: =I55/H53 -> 131147.54 | K72: =I72*(($B$38*30)/360) -> 10327.869 | L72: =J72+K72 -> 141475.41 | M72: =I72-J72 -> 786885.24 | O72: 18 | P72: =T71 -> 2491803.3 | Q72: =P55/O53 -> 131147.54 | R72: =P72*(($B$38*30)/360) -> 28032.787 | S72: =Q72+R72 -> 159180.33 | T72: =P72-Q72 -> 2360655.7 | W72: 18 | X72: =AB71 -> 4065573.7 | Y72: =$X$55/$W$53 -> 131147.54 | Z72: =X72*(($B$38*30)/360) -> 45737.705 | AA72: =Y72+Z72 -> 176885.24 | AB72: =X72-Y72 -> 3934426.2 | AD72: 18 | AE72: =AI71 -> 5639344.2 | AF72: =$X$55/$W$53 -> 131147.54 | AG72: =AE72*(($B$38*30)/360) -> 63442.622 | AH72: =AF72+AG72 -> 194590.16 | AI72: =AE72-AF72 -> 5508196.7 | AZ72: 28 | BA72: =BE71 -> 6093309 | BB72: =BD72-BC72 -> 658077.34 | BC72: =BA72*(($R$29*30)/360) -> 43160.939 | BD72: =BD71 -> 701238.28 | BE72: =BA72-BB72 -> 5435231.6 | BG72: 28 | BH72: =BL71 -> 10648988 | BI72: =BK72-BJ72 -> 472104.74 | BJ72: =BH72*(($R$29*30)/360) -> 75430.332 | BK72: =BK71 -> 547535.07 | BL72: =BH72-BI72 -> 10176883 | BN72: 28 | BO72: =BS71 -> 13369380 | BP72: =BR72-BQ72 -> 361052.5 | BQ72: =BO72*(($R$29*30)/360) -> 94699.774 | BR72: =BR71 -> 455752.28 | BS72: =BO72-BP72 -> 13008327
H73: 19 | I73: =M72 -> 786885.24 | J73: =I55/H53 -> 131147.54 | K73: =I73*(($B$38*30)/360) -> 8852.4589 | L73: =J73+K73 -> 140000 | M73: =I73-J73 -> 655737.7 | O73: 19 | P73: =T72 -> 2360655.7 | Q73: =P55/O53 -> 131147.54 | R73: =P73*(($B$38*30)/360) -> 26557.377 | S73: =Q73+R73 -> 157704.92 | T73: =P73-Q73 -> 2229508.2 | W73: 19 | X73: =AB72 -> 3934426.2 | Y73: =$X$55/$W$53 -> 131147.54 | Z73: =X73*(($B$38*30)/360) -> 44262.295 | AA73: =Y73+Z73 -> 175409.83 | AB73: =X73-Y73 -> 3803278.7 | AD73: 19 | AE73: =AI72 -> 5508196.7 | AF73: =$X$55/$W$53 -> 131147.54 | AG73: =AE73*(($B$38*30)/360) -> 61967.213 | AH73: =AF73+AG73 -> 193114.75 | AI73: =AE73-AF73 -> 5377049.1 | AZ73: 29 | BA73: =BE72 -> 5435231.6 | BB73: =BD73-BC73 -> 662738.72 | BC73: =BA73*(($R$29*30)/360) -> 38499.557 | BD73: =BD72 -> 701238.28 | BE73: =BA73-BB73 -> 4772492.9 | BG73: 29 | BH73: =BL72 -> 10176883 | BI73: =BK73-BJ73 -> 475448.81 | BJ73: =BH73*(($R$29*30)/360) -> 72086.257 | BK73: =BK72 -> 547535.07 | BL73: =BH73-BI73 -> 9701434.5 | BN73: 29 | BO73: =BS72 -> 13008327 | BP73: =BR73-BQ73 -> 363609.96 | BQ73: =BO73*(($R$29*30)/360) -> 92142.319 | BR73: =BR72 -> 455752.28 | BS73: =BO73-BP73 -> 12644717
H74: 20 | I74: =M73 -> 655737.7 | J74: =I55/H53 -> 131147.54 | K74: =I74*(($B$38*30)/360) -> 7377.0491 | L74: =J74+K74 -> 138524.59 | M74: =I74-J74 -> 524590.16 | O74: 20 | P74: =T73 -> 2229508.2 | Q74: =P55/O53 -> 131147.54 | R74: =P74*(($B$38*30)/360) -> 25081.967 | S74: =Q74+R74 -> 156229.51 | T74: =P74-Q74 -> 2098360.6 | W74: 20 | X74: =AB73 -> 3803278.7 | Y74: =$X$55/$W$53 -> 131147.54 | Z74: =X74*(($B$38*30)/360) -> 42786.885 | AA74: =Y74+Z74 -> 173934.42 | AB74: =X74-Y74 -> 3672131.1 | AD74: 20 | AE74: =AI73 -> 5377049.1 | AF74: =$X$55/$W$53 -> 131147.54 | AG74: =AE74*(($B$38*30)/360) -> 60491.803 | AH74: =AF74+AG74 -> 191639.34 | AI74: =AE74-AF74 -> 5245901.6 | AZ74: 30 | BA74: =BE73 -> 4772492.9 | BB74: =BD74-BC74 -> 667433.12 | BC74: =BA74*(($R$29*30)/360) -> 33805.158 | BD74: =BD73 -> 701238.28 | BE74: =BA74-BB74 -> 4105059.8 | BG74: 30 | BH74: =BL73 -> 9701434.5 | BI74: =BK74-BJ74 -> 478816.57 | BJ74: =BH74*(($R$29*30)/360) -> 68718.495 | BK74: =BK73 -> 547535.07 | BL74: =BH74-BI74 -> 9222618 | BN74: 30 | BO74: =BS73 -> 12644717 | BP74: =BR74-BQ74 -> 366185.53 | BQ74: =BO74*(($R$29*30)/360) -> 89566.748 | BR74: =BR73 -> 455752.28 | BS74: =BO74-BP74 -> 12278532
H75: 21 | I75: =M74 -> 524590.16 | J75: =I55/H53 -> 131147.54 | K75: =I75*(($B$38*30)/360) -> 5901.6393 | L75: =J75+K75 -> 137049.18 | M75: =I75-J75 -> 393442.62 | O75: 21 | P75: =T74 -> 2098360.6 | Q75: =P55/O53 -> 131147.54 | R75: =P75*(($B$38*30)/360) -> 23606.557 | S75: =Q75+R75 -> 154754.1 | T75: =P75-Q75 -> 1967213.1 | W75: 21 | X75: =AB74 -> 3672131.1 | Y75: =$X$55/$W$53 -> 131147.54 | Z75: =X75*(($B$38*30)/360) -> 41311.475 | AA75: =Y75+Z75 -> 172459.02 | AB75: =X75-Y75 -> 3540983.6 | AD75: 21 | AE75: =AI74 -> 5245901.6 | AF75: =$X$55/$W$53 -> 131147.54 | AG75: =AE75*(($B$38*30)/360) -> 59016.393 | AH75: =AF75+AG75 -> 190163.93 | AI75: =AE75-AF75 -> 5114754.1 | AZ75: 31 | BA75: =BE74 -> 4105059.8 | BB75: =BD75-BC75 -> 672160.77 | BC75: =BA75*(($R$29*30)/360) -> 29077.507 | BD75: =BD74 -> 701238.28 | BE75: =BA75-BB75 -> 3432899 | BG75: 31 | BH75: =BL74 -> 9222618 | BI75: =BK75-BJ75 -> 482208.19 | BJ75: =BH75*(($R$29*30)/360) -> 65326.877 | BK75: =BK74 -> 547535.07 | BL75: =BH75-BI75 -> 8740409.8 | BN75: 31 | BO75: =BS74 -> 12278532 | BP75: =BR75-BQ75 -> 368779.34 | BQ75: =BO75*(($R$29*30)/360) -> 86972.934 | BR75: =BR74 -> 455752.28 | BS75: =BO75-BP75 -> 11909753
H76: 22 | I76: =M75 -> 393442.62 | J76: =I55/H53 -> 131147.54 | K76: =I76*(($B$38*30)/360) -> 4426.2295 | L76: =J76+K76 -> 135573.77 | M76: =I76-J76 -> 262295.08 | O76: 22 | P76: =T75 -> 1967213.1 | Q76: =P55/O53 -> 131147.54 | R76: =P76*(($B$38*30)/360) -> 22131.147 | S76: =Q76+R76 -> 153278.69 | T76: =P76-Q76 -> 1836065.6 | W76: 22 | X76: =AB75 -> 3540983.6 | Y76: =$X$55/$W$53 -> 131147.54 | Z76: =X76*(($B$38*30)/360) -> 39836.065 | AA76: =Y76+Z76 -> 170983.61 | AB76: =X76-Y76 -> 3409836 | AD76: 22 | AE76: =AI75 -> 5114754.1 | AF76: =$X$55/$W$53 -> 131147.54 | AG76: =AE76*(($B$38*30)/360) -> 57540.983 | AH76: =AF76+AG76 -> 188688.52 | AI76: =AE76-AF76 -> 4983606.5 | AZ76: 32 | BA76: =BE75 -> 3432899 | BB76: =BD76-BC76 -> 676921.91 | BC76: =BA76*(($R$29*30)/360) -> 24316.368 | BD76: =BD75 -> 701238.28 | BE76: =BA76-BB76 -> 2755977.1 | BG76: 32 | BH76: =BL75 -> 8740409.8 | BI76: =BK76-BJ76 -> 485623.83 | BJ76: =BH76*(($R$29*30)/360) -> 61911.236 | BK76: =BK75 -> 547535.07 | BL76: =BH76-BI76 -> 8254785.9 | BN76: 32 | BO76: =BS75 -> 11909753 | BP76: =BR76-BQ76 -> 371391.53 | BQ76: =BO76*(($R$29*30)/360) -> 84360.747 | BR76: =BR75 -> 455752.28 | BS76: =BO76-BP76 -> 11538361
H77: 23 | I77: =M76 -> 262295.08 | J77: =I55/H53 -> 131147.54 | K77: =I77*(($B$38*30)/360) -> 2950.8196 | L77: =J77+K77 -> 134098.36 | M77: =I77-J77 -> 131147.54 | O77: 23 | P77: =T76 -> 1836065.6 | Q77: =P55/O53 -> 131147.54 | R77: =P77*(($B$38*30)/360) -> 20655.738 | S77: =Q77+R77 -> 151803.28 | T77: =P77-Q77 -> 1704918 | W77: 23 | X77: =AB76 -> 3409836 | Y77: =$X$55/$W$53 -> 131147.54 | Z77: =X77*(($B$38*30)/360) -> 38360.655 | AA77: =Y77+Z77 -> 169508.2 | AB77: =X77-Y77 -> 3278688.5 | AD77: 23 | AE77: =AI76 -> 4983606.5 | AF77: =$X$55/$W$53 -> 131147.54 | AG77: =AE77*(($B$38*30)/360) -> 56065.573 | AH77: =AF77+AG77 -> 187213.11 | AI77: =AE77-AF77 -> 4852459 | AZ77: 33 | BA77: =BE76 -> 2755977.1 | BB77: =BD77-BC77 -> 681716.77 | BC77: =BA77*(($R$29*30)/360) -> 19521.505 | BD77: =BD76 -> 701238.28 | BE77: =BA77-BB77 -> 2074260.3 | BG77: 33 | BH77: =BL76 -> 8254785.9 | BI77: =BK77-BJ77 -> 489063.67 | BJ77: =BH77*(($R$29*30)/360) -> 58471.4 | BK77: =BK76 -> 547535.07 | BL77: =BH77-BI77 -> 7765722.3 | BN77: 33 | BO77: =BS76 -> 11538361 | BP77: =BR77-BQ77 -> 374022.22 | BQ77: =BO77*(($R$29*30)/360) -> 81730.057 | BR77: =BR76 -> 455752.28 | BS77: =BO77-BP77 -> 11164339
H78: 24 | I78: =M77 -> 131147.54 | J78: =I55/H53 -> 131147.54 | K78: =I78*(($B$38*30)/360) -> 1475.4098 | L78: =J78+K78 -> 132622.95 | M78: =I78-J78 -> -8.7311491e-10 | O78: 24 | P78: =T77 -> 1704918 | Q78: =P55/O53 -> 131147.54 | R78: =P78*(($B$38*30)/360) -> 19180.328 | S78: =Q78+R78 -> 150327.87 | T78: =P78-Q78 -> 1573770.5 | W78: 24 | X78: =AB77 -> 3278688.5 | Y78: =$X$55/$W$53 -> 131147.54 | Z78: =X78*(($B$38*30)/360) -> 36885.246 | AA78: =Y78+Z78 -> 168032.79 | AB78: =X78-Y78 -> 3147541 | AD78: 24 | AE78: =AI77 -> 4852459 | AF78: =$X$55/$W$53 -> 131147.54 | AG78: =AE78*(($B$38*30)/360) -> 54590.164 | AH78: =AF78+AG78 -> 185737.7 | AI78: =AE78-AF78 -> 4721311.4 | AZ78: 34 | BA78: =BE77 -> 2074260.3 | BB78: =BD78-BC78 -> 686545.6 | BC78: =BA78*(($R$29*30)/360) -> 14692.677 | BD78: =BD77 -> 701238.28 | BE78: =BA78-BB78 -> 1387714.7 | BG78: 34 | BH78: =BL77 -> 7765722.3 | BI78: =BK78-BJ78 -> 492527.87 | BJ78: =BH78*(($R$29*30)/360) -> 55007.199 | BK78: =BK77 -> 547535.07 | BL78: =BH78-BI78 -> 7273194.4 | BN78: 34 | BO78: =BS77 -> 11164339 | BP78: =BR78-BQ78 -> 376671.54 | BQ78: =BO78*(($R$29*30)/360) -> 79080.733 | BR78: =BR77 -> 455752.28 | BS78: =BO78-BP78 -> 10787667
H79: итого: | J79: =SUM(J55:J78) -> 3147541 | K79: =SUM(K55:K78) -> 442622.95 | L79: =J79+K79 -> 3590163.9 | O79: 25 | P79: =T78 -> 1573770.5 | Q79: =P55/O53 -> 131147.54 | R79: =P79*(($B$38*30)/360) -> 17704.918 | S79: =Q79+R79 -> 148852.46 | T79: =P79-Q79 -> 1442622.9 | W79: 25 | X79: =AB78 -> 3147541 | Y79: =$X$55/$W$53 -> 131147.54 | Z79: =X79*(($B$38*30)/360) -> 35409.836 | AA79: =Y79+Z79 -> 166557.38 | AB79: =X79-Y79 -> 3016393.4 | AD79: 25 | AE79: =AI78 -> 4721311.4 | AF79: =$X$55/$W$53 -> 131147.54 | AG79: =AE79*(($B$38*30)/360) -> 53114.754 | AH79: =AF79+AG79 -> 184262.29 | AI79: =AE79-AF79 -> 4590163.9 | AZ79: 35 | BA79: =BE78 -> 1387714.7 | BB79: =BD79-BC79 -> 691408.63 | BC79: =BA79*(($R$29*30)/360) -> 9829.6461 | BD79: =BD78 -> 701238.28 | BE79: =BA79-BB79 -> 696306.11 | BG79: 35 | BH79: =BL78 -> 7273194.4 | BI79: =BK79-BJ79 -> 496016.61 | BJ79: =BH79*(($R$29*30)/360) -> 51518.46 | BK79: =BK78 -> 547535.07 | BL79: =BH79-BI79 -> 6777177.8 | BN79: 35 | BO79: =BS78 -> 10787667 | BP79: =BR79-BQ79 -> 379339.63 | BQ79: =BO79*(($R$29*30)/360) -> 76412.643 | BR79: =BR78 -> 455752.28 | BS79: =BO79-BP79 -> 10408328
O80: 26 | P80: =T79 -> 1442622.9 | Q80: =P55/O53 -> 131147.54 | R80: =P80*(($B$38*30)/360) -> 16229.508 | S80: =Q80+R80 -> 147377.05 | T80: =P80-Q80 -> 1311475.4 | W80: 26 | X80: =AB79 -> 3016393.4 | Y80: =$X$55/$W$53 -> 131147.54 | Z80: =X80*(($B$38*30)/360) -> 33934.426 | AA80: =Y80+Z80 -> 165081.97 | AB80: =X80-Y80 -> 2885245.9 | AD80: 26 | AE80: =AI79 -> 4590163.9 | AF80: =$X$55/$W$53 -> 131147.54 | AG80: =AE80*(($B$38*30)/360) -> 51639.344 | AH80: =AF80+AG80 -> 182786.88 | AI80: =AE80-AF80 -> 4459016.4 | AZ80: 36 | BA80: =BE79 -> 696306.11 | BB80: =BD80-BC80 -> 696306.11 | BC80: =BA80*(($R$29*30)/360) -> 4932.1683 | BD80: =BD79 -> 701238.28 | BE80: =BA80-BB80 -> 3.0267984e-09 | BG80: 36 | BH80: =BL79 -> 6777177.8 | BI80: =BK80-BJ80 -> 499530.06 | BJ80: =BH80*(($R$29*30)/360) -> 48005.009 | BK80: =BK79 -> 547535.07 | BL80: =BH80-BI80 -> 6277647.7 | BN80: 36 | BO80: =BS79 -> 10408328 | BP80: =BR80-BQ80 -> 382026.62 | BQ80: =BO80*(($R$29*30)/360) -> 73725.654 | BR80: =BR79 -> 455752.28 | BS80: =BO80-BP80 -> 10026301
O81: 27 | P81: =T80 -> 1311475.4 | Q81: =P55/O53 -> 131147.54 | R81: =P81*(($B$38*30)/360) -> 14754.098 | S81: =Q81+R81 -> 145901.64 | T81: =P81-Q81 -> 1180327.9 | W81: 27 | X81: =AB80 -> 2885245.9 | Y81: =$X$55/$W$53 -> 131147.54 | Z81: =X81*(($B$38*30)/360) -> 32459.016 | AA81: =Y81+Z81 -> 163606.56 | AB81: =X81-Y81 -> 2754098.3 | AD81: 27 | AE81: =AI80 -> 4459016.4 | AF81: =$X$55/$W$53 -> 131147.54 | AG81: =AE81*(($B$38*30)/360) -> 50163.934 | AH81: =AF81+AG81 -> 181311.47 | AI81: =AE81-AF81 -> 4327868.8 | AZ81: итого: | BB81: =SUM(BB45:BB80) -> 22213905 | BC81: =SUM(BC45:BC80) -> 3030673 | BG81: 37 | BH81: =BL80 -> 6277647.7 | BI81: =BK81-BJ81 -> 503068.4 | BJ81: =BH81*(($R$29*30)/360) -> 44466.671 | BK81: =BK80 -> 547535.07 | BL81: =BH81-BI81 -> 5774579.3 | BN81: 37 | BO81: =BS80 -> 10026301 | BP81: =BR81-BQ81 -> 384732.65 | BQ81: =BO81*(($R$29*30)/360) -> 71019.632 | BR81: =BR80 -> 455752.28 | BS81: =BO81-BP81 -> 9641568.3
O82: 28 | P82: =T81 -> 1180327.9 | Q82: =P55/O53 -> 131147.54 | R82: =P82*(($B$38*30)/360) -> 13278.688 | S82: =Q82+R82 -> 144426.23 | T82: =P82-Q82 -> 1049180.3 | W82: 28 | X82: =AB81 -> 2754098.3 | Y82: =$X$55/$W$53 -> 131147.54 | Z82: =X82*(($B$38*30)/360) -> 30983.606 | AA82: =Y82+Z82 -> 162131.15 | AB82: =X82-Y82 -> 2622950.8 | AD82: 28 | AE82: =AI81 -> 4327868.8 | AF82: =$X$55/$W$53 -> 131147.54 | AG82: =AE82*(($B$38*30)/360) -> 48688.524 | AH82: =AF82+AG82 -> 179836.06 | AI82: =AE82-AF82 -> 4196721.3 | BG82: 38 | BH82: =BL81 -> 5774579.3 | BI82: =BK82-BJ82 -> 506631.8 | BJ82: =BH82*(($R$29*30)/360) -> 40903.27 | BK82: =BK81 -> 547535.07 | BL82: =BH82-BI82 -> 5267947.5 | BN82: 38 | BO82: =BS81 -> 9641568.3 | BP82: =BR82-BQ82 -> 387457.84 | BQ82: =BO82*(($R$29*30)/360) -> 68294.442 | BR82: =BR81 -> 455752.28 | BS82: =BO82-BP82 -> 9254110.5
O83: 29 | P83: =T82 -> 1049180.3 | Q83: =P55/O53 -> 131147.54 | R83: =P83*(($B$38*30)/360) -> 11803.279 | S83: =Q83+R83 -> 142950.82 | T83: =P83-Q83 -> 918032.78 | W83: 29 | X83: =AB82 -> 2622950.8 | Y83: =$X$55/$W$53 -> 131147.54 | Z83: =X83*(($B$38*30)/360) -> 29508.196 | AA83: =Y83+Z83 -> 160655.74 | AB83: =X83-Y83 -> 2491803.3 | AD83: 29 | AE83: =AI82 -> 4196721.3 | AF83: =$X$55/$W$53 -> 131147.54 | AG83: =AE83*(($B$38*30)/360) -> 47213.114 | AH83: =AF83+AG83 -> 178360.65 | AI83: =AE83-AF83 -> 4065573.7 | BG83: 39 | BH83: =BL82 -> 5267947.5 | BI83: =BK83-BJ83 -> 510220.44 | BJ83: =BH83*(($R$29*30)/360) -> 37314.628 | BK83: =BK82 -> 547535.07 | BL83: =BH83-BI83 -> 4757727.1 | BN83: 39 | BO83: =BS82 -> 9254110.5 | BP83: =BR83-BQ83 -> 390202.33 | BQ83: =BO83*(($R$29*30)/360) -> 65549.949 | BR83: =BR82 -> 455752.28 | BS83: =BO83-BP83 -> 8863908.2
O84: 30 | P84: =T83 -> 918032.78 | Q84: =P55/O53 -> 131147.54 | R84: =P84*(($B$38*30)/360) -> 10327.869 | S84: =Q84+R84 -> 141475.41 | T84: =P84-Q84 -> 786885.24 | W84: 30 | X84: =AB83 -> 2491803.3 | Y84: =$X$55/$W$53 -> 131147.54 | Z84: =X84*(($B$38*30)/360) -> 28032.787 | AA84: =Y84+Z84 -> 159180.33 | AB84: =X84-Y84 -> 2360655.7 | AD84: 30 | AE84: =AI83 -> 4065573.7 | AF84: =$X$55/$W$53 -> 131147.54 | AG84: =AE84*(($B$38*30)/360) -> 45737.705 | AH84: =AF84+AG84 -> 176885.24 | AI84: =AE84-AF84 -> 3934426.2 | BG84: 40 | BH84: =BL83 -> 4757727.1 | BI84: =BK84-BJ84 -> 513834.5 | BJ84: =BH84*(($R$29*30)/360) -> 33700.567 | BK84: =BK83 -> 547535.07 | BL84: =BH84-BI84 -> 4243892.6 | BN84: 40 | BO84: =BS83 -> 8863908.2 | BP84: =BR84-BQ84 -> 392966.26 | BQ84: =BO84*(($R$29*30)/360) -> 62786.016 | BR84: =BR83 -> 455752.28 | BS84: =BO84-BP84 -> 8470941.9
O85: 31 | P85: =T84 -> 786885.24 | Q85: =P55/O53 -> 131147.54 | R85: =P85*(($B$38*30)/360) -> 8852.4589 | S85: =Q85+R85 -> 140000 | T85: =P85-Q85 -> 655737.7 | W85: 31 | X85: =AB84 -> 2360655.7 | Y85: =$X$55/$W$53 -> 131147.54 | Z85: =X85*(($B$38*30)/360) -> 26557.377 | AA85: =Y85+Z85 -> 157704.92 | AB85: =X85-Y85 -> 2229508.2 | AD85: 31 | AE85: =AI84 -> 3934426.2 | AF85: =$X$55/$W$53 -> 131147.54 | AG85: =AE85*(($B$38*30)/360) -> 44262.295 | AH85: =AF85+AG85 -> 175409.83 | AI85: =AE85-AF85 -> 3803278.7 | BG85: 41 | BH85: =BL84 -> 4243892.6 | BI85: =BK85-BJ85 -> 517474.16 | BJ85: =BH85*(($R$29*30)/360) -> 30060.906 | BK85: =BK84 -> 547535.07 | BL85: =BH85-BI85 -> 3726418.4 | BN85: 41 | BO85: =BS84 -> 8470941.9 | BP85: =BR85-BQ85 -> 395749.77 | BQ85: =BO85*(($R$29*30)/360) -> 60002.505 | BR85: =BR84 -> 455752.28 | BS85: =BO85-BP85 -> 8075192.1
O86: 32 | P86: =T85 -> 655737.7 | Q86: =P55/O53 -> 131147.54 | R86: =P86*(($B$38*30)/360) -> 7377.0491 | S86: =Q86+R86 -> 138524.59 | T86: =P86-Q86 -> 524590.16 | W86: 32 | X86: =AB85 -> 2229508.2 | Y86: =$X$55/$W$53 -> 131147.54 | Z86: =X86*(($B$38*30)/360) -> 25081.967 | AA86: =Y86+Z86 -> 156229.51 | AB86: =X86-Y86 -> 2098360.6 | AD86: 32 | AE86: =AI85 -> 3803278.7 | AF86: =$X$55/$W$53 -> 131147.54 | AG86: =AE86*(($B$38*30)/360) -> 42786.885 | AH86: =AF86+AG86 -> 173934.42 | AI86: =AE86-AF86 -> 3672131.1 | BG86: 42 | BH86: =BL85 -> 3726418.4 | BI86: =BK86-BJ86 -> 521139.61 | BJ86: =BH86*(($R$29*30)/360) -> 26395.464 | BK86: =BK85 -> 547535.07 | BL86: =BH86-BI86 -> 3205278.8 | BN86: 42 | BO86: =BS85 -> 8075192.1 | BP86: =BR86-BQ86 -> 398553 | BQ86: =BO86*(($R$29*30)/360) -> 57199.278 | BR86: =BR85 -> 455752.28 | BS86: =BO86-BP86 -> 7676639.1
O87: 33 | P87: =T86 -> 524590.16 | Q87: =P55/O53 -> 131147.54 | R87: =P87*(($B$38*30)/360) -> 5901.6393 | S87: =Q87+R87 -> 137049.18 | T87: =P87-Q87 -> 393442.62 | W87: 33 | X87: =AB86 -> 2098360.6 | Y87: =$X$55/$W$53 -> 131147.54 | Z87: =X87*(($B$38*30)/360) -> 23606.557 | AA87: =Y87+Z87 -> 154754.1 | AB87: =X87-Y87 -> 1967213.1 | AD87: 33 | AE87: =AI86 -> 3672131.1 | AF87: =$X$55/$W$53 -> 131147.54 | AG87: =AE87*(($B$38*30)/360) -> 41311.475 | AH87: =AF87+AG87 -> 172459.02 | AI87: =AE87-AF87 -> 3540983.6 | BG87: 43 | BH87: =BL86 -> 3205278.8 | BI87: =BK87-BJ87 -> 524831.01 | BJ87: =BH87*(($R$29*30)/360) -> 22704.058 | BK87: =BK86 -> 547535.07 | BL87: =BH87-BI87 -> 2680447.8 | BN87: 43 | BO87: =BS86 -> 7676639.1 | BP87: =BR87-BQ87 -> 401376.08 | BQ87: =BO87*(($R$29*30)/360) -> 54376.194 | BR87: =BR86 -> 455752.28 | BS87: =BO87-BP87 -> 7275263.1
O88: 34 | P88: =T87 -> 393442.62 | Q88: =P55/O53 -> 131147.54 | R88: =P88*(($B$38*30)/360) -> 4426.2295 | S88: =Q88+R88 -> 135573.77 | T88: =P88-Q88 -> 262295.08 | W88: 34 | X88: =AB87 -> 1967213.1 | Y88: =$X$55/$W$53 -> 131147.54 | Z88: =X88*(($B$38*30)/360) -> 22131.147 | AA88: =Y88+Z88 -> 153278.69 | AB88: =X88-Y88 -> 1836065.6 | AD88: 34 | AE88: =AI87 -> 3540983.6 | AF88: =$X$55/$W$53 -> 131147.54 | AG88: =AE88*(($B$38*30)/360) -> 39836.065 | AH88: =AF88+AG88 -> 170983.61 | AI88: =AE88-AF88 -> 3409836 | BG88: 44 | BH88: =BL87 -> 2680447.8 | BI88: =BK88-BJ88 -> 528548.56 | BJ88: =BH88*(($R$29*30)/360) -> 18986.505 | BK88: =BK87 -> 547535.07 | BL88: =BH88-BI88 -> 2151899.2 | BN88: 44 | BO88: =BS87 -> 7275263.1 | BP88: =BR88-BQ88 -> 404219.16 | BQ88: =BO88*(($R$29*30)/360) -> 51533.113 | BR88: =BR87 -> 455752.28 | BS88: =BO88-BP88 -> 6871043.9
O89: 35 | P89: =T88 -> 262295.08 | Q89: =P55/O53 -> 131147.54 | R89: =P89*(($B$38*30)/360) -> 2950.8196 | S89: =Q89+R89 -> 134098.36 | T89: =P89-Q89 -> 131147.54 | W89: 35 | X89: =AB88 -> 1836065.6 | Y89: =$X$55/$W$53 -> 131147.54 | Z89: =X89*(($B$38*30)/360) -> 20655.738 | AA89: =Y89+Z89 -> 151803.28 | AB89: =X89-Y89 -> 1704918 | AD89: 35 | AE89: =AI88 -> 3409836 | AF89: =$X$55/$W$53 -> 131147.54 | AG89: =AE89*(($B$38*30)/360) -> 38360.655 | AH89: =AF89+AG89 -> 169508.2 | AI89: =AE89-AF89 -> 3278688.5 | BG89: 45 | BH89: =BL88 -> 2151899.2 | BI89: =BK89-BJ89 -> 532292.45 | BJ89: =BH89*(($R$29*30)/360) -> 15242.62 | BK89: =BK88 -> 547535.07 | BL89: =BH89-BI89 -> 1619606.8 | BN89: 45 | BO89: =BS88 -> 6871043.9 | BP89: =BR89-BQ89 -> 407082.38 | BQ89: =BO89*(($R$29*30)/360) -> 48669.894 | BR89: =BR88 -> 455752.28 | BS89: =BO89-BP89 -> 6463961.5
O90: 36 | P90: =T89 -> 131147.54 | Q90: =P55/O53 -> 131147.54 | R90: =P90*(($B$38*30)/360) -> 1475.4098 | S90: =Q90+R90 -> 132622.95 | T90: =P90-Q90 -> -8.7311491e-10 | W90: 36 | X90: =AB89 -> 1704918 | Y90: =$X$55/$W$53 -> 131147.54 | Z90: =X90*(($B$38*30)/360) -> 19180.328 | AA90: =Y90+Z90 -> 150327.87 | AB90: =X90-Y90 -> 1573770.5 | AD90: 36 | AE90: =AI89 -> 3278688.5 | AF90: =$X$55/$W$53 -> 131147.54 | AG90: =AE90*(($B$38*30)/360) -> 36885.246 | AH90: =AF90+AG90 -> 168032.79 | AI90: =AE90-AF90 -> 3147541 | BG90: 46 | BH90: =BL89 -> 1619606.8 | BI90: =BK90-BJ90 -> 536062.85 | BJ90: =BH90*(($R$29*30)/360) -> 11472.215 | BK90: =BK89 -> 547535.07 | BL90: =BH90-BI90 -> 1083543.9 | BN90: 46 | BO90: =BS89 -> 6463961.5 | BP90: =BR90-BQ90 -> 409965.88 | BQ90: =BO90*(($R$29*30)/360) -> 45786.394 | BR90: =BR89 -> 455752.28 | BS90: =BO90-BP90 -> 6053995.6
O91: Итого: | Q91: =SUM(Q55:Q90) -> 4721311.4 | R91: =SUM(R55:R90) -> 982622.94 | W91: 37 | X91: =AB90 -> 1573770.5 | Y91: =$X$55/$W$53 -> 131147.54 | Z91: =X91*(($B$38*30)/360) -> 17704.918 | AA91: =Y91+Z91 -> 148852.46 | AB91: =X91-Y91 -> 1442622.9 | AD91: 37 | AE91: =AI90 -> 3147541 | AF91: =$X$55/$W$53 -> 131147.54 | AG91: =AE91*(($B$38*30)/360) -> 35409.836 | AH91: =AF91+AG91 -> 166557.38 | AI91: =AE91-AF91 -> 3016393.4 | BG91: 47 | BH91: =BL90 -> 1083543.9 | BI91: =BK91-BJ91 -> 539859.97 | BJ91: =BH91*(($R$29*30)/360) -> 7675.1029 | BK91: =BK90 -> 547535.07 | BL91: =BH91-BI91 -> 543683.97 | BN91: 47 | BO91: =BS90 -> 6053995.6 | BP91: =BR91-BQ91 -> 412869.81 | BQ91: =BO91*(($R$29*30)/360) -> 42882.469 | BR91: =BR90 -> 455752.28 | BS91: =BO91-BP91 -> 5641125.8
W92: 38 | X92: =AB91 -> 1442622.9 | Y92: =$X$55/$W$53 -> 131147.54 | Z92: =X92*(($B$38*30)/360) -> 16229.508 | AA92: =Y92+Z92 -> 147377.05 | AB92: =X92-Y92 -> 1311475.4 | AD92: 38 | AE92: =AI91 -> 3016393.4 | AF92: =$X$55/$W$53 -> 131147.54 | AG92: =AE92*(($B$38*30)/360) -> 33934.426 | AH92: =AF92+AG92 -> 165081.97 | AI92: =AE92-AF92 -> 2885245.9 | BG92: 48 | BH92: =BL91 -> 543683.97 | BI92: =BK92-BJ92 -> 543683.97 | BJ92: =BH92*(($R$29*30)/360) -> 3851.0948 | BK92: =BK91 -> 547535.07 | BL92: =BH92-BI92 -> 0 | BN92: 48 | BO92: =BS91 -> 5641125.8 | BP92: =BR92-BQ92 -> 415794.3 | BQ92: =BO92*(($R$29*30)/360) -> 39957.975 | BR92: =BR91 -> 455752.28 | BS92: =BO92-BP92 -> 5225331.5
W93: 39 | X93: =AB92 -> 1311475.4 | Y93: =$X$55/$W$53 -> 131147.54 | Z93: =X93*(($B$38*30)/360) -> 14754.098 | AA93: =Y93+Z93 -> 145901.64 | AB93: =X93-Y93 -> 1180327.9 | AD93: 39 | AE93: =AI92 -> 2885245.9 | AF93: =$X$55/$W$53 -> 131147.54 | AG93: =AE93*(($B$38*30)/360) -> 32459.016 | AH93: =AF93+AG93 -> 163606.56 | AI93: =AE93-AF93 -> 2754098.3 | BG93: итого: | BI93: =SUM(BI45:BI92) -> 22213905 | BJ93: =SUM(BJ45:BJ92) -> 4067778.3 | BN93: 49 | BO93: =BS92 -> 5225331.5 | BP93: =BR93-BQ93 -> 418739.51 | BQ93: =BO93*(($R$29*30)/360) -> 37012.765 | BR93: =BR92 -> 455752.28 | BS93: =BO93-BP93 -> 4806592
W94: 40 | X94: =AB93 -> 1180327.9 | Y94: =$X$55/$W$53 -> 131147.54 | Z94: =X94*(($B$38*30)/360) -> 13278.688 | AA94: =Y94+Z94 -> 144426.23 | AB94: =X94-Y94 -> 1049180.3 | AD94: 40 | AE94: =AI93 -> 2754098.3 | AF94: =$X$55/$W$53 -> 131147.54 | AG94: =AE94*(($B$38*30)/360) -> 30983.606 | AH94: =AF94+AG94 -> 162131.15 | AI94: =AE94-AF94 -> 2622950.8 | BN94: 50 | BO94: =BS93 -> 4806592 | BP94: =BR94-BQ94 -> 421705.58 | BQ94: =BO94*(($R$29*30)/360) -> 34046.693 | BR94: =BR93 -> 455752.28 | BS94: =BO94-BP94 -> 4384886.4
W95: 41 | X95: =AB94 -> 1049180.3 | Y95: =$X$55/$W$53 -> 131147.54 | Z95: =X95*(($B$38*30)/360) -> 11803.279 | AA95: =Y95+Z95 -> 142950.82 | AB95: =X95-Y95 -> 918032.78 | AD95: 41 | AE95: =AI94 -> 2622950.8 | AF95: =$X$55/$W$53 -> 131147.54 | AG95: =AE95*(($B$38*30)/360) -> 29508.196 | AH95: =AF95+AG95 -> 160655.74 | AI95: =AE95-AF95 -> 2491803.3 | BN95: 51 | BO95: =BS94 -> 4384886.4 | BP95: =BR95-BQ95 -> 424692.67 | BQ95: =BO95*(($R$29*30)/360) -> 31059.612 | BR95: =BR94 -> 455752.28 | BS95: =BO95-BP95 -> 3960193.7
W96: 42 | X96: =AB95 -> 918032.78 | Y96: =$X$55/$W$53 -> 131147.54 | Z96: =X96*(($B$38*30)/360) -> 10327.869 | AA96: =Y96+Z96 -> 141475.41 | AB96: =X96-Y96 -> 786885.24 | AD96: 42 | AE96: =AI95 -> 2491803.3 | AF96: =$X$55/$W$53 -> 131147.54 | AG96: =AE96*(($B$38*30)/360) -> 28032.787 | AH96: =AF96+AG96 -> 159180.33 | AI96: =AE96-AF96 -> 2360655.7 | BN96: 52 | BO96: =BS95 -> 3960193.7 | BP96: =BR96-BQ96 -> 427700.91 | BQ96: =BO96*(($R$29*30)/360) -> 28051.372 | BR96: =BR95 -> 455752.28 | BS96: =BO96-BP96 -> 3532492.8
W97: 43 | X97: =AB96 -> 786885.24 | Y97: =$X$55/$W$53 -> 131147.54 | Z97: =X97*(($B$38*30)/360) -> 8852.4589 | AA97: =Y97+Z97 -> 140000 | AB97: =X97-Y97 -> 655737.7 | AD97: 43 | AE97: =AI96 -> 2360655.7 | AF97: =$X$55/$W$53 -> 131147.54 | AG97: =AE97*(($B$38*30)/360) -> 26557.377 | AH97: =AF97+AG97 -> 157704.92 | AI97: =AE97-AF97 -> 2229508.2 | BN97: 53 | BO97: =BS96 -> 3532492.8 | BP97: =BR97-BQ97 -> 430730.45 | BQ97: =BO97*(($R$29*30)/360) -> 25021.824 | BR97: =BR96 -> 455752.28 | BS97: =BO97-BP97 -> 3101762.4
W98: 44 | X98: =AB97 -> 655737.7 | Y98: =$X$55/$W$53 -> 131147.54 | Z98: =X98*(($B$38*30)/360) -> 7377.0491 | AA98: =Y98+Z98 -> 138524.59 | AB98: =X98-Y98 -> 524590.16 | AD98: 44 | AE98: =AI97 -> 2229508.2 | AF98: =$X$55/$W$53 -> 131147.54 | AG98: =AE98*(($B$38*30)/360) -> 25081.967 | AH98: =AF98+AG98 -> 156229.51 | AI98: =AE98-AF98 -> 2098360.6 | BN98: 54 | BO98: =BS97 -> 3101762.4 | BP98: =BR98-BQ98 -> 433781.46 | BQ98: =BO98*(($R$29*30)/360) -> 21970.817 | BR98: =BR97 -> 455752.28 | BS98: =BO98-BP98 -> 2667980.9
W99: 45 | X99: =AB98 -> 524590.16 | Y99: =$X$55/$W$53 -> 131147.54 | Z99: =X99*(($B$38*30)/360) -> 5901.6393 | AA99: =Y99+Z99 -> 137049.18 | AB99: =X99-Y99 -> 393442.62 | AD99: 45 | AE99: =AI98 -> 2098360.6 | AF99: =$X$55/$W$53 -> 131147.54 | AG99: =AE99*(($B$38*30)/360) -> 23606.557 | AH99: =AF99+AG99 -> 154754.1 | AI99: =AE99-AF99 -> 1967213.1 | BN99: 55 | BO99: =BS98 -> 2667980.9 | BP99: =BR99-BQ99 -> 436854.08 | BQ99: =BO99*(($R$29*30)/360) -> 18898.198 | BR99: =BR98 -> 455752.28 | BS99: =BO99-BP99 -> 2231126.9
W100: 46 | X100: =AB99 -> 393442.62 | Y100: =$X$55/$W$53 -> 131147.54 | Z100: =X100*(($B$38*30)/360) -> 4426.2295 | AA100: =Y100+Z100 -> 135573.77 | AB100: =X100-Y100 -> 262295.08 | AD100: 46 | AE100: =AI99 -> 1967213.1 | AF100: =$X$55/$W$53 -> 131147.54 | AG100: =AE100*(($B$38*30)/360) -> 22131.147 | AH100: =AF100+AG100 -> 153278.69 | AI100: =AE100-AF100 -> 1836065.6 | BN100: 56 | BO100: =BS99 -> 2231126.9 | BP100: =BR100-BQ100 -> 439948.46 | BQ100: =BO100*(($R$29*30)/360) -> 15803.815 | BR100: =BR99 -> 455752.28 | BS100: =BO100-BP100 -> 1791178.4
W101: 47 | X101: =AB100 -> 262295.08 | Y101: =$X$55/$W$53 -> 131147.54 | Z101: =X101*(($B$38*30)/360) -> 2950.8196 | AA101: =Y101+Z101 -> 134098.36 | AB101: =X101-Y101 -> 131147.54 | AD101: 47 | AE101: =AI100 -> 1836065.6 | AF101: =$X$55/$W$53 -> 131147.54 | AG101: =AE101*(($B$38*30)/360) -> 20655.738 | AH101: =AF101+AG101 -> 151803.28 | AI101: =AE101-AF101 -> 1704918 | BN101: 57 | BO101: =BS100 -> 1791178.4 | BP101: =BR101-BQ101 -> 443064.76 | BQ101: =BO101*(($R$29*30)/360) -> 12687.514 | BR101: =BR100 -> 455752.28 | BS101: =BO101-BP101 -> 1348113.6
W102: 48 | X102: =AB101 -> 131147.54 | Y102: =$X$55/$W$53 -> 131147.54 | Z102: =X102*(($B$38*30)/360) -> 1475.4098 | AA102: =Y102+Z102 -> 132622.95 | AB102: =X102-Y102 -> -1.8044375e-09 | AD102: 48 | AE102: =AI101 -> 1704918 | AF102: =$X$55/$W$53 -> 131147.54 | AG102: =AE102*(($B$38*30)/360) -> 19180.328 | AH102: =AF102+AG102 -> 150327.87 | AI102: =AE102-AF102 -> 1573770.5 | BN102: 58 | BO102: =BS101 -> 1348113.6 | BP102: =BR102-BQ102 -> 446203.14 | BQ102: =BO102*(($R$29*30)/360) -> 9549.1382 | BR102: =BR101 -> 455752.28 | BS102: =BO102-BP102 -> 901910.48
W103: Итого: | Y103: =SUM(Y55:Y102) -> 6295081.9 | Z103: =SUM(Z55:Z102) -> 1735082 | AD103: 49 | AE103: =AI102 -> 1573770.5 | AF103: =$X$55/$W$53 -> 131147.54 | AG103: =AE103*(($B$38*30)/360) -> 17704.918 | AH103: =AF103+AG103 -> 148852.46 | AI103: =AE103-AF103 -> 1442622.9 | BN103: 59 | BO103: =BS102 -> 901910.48 | BP103: =BR103-BQ103 -> 449363.75 | BQ103: =BO103*(($R$29*30)/360) -> 6388.5326 | BR103: =BR102 -> 455752.28 | BS103: =BO103-BP103 -> 452546.74
AD104: 50 | AE104: =AI103 -> 1442622.9 | AF104: =$X$55/$W$53 -> 131147.54 | AG104: =AE104*(($B$38*30)/360) -> 16229.508 | AH104: =AF104+AG104 -> 147377.05 | AI104: =AE104-AF104 -> 1311475.4 | BN104: 60 | BO104: =BS103 -> 452546.74 | BP104: =BR104-BQ104 -> 452546.74 | BQ104: =BO104*(($R$29*30)/360) -> 3205.5394 | BR104: =BR103 -> 455752.28 | BS104: =BO104-BP104 -> 1.5133992e-08
AD105: 51 | AE105: =AI104 -> 1311475.4 | AF105: =$X$55/$W$53 -> 131147.54 | AG105: =AE105*(($B$38*30)/360) -> 14754.098 | AH105: =AF105+AG105 -> 145901.64 | AI105: =AE105-AF105 -> 1180327.9 | BN105: итого: | BP105: =SUM(BP45:BP104) -> 22213905 | BQ105: =SUM(BQ45:BQ104) -> 5131231.7
AD106: 52 | AE106: =AI105 -> 1180327.9 | AF106: =$X$55/$W$53 -> 131147.54 | AG106: =AE106*(($B$38*30)/360) -> 13278.688 | AH106: =AF106+AG106 -> 144426.23 | AI106: =AE106-AF106 -> 1049180.3
AD107: 53 | AE107: =AI106 -> 1049180.3 | AF107: =$X$55/$W$53 -> 131147.54 | AG107: =AE107*(($B$38*30)/360) -> 11803.279 | AH107: =AF107+AG107 -> 142950.82 | AI107: =AE107-AF107 -> 918032.78
...

Sheet Алтын Банк - Онай
A1: Оңай Алтын Банк
A4: Условия программы | D4: Срок / Взнос
A5: При полном подтверждении доходов | D5: до 20 лет / от 20%
A6: При частичном подтверждении доходов | D6: до 15 лет / от 20%
A7: Целевая группа | D7: Физические лица. Граждане РК, жители РК с Видом на Жительства до срока окончания, в случае стажа работы свыше 5 лет в КЗ то можно на мах срок займа
A8: Первоначальный взнос | D8: от 20% (При наличии дополнительного обеспечения возможно оформление кредита без первоначального взноса.)
A9: ь | D9: Минимум 1 млн – максимум 175 млн с ПД, 50 млн БПД
A10: Возраст Заемщика | D10: От 21 года до 65 лет на момент завершения срока кредита
A11: Подтверждение доходов | D11: Рассматриваются любые варианты подтверждения доходов. При ПВ от 20% возможность оформления с косвенным подтверждением дохода.
A12: РАСХОДЫ, СВЯЗАННЫЕ С ОФОРМЛЕНИЕМ КРЕДИТА
A13: Комиссия за рассмотрения кредитной заявки | D13: 0 тенге
A14: Комиссия за предоставление займа | D14: 0 тенге
A15: Возможно доп расходы клиента: | D15: Стоимость оценки 12-15 тыс. тг , регистрация Договоров Залога 3 тыс. тг (ЦОН), согласие завереное нотариусом 5 тыс. тг, страхование доп залога от 0,1% .
A16: Досрочное погашение | D16: 25 000 тенге до 12 месяцев, свыше 12 месяцев 0 тенге. Разрешается полное/частичное досрочное погашение в любое время. При частичном досрочном погашении сумма частичного погашения должна быть не менее суммы трех (очередных) ежемесячных платежей.
A17: Залогодатель | D17: Любое 3 лицо (до 70 лет должен закрыться кредит).
A18: Созаещик | D18: любое 3 лицо , не более 2 человек.
A22: Оңай (cтандарт) | I22: Алтын по акции с 01.03. по 15.04.2023г.
A23: Первоначальный взнос / срок | B23: 0% (доп.залог) | C23: 0.2 | D23: 0.3 | E23: 0.4 | F23: 0.5 | G23: 0.6 | H23: от 40% | I23: с подтв | N23: без подт-я
A24: 12 | B24: 2 | C24: 0.1 | H24: 0.1 | I24: 0.2 | J24: 0.3 | K24: 0.4 | L24: 0.5 | M24: 0.6 | N24: от 40%
A25: 13-24 | B25: 11.5 | C25: 8.5 | D25: 6.5 | E25: 4 | F25: 0.5 | G25: 0.1 | H25: 1.5 | I25: 0.1 | N25: 0.1
A26: 25-36 | B26: 15 | C26: 12 | D26: 11 | E26: 9.5 | F26: 7 | G26: 3 | H26: 7.5 | I26: 6.5 | J26: 5 | K26: 2 | L26: 0.1 | M26: 0.1 | N26: 2.5
A27: 37-60 | B27: 17.5 | C27: 16 | D27: 15 | E27: 14 | F27: 12 | G27: 10 | H27: 12 | I27: 10.5 | J27: 10 | K27: 7.5 | L27: 5 | M27: 1 | N27: 8
A28: 61-120 | B28: 18 | C28: 18 | D28: 17 | E28: 16 | F28: 15 | G28: 13 | H28: 12 | I28: 13.99 | J28: 13.5 | K28: 12 | L28: 10.5 | M28: 7.5 | N28: 12.3
A29: 121-180 | B29: 18 | C29: 18 | D29: 18 | E29: 17 | F29: 16 | G29: 15 | H29: 12 | I29: 13.99 | J29: 13.5 | K29: 13 | L29: 13 | M29: 13 | N29: 14
A30: 181-240 | B30: 18 | C30: 18 | D30: 18 | E30: 17.5 | F30: 16.5 | G30: 15.5 | H30: 14.5 | I30: 13.99 | J30: 13.5 | K30: 13 | L30: 13 | M30: 13 | N30: 14
A34: Оңай (Aкция)
A35: Первоначальный взнос / срок | B35: 0% (доп.залог) | C35: 0.2 | D35: 0.3 | E35: 0.4 | F35: 0.5 | G35: 0.6 | H35: от 40%
A36: 12 | B36: 0.1 | H36: 0.1
A37: 13-24 | B37: 7 | C37: 1.5 | D37: 0.5 | E37: 0.1 | F37: 0.1 | G37: 0.1 | H37: 0.1
A38: 25-36 | B38: 12 | C38: 8 | D38: 7 | E38: 5.5 | F38: 4 | G38: 1 | H38: 4.5
A39: 37-60 | B39: 15.5 | C39: 14 | D39: 13 | E39: 10 | F39: 8 | G39: 5 | H39: 9
A40: 61-120 | B40: 15.5 | C40: 15 | D40: 14 | E40: 12.5 | F40: 11 | G40: 9 | H40: 9.5
A41: 121-180 | B41: 16 | C41: 16 | D41: 15 | E41: 14 | F41: 13 | G41: 11 | H41: 9.5
A42: 181-240 | B42: 17 | C42: 16.5 | D42: 16 | E42: 15 | F42: 15 | G42: 13 | H42: 12.5
A44: Банк | C44: Оңай 1%
A45: доход | B45: с подтв
A46: ПВ | B46: 0% (доп.залог) | C46: 0.2 | D46: 0.3 | E46: 0.4 | F46: 0.5 | G46: 0.6
A47: 12 | B47: 0.1 | C47: 0.1
A48: 13-24 | B48: 9 | C48: 4 | D48: 3.5 | E48: 0.5 | F48: 0.1 | G48: 0.1
A49: 25-36 | B49: 12 | C49: 9 | D49: 8.5 | E49: 6 | F49: 3.5 | G49: 0.1
A50: 37-60 | B50: 15 | C50: 13 | D50: 12.5 | E50: 11 | F50: 9 | G50: 5
A51: 61-120 | B51: 15 | C51: 13 | D51: 12.5 | E51: 12 | F51: 12 | G51: 12
A52: 121-180 | B52: 15 | C52: 13 | D52: 12.5 | E52: 12 | F52: 12 | G52: 12
A53: 181-240 | B53: 17.5 | C53: 16.5 | D53: 16 | E53: 15.5 | F53: 15 | G53: 13.5
A55: Первый график (выгодный): по выбору клиента
A56: Стоимость недвижимости | C56: 30000000
A57: Стоимость квартиры в ипотеку | C57: =C56*1.05 -> 31500000
A58: Первоначальный взнос - % | C58: 0.2
A59: Первоначальный взнос | C59: =C57*C58 -> 6300000
A60: Сумма Займа | C60: =C57-C59 -> 25200000
A61: Ставка вознагражд годовая | C61: 0.145
A62: Срок кредита | C62: 180
A63: Ежемесячное погашение | C63: =ROUND(POWER((1+C61/12),C62)*C61/12/(POWER((1+C61/12),C62)-1)*C60,0) -> 344106
A64: Переплата за весь срок | C64: =C63*C62-C60 -> 36739080

Sheet Каскад ДДУ,готов.жилье
A1: Фридом - каскадные ставки на готовое жилье и ДДУ
A3: Условия программы: | D3: Срок / Взнос
A4: При полном подтверждении доходов | D4: от 20% до 20 лет
A5: Целевая группа | D5: Физические лица. Граждане РК, жители РК с Видом на Жительства НЕЛЬЗЯ
A6: Сумма кредита | D6: Минимум 3 млн – максимум 80 млн при Каскад ДДУ, максимум 35 млн при Каскад готовое жилье
A7: Возраст Заемщика | D7: От 21 года до 63 лет на момент завершения срока кредита
A8: РАСХОДЫ, СВЯЗАННЫЕ С ОФОРМЛЕНИЕМ КРЕДИТА
A9: Комиссия за рассмотрения кредитной заявки | D9: 30 000 тенге
A10: Досрочное погашение | D10: При сокращений суммы платежа-без комисий. При сокращении срока - 1 раз 10.000 тг,последующие 20.000 тг.
A12: СТАНДАРТ
A13: Срок кредитования | B13: Размер первоначального взноса
B14: 0.2 | C14: 0.3 | D14: 0.4 | E14: 50% и более
A15: С 1 года до 3 лет (включительно) | B15: 16 | C15: 15.5 | D15: 15 | E15: 14.5
A16: С 3х лет до 5 лет (включительно) | B16: 18 | C16: 17.5 | D16: 17 | E16: 16.5
A17: На оставшийся срок (до 20 лет) | B17: 24 | C17: 24 | D17: 23 | E17: 23
A20: Стоимость квартиры | B20: 30000000 | C20: ← | D20: Менять только желтые поля!
A21: Надбавка | B21: 0.05
A22: Стоимость квартиры в ипотеку | B22: =B20*1.05 -> 31500000
A23: Первоначальный взнос - % | B23: 0.5
A24: Первоначальный взнос | B24: =B22*B23 -> 15750000
A25: Сумма Займа | B25: =B22-B24 -> 15750000
A26: Срок кредита | B26: 180 | C26: Ежемесячное погашение
A27: Ставка - с 1 до 36 месяцев | B27: =IF(B23>=0.5,14.5,IF(B23>=0.4,15,IF(B23>=0.3,15.5,16))) -> 14.5 | C27: =AVERAGE(J59:J94) -> 202246.91
A28: Ставка - с 37 до 60 месяцев | B28: =IF(B23>=0.5,16.5,IF(B23>=0.4,17,IF(B23>=0.3,17.5,18))) -> 16.5 | C28: =AVERAGE(J95:J118) -> 231096.77
A29: Ставка - с 61 до 240 месяцев | B29: =IF(B23>=0.5,23,IF(B23>=0.4,23,IF(B23>=0.3,24,24))) -> 23 | C29: =J127 -> 312111.99
A30: ГЭСВ | B30: =D51 -> 0.33996192
A31: Переплата за весь срок | B31: =C27*36+C28*24+C29*(B26-60)-B25 -> 34530651
B40: Условия компенсации | J40: Плавающие ставки | P40: Условия компенсации | X40: Плавающие ставки
B41: ПВ | C41: =B23*100 -> 50 | D41: =D48/(100-C41)% -> 31500000 | I41: 0 | J41: 1 день | K41: =K44 -> 23 | P41: ПВ | Q41: =J23*100 -> 0 | R41: =R48/(100-Q41)% -> 0 | W41: 0 | X41: 1 день | Y41: =Y44 -> 0
B42: Компенсация | C42: 10 | D42: =D41*C42% -> 3150000 | I42: 36 | J42: срок 1-3 | K42: =B27 -> 14.5 | P42: Компенсация | Q42: 10 | R42: =R41*Q42% -> 0 | W42: 36 | X42: срок 1-3 | Y42: =J27 -> 0
I43: 60 | J43: срок 4-5 | K43: =B28 -> 16.5 | W43: 60 | X43: срок 4-5 | Y43: =J28 -> 0
I44: 240 | J44: свыше 5 | K44: =B29 -> 23 | L44: 2 | W44: 240 | X44: свыше 5 | Y44: =J29 -> 0 | Z44: 2
L45: 3 | Z45: 3
L46: 4 | Z46: 4
C48: Сумма и валюта займа | D48: =B25 -> 15750000 | J48: ГЭСВ | K48: =XIRR(J58:J298,B58:B298) -> 0.25342088 | Q48: Сумма и валюта займа | R48: =J25 -> 0 | X48: ГЭСВ | Y48: =XIRR(X58:X298,P58:P298) -> #NUM!
C49: Срок займа | D49: =B26 -> 180 | J49: Общая переплата | K49: =SUM(I59:I298) -> 18669742 | Q49: Срок займа | R49: =J26 -> 0 | X49: Общая переплата | Y49: =SUM(W59:W298) -> #NUM!
C50: Ставка вознаграждения | D50: =K41 -> 23 | J50: дюрация | K50: 60 | Q50: Ставка вознаграждения | R50: =Y41 -> 0 | X50: дюрация | Y50: 60
C51: ГЭСВ | D51: =XIRR(C58:C298,B58:B298) -> 0.33996192 | J51: ГЭСВ на дюрацию | K51: =XIRR(OFFSET(L58,0,0,K50+1,1),OFFSET(B58,0,0,K50+1,1)) -> 0.24106507 | Q51: ГЭСВ | R51: =XIRR(Q58:Q298,P58:P298) -> #NUM! | X51: ГЭСВ на дюрацию | Y51: =XIRR(OFFSET(Z58,0,0,Y50+1,1),OFFSET(P58,0,0,Y50+1,1)) -> #NUM!
C52: сумма аннуитета | D52: =-PMT(K44%/12,D49,D48) -> 312111.99 | Q52: сумма аннуитета | R52: =-PMT(Y44%/12,R49,R48) -> #NUM!
C53: переплата | D53: =SUM(E59:E298) -> 24569250 | J53: остаток ОД на дюрацию | K53: =OFFSET(F58,K50,0,1,1) -> 14615557 | Q53: переплата | R53: =SUM(S59:S298) -> #NUM! | X53: остаток ОД на дюрацию | Y53: =OFFSET(T58,Y50,0,1,1) -> #NUM!
A55: СТАНДАРТНЫЙ ГРАФИК | I55: НОВЫЙ ГРАФИК | O55: СТАНДАРТНЫЙ ГРАФИК | W55: НОВЫЙ ГРАФИК
K56: =SUM(K59:K298) -> -5899508.4 | L56: =XIRR(L58:L118,B58:B118) -> 0.24106507 | Y56: =SUM(Y59:Y298) -> #NUM! | Z56: =XIRR(Z58:Z118,P58:P118) -> #NUM!
A57: № п/п/ № р/н | B57: Дата платежа/ Төлем күні | C57: Платеж | D57: ОД | E57: % | F57: Остаток ОД | I57: % под новые ставки | J57: Новый еж.платеж | K57: экономия в Платеже внутри займа | O57: № п/п/ № р/н | P57: Дата платежа/ Төлем күні | Q57: Платеж | R57: ОД | S57: % | T57: Остаток ОД | W57: % под новые ставки | X57: Новый еж.платеж | Y57: экономия в Платеже внутри займа
B58: 44953 | C58: =-D48+D42 -> -12600000 | F58: =D48 -> 15750000 | J58: =C58 -> -12600000 | L58: =J58 -> -12600000 | P58: 44953 | Q58: =-R48+R42 -> 0 | T58: =R48 -> 0 | X58: =Q58 -> 0 | Z58: =X58 -> 0
A59: 1 | B59: 44984 | C59: =D52 -> 312111.99 | D59: =C59-E59 -> 10236.995 | E59: =F58*$K$41%/12 -> 301875 | F59: =F58-D59 -> 15739763 | H59: =IF(A59<=$I$42,$K$42,IF(A59<=$I$43,$K$43,IF(A59<=$I$44,$K$44,$K$45))) -> 14.5 | I59: =F58*K41%/360+F58*K42%/360*29 -> 194031.25 | J59: =D59+I59 -> 204268.24 | K59: =J59-C59 -> -107843.75 | L59: =J59 -> 204268.24 | O59: 1 | P59: 44984 | Q59: =R52 -> #NUM! | R59: =Q59-S59 -> #NUM! | S59: =T58*$K$41%/12 -> 0 | T59: =T58-R59 -> #NUM! | V59: =IF(O59<=$I$42,$K$42,IF(O59<=$I$43,$K$43,IF(O59<=$I$44,$K$44,$K$45))) -> 14.5 | W59: =T58*Y41%/360+T58*Y42%/360*29 -> 0 | X59: =R59+W59 -> #NUM! | Y59: =X59-Q59 -> #NUM! | Z59: =X59 -> #NUM!
A60: 2 | B60: 45012 | C60: =C59 -> 312111.99 | D60: =C60-E60 -> 10433.204 | E60: =F59*$K$41%/12 -> 301678.79 | F60: =F59-D60 -> 15729330 | H60: =IF(A60<=$I$42,$K$42,IF(A60<=$I$43,$K$43,IF(A60<=$I$44,$K$44,$K$45))) -> 14.5 | I60: =F59*H60%/12 -> 190188.8 | J60: =D60+I60 -> 200622.01 | K60: =J60-C60 -> -111489.99 | L60: =J60+IF(A60=$K$50,F60,0) -> 200622.01 | O60: 2 | P60: 45012 | Q60: =Q59 -> #NUM! | R60: =Q60-S60 -> #NUM! | S60: =T59*$K$41%/12 -> #NUM! | T60: =T59-R60 -> #NUM! | V60: =IF(O60<=$I$42,$K$42,IF(O60<=$I$43,$K$43,IF(O60<=$I$44,$K$44,$K$45))) -> 14.5 | W60: =T59*V60%/12 -> #NUM! | X60: =R60+W60 -> #NUM! | Y60: =X60-Q60 -> #NUM! | Z60: =X60+IF(O60=$K$50,T60,0) -> #NUM!
A61: 3 | B61: 45043 | C61: =C60 -> 312111.99 | D61: =C61-E61 -> 10633.174 | E61: =F60*$K$41%/12 -> 301478.82 | F61: =F60-D61 -> 15718697 | H61: =IF(A61<=$I$42,$K$42,IF(A61<=$I$43,$K$43,IF(A61<=$I$44,$K$44,$K$45))) -> 14.5 | I61: =F60*H61%/12 -> 190062.74 | J61: =D61+I61 -> 200695.91 | K61: =J61-C61 -> -111416.09 | L61: =J61+IF(A61=$K$50,F61,0) -> 200695.91 | O61: 3 | P61: 45043 | Q61: =Q60 -> #NUM! | R61: =Q61-S61 -> #NUM! | S61: =T60*$K$41%/12 -> #NUM! | T61: =T60-R61 -> #NUM! | V61: =IF(O61<=$I$42,$K$42,IF(O61<=$I$43,$K$43,IF(O61<=$I$44,$K$44,$K$45))) -> 14.5 | W61: =T60*V61%/12 -> #NUM! | X61: =R61+W61 -> #NUM! | Y61: =X61-Q61 -> #NUM! | Z61: =X61+IF(O61=$K$50,T61,0) -> #NUM!
A62: 4 | B62: 45075 | C62: =C61 -> 312111.99 | D62: =C62-E62 -> 10836.976 | E62: =F61*$K$41%/12 -> 301275.02 | F62: =F61-D62 -> 15707860 | H62: =IF(A62<=$I$42,$K$42,IF(A62<=$I$43,$K$43,IF(A62<=$I$44,$K$44,$K$45))) -> 14.5 | I62: =F61*H62%/12 -> 189934.25 | J62: =D62+I62 -> 200771.23 | K62: =J62-C62 -> -111340.77 | L62: =J62+IF(A62=$K$50,F62,0) -> 200771.23 | O62: 4 | P62: 45075 | Q62: =Q61 -> #NUM! | R62: =Q62-S62 -> #NUM! | S62: =T61*$K$41%/12 -> #NUM! | T62: =T61-R62 -> #NUM! | V62: =IF(O62<=$I$42,$K$42,IF(O62<=$I$43,$K$43,IF(O62<=$I$44,$K$44,$K$45))) -> 14.5 | W62: =T61*V62%/12 -> #NUM! | X62: =R62+W62 -> #NUM! | Y62: =X62-Q62 -> #NUM! | Z62: =X62+IF(O62=$K$50,T62,0) -> #NUM!
A63: 5 | B63: 45104 | C63: =C62 -> 312111.99 | D63: =C63-E63 -> 11044.685 | E63: =F62*$K$41%/12 -> 301067.31 | F63: =F62-D63 -> 15696815 | H63: =IF(A63<=$I$42,$K$42,IF(A63<=$I$43,$K$43,IF(A63<=$I$44,$K$44,$K$45))) -> 14.5 | I63: =F62*H63%/12 -> 189803.3 | J63: =D63+I63 -> 200847.99 | K63: =J63-C63 -> -111264.01 | L63: =J63+IF(A63=$K$50,F63,0) -> 200847.99 | O63: 5 | P63: 45104 | Q63: =Q62 -> #NUM! | R63: =Q63-S63 -> #NUM! | S63: =T62*$K$41%/12 -> #NUM! | T63: =T62-R63 -> #NUM! | V63: =IF(O63<=$I$42,$K$42,IF(O63<=$I$43,$K$43,IF(O63<=$I$44,$K$44,$K$45))) -> 14.5 | W63: =T62*V63%/12 -> #NUM! | X63: =R63+W63 -> #NUM! | Y63: =X63-Q63 -> #NUM! | Z63: =X63+IF(O63=$K$50,T63,0) -> #NUM!
A64: 6 | B64: 45134 | C64: =C63 -> 312111.99 | D64: =C64-E64 -> 11256.375 | E64: =F63*$K$41%/12 -> 300855.62 | F64: =F63-D64 -> 15685559 | H64: =IF(A64<=$I$42,$K$42,IF(A64<=$I$43,$K$43,IF(A64<=$I$44,$K$44,$K$45))) -> 14.5 | I64: =F63*H64%/12 -> 189669.85 | J64: =D64+I64 -> 200926.22 | K64: =J64-C64 -> -111185.77 | L64: =J64+IF(A64=$K$50,F64,0) -> 200926.22 | O64: 6 | P64: 45134 | Q64: =Q63 -> #NUM! | R64: =Q64-S64 -> #NUM! | S64: =T63*$K$41%/12 -> #NUM! | T64: =T63-R64 -> #NUM! | V64: =IF(O64<=$I$42,$K$42,IF(O64<=$I$43,$K$43,IF(O64<=$I$44,$K$44,$K$45))) -> 14.5 | W64: =T63*V64%/12 -> #NUM! | X64: =R64+W64 -> #NUM! | Y64: =X64-Q64 -> #NUM! | Z64: =X64+IF(O64=$K$50,T64,0) -> #NUM!
A65: 7 | B65: 45166 | C65: =C64 -> 312111.99 | D65: =C65-E65 -> 11472.122 | E65: =F64*$K$41%/12 -> 300639.87 | F65: =F64-D65 -> 15674086 | H65: =IF(A65<=$I$42,$K$42,IF(A65<=$I$43,$K$43,IF(A65<=$I$44,$K$44,$K$45))) -> 14.5 | I65: =F64*H65%/12 -> 189533.83 | J65: =D65+I65 -> 201005.95 | K65: =J65-C65 -> -111106.04 | L65: =J65+IF(A65=$K$50,F65,0) -> 201005.95 | O65: 7 | P65: 45166 | Q65: =Q64 -> #NUM! | R65: =Q65-S65 -> #NUM! | S65: =T64*$K$41%/12 -> #NUM! | T65: =T64-R65 -> #NUM! | V65: =IF(O65<=$I$42,$K$42,IF(O65<=$I$43,$K$43,IF(O65<=$I$44,$K$44,$K$45))) -> 14.5 | W65: =T64*V65%/12 -> #NUM! | X65: =R65+W65 -> #NUM! | Y65: =X65-Q65 -> #NUM! | Z65: =X65+IF(O65=$K$50,T65,0) -> #NUM!
A66: 8 | B66: 45196 | C66: =C65 -> 312111.99 | D66: =C66-E66 -> 11692.004 | E66: =F65*$K$41%/12 -> 300419.99 | F66: =F65-D66 -> 15662394 | H66: =IF(A66<=$I$42,$K$42,IF(A66<=$I$43,$K$43,IF(A66<=$I$44,$K$44,$K$45))) -> 14.5 | I66: =F65*H66%/12 -> 189395.21 | J66: =D66+I66 -> 201087.22 | K66: =J66-C66 -> -111024.78 | L66: =J66+IF(A66=$K$50,F66,0) -> 201087.22 | O66: 8 | P66: 45196 | Q66: =Q65 -> #NUM! | R66: =Q66-S66 -> #NUM! | S66: =T65*$K$41%/12 -> #NUM! | T66: =T65-R66 -> #NUM! | V66: =IF(O66<=$I$42,$K$42,IF(O66<=$I$43,$K$43,IF(O66<=$I$44,$K$44,$K$45))) -> 14.5 | W66: =T65*V66%/12 -> #NUM! | X66: =R66+W66 -> #NUM! | Y66: =X66-Q66 -> #NUM! | Z66: =X66+IF(O66=$K$50,T66,0) -> #NUM!
A67: 9 | B67: 45226 | C67: =C66 -> 312111.99 | D67: =C67-E67 -> 11916.101 | E67: =F66*$K$41%/12 -> 300195.89 | F67: =F66-D67 -> 15650478 | H67: =IF(A67<=$I$42,$K$42,IF(A67<=$I$43,$K$43,IF(A67<=$I$44,$K$44,$K$45))) -> 14.5 | I67: =F66*H67%/12 -> 189253.93 | J67: =D67+I67 -> 201170.03 | K67: =J67-C67 -> -110941.96 | L67: =J67+IF(A67=$K$50,F67,0) -> 201170.03 | O67: 9 | P67: 45226 | Q67: =Q66 -> #NUM! | R67: =Q67-S67 -> #NUM! | S67: =T66*$K$41%/12 -> #NUM! | T67: =T66-R67 -> #NUM! | V67: =IF(O67<=$I$42,$K$42,IF(O67<=$I$43,$K$43,IF(O67<=$I$44,$K$44,$K$45))) -> 14.5 | W67: =T66*V67%/12 -> #NUM! | X67: =R67+W67 -> #NUM! | Y67: =X67-Q67 -> #NUM! | Z67: =X67+IF(O67=$K$50,T67,0) -> #NUM!
A68: 10 | B68: 45257 | C68: =C67 -> 312111.99 | D68: =C68-E68 -> 12144.493 | E68: =F67*$K$41%/12 -> 299967.5 | F68: =F67-D68 -> 15638334 | H68: =IF(A68<=$I$42,$K$42,IF(A68<=$I$43,$K$43,IF(A68<=$I$44,$K$44,$K$45))) -> 14.5 | I68: =F67*H68%/12 -> 189109.95 | J68: =D68+I68 -> 201254.44 | K68: =J68-C68 -> -110857.56 | L68: =J68+IF(A68=$K$50,F68,0) -> 201254.44 | O68: 10 | P68: 45257 | Q68: =Q67 -> #NUM! | R68: =Q68-S68 -> #NUM! | S68: =T67*$K$41%/12 -> #NUM! | T68: =T67-R68 -> #NUM! | V68: =IF(O68<=$I$42,$K$42,IF(O68<=$I$43,$K$43,IF(O68<=$I$44,$K$44,$K$45))) -> 14.5 | W68: =T67*V68%/12 -> #NUM! | X68: =R68+W68 -> #NUM! | Y68: =X68-Q68 -> #NUM! | Z68: =X68+IF(O68=$K$50,T68,0) -> #NUM!
A69: 11 | B69: 45287 | C69: =C68 -> 312111.99 | D69: =C69-E69 -> 12377.262 | E69: =F68*$K$41%/12 -> 299734.73 | F69: =F68-D69 -> 15625957 | H69: =IF(A69<=$I$42,$K$42,IF(A69<=$I$43,$K$43,IF(A69<=$I$44,$K$44,$K$45))) -> 14.5 | I69: =F68*H69%/12 -> 188963.2 | J69: =D69+I69 -> 201340.46 | K69: =J69-C69 -> -110771.53 | L69: =J69+IF(A69=$K$50,F69,0) -> 201340.46 | O69: 11 | P69: 45287 | Q69: =Q68 -> #NUM! | R69: =Q69-S69 -> #NUM! | S69: =T68*$K$41%/12 -> #NUM! | T69: =T68-R69 -> #NUM! | V69: =IF(O69<=$I$42,$K$42,IF(O69<=$I$43,$K$43,IF(O69<=$I$44,$K$44,$K$45))) -> 14.5 | W69: =T68*V69%/12 -> #NUM! | X69: =R69+W69 -> #NUM! | Y69: =X69-Q69 -> #NUM! | Z69: =X69+IF(O69=$K$50,T69,0) -> #NUM!
A70: 12 | B70: 45320 | C70: =C69 -> 312111.99 | D70: =C70-E70 -> 12614.493 | E70: =F69*$K$41%/12 -> 299497.5 | F70: =F69-D70 -> 15613342 | H70: =IF(A70<=$I$42,$K$42,IF(A70<=$I$43,$K$43,IF(A70<=$I$44,$K$44,$K$45))) -> 14.5 | I70: =F69*H70%/12 -> 188813.64 | J70: =D70+I70 -> 201428.14 | K70: =J70-C70 -> -110683.86 | L70: =J70+IF(A70=$K$50,F70,0) -> 201428.14 | O70: 12 | P70: 45320 | Q70: =Q69 -> #NUM! | R70: =Q70-S70 -> #NUM! | S70: =T69*$K$41%/12 -> #NUM! | T70: =T69-R70 -> #NUM! | V70: =IF(O70<=$I$42,$K$42,IF(O70<=$I$43,$K$43,IF(O70<=$I$44,$K$44,$K$45))) -> 14.5 | W70: =T69*V70%/12 -> #NUM! | X70: =R70+W70 -> #NUM! | Y70: =X70-Q70 -> #NUM! | Z70: =X70+IF(O70=$K$50,T70,0) -> #NUM!
A71: 13 | B71: 45349 | C71: =C70 -> 312111.99 | D71: =C71-E71 -> 12856.271 | E71: =F70*$K$41%/12 -> 299255.72 | F71: =F70-D71 -> 15600486 | H71: =IF(A71<=$I$42,$K$42,IF(A71<=$I$43,$K$43,IF(A71<=$I$44,$K$44,$K$45))) -> 14.5 | I71: =F70*H71%/12 -> 188661.22 | J71: =D71+I71 -> 201517.49 | K71: =J71-C71 -> -110594.51 | L71: =J71+IF(A71=$K$50,F71,0) -> 201517.49 | O71: 13 | P71: 45349 | Q71: =Q70 -> #NUM! | R71: =Q71-S71 -> #NUM! | S71: =T70*$K$41%/12 -> #NUM! | T71: =T70-R71 -> #NUM! | V71: =IF(O71<=$I$42,$K$42,IF(O71<=$I$43,$K$43,IF(O71<=$I$44,$K$44,$K$45))) -> 14.5 | W71: =T70*V71%/12 -> #NUM! | X71: =R71+W71 -> #NUM! | Y71: =X71-Q71 -> #NUM! | Z71: =X71+IF(O71=$K$50,T71,0) -> #NUM!
... A298: 240 | B298: 52258 | C298: =C297 -> 312111.99 | D298: =C298-E298 -> 956704.7 | E298: =F297*$K$41%/12 -> -644592.71 | F298: =F297-D298 -> -34587628 | H298: =IF(A298<=$I$42,$K$42,IF(A298<=$I$43,$K$43,IF(A298<=$I$44,$K$44,$K$45))) -> 23 | I298: =F297*H298%/12 -> -644592.71 | J298: =D298+I298 -> 312111.99 | K298: =J298-C298 -> 0 | L298: =J298+IF(A298=$K$50,F298,0) -> 312111.99 | O298: 240 | P298: 52258 | Q298: =Q297 -> #NUM! | R298: =Q298-S298 -> #NUM! | S298: =T297*$K$41%/12 -> #NUM! | T298: =T297-R298 -> #NUM! | V298: =IF(O298<=$I$42,$K$42,IF(O298<=$I$43,$K$43,IF(O298<=$I$44,$K$44,$K$45))) -> 23 | W298: =T297*V298%/12 -> #NUM! | X298: =R298+W298 -> #NUM! | Y298: =X298-Q298 -> #NUM! | Z298: =X298+IF(O298=$K$50,T298,0) -> #NUM!
A299: Итого/Барлығы: | C299: =SUM(C59:C298) -> 74906879 | D299: =SUM(D59:D298) -> 50337628 | E299: =SUM(E59:E298) -> 24569250 | O299: Итого/Барлығы: | Q299: =SUM(Q59:Q298) -> #NUM! | R299: =SUM(R59:R298) -> #NUM! | S299: =SUM(S59:S298) -> #NUM!
A302: Настоящим Заёмщик подтверждает, что Банк предложил ему производить погашение займа
A303: методами дифференцированных платежей или аннуитетных платежей.
A304: Заёмщик выбрал _____________(указать дифференцированный или аннуитетный) метод погашения суммы займа.
A305: Қарыз алушы осымен Банк оған қарызды дифференцирленген төлем немесе аннуитеттік төлем әдістерімен
A306: өтеу жүргізуді ұсынғанын растайды.
A307: Қарыз алушы қарыз сомасын өтеудің _____________ әдісін таңдады (дифференцирленген немесе аннуитеттік көрсету).
A310: Банк/Банк:
A312: __________________________
A313: АО «Банк Kassa Nova» (ДБ АО «ForteBank»)
A314: Курмангожин Алмаз Муратбекович
A317: м.п./м.о.

Sheet ФридБанк ДДУ
A1: Цифровая FFB ДДУ
A4: Условия программы: | C4: Срок / Первоначальный Взнос
A5: При полном подтверждении доходов | C5: до 15 лет / от 20%
A7: Целевая группа | C7: Физические лица. Граждане РК.
A8: Сумма кредита | C8: Минимум 3 млн – максимум 80 млн
A9: Возраст Заемщика | C9: От 21 года до 63 лет на момент завершения срока кредита
A10: Подтверждение доходов | C10: * При оформлении займа с подтверждением доходов 6 месяцев пенсионных отчислений в ЕНПФ обязательны.
A11: РАСХОДЫ, СВЯЗАННЫЕ С ОФОРМЛЕНИЕМ КРЕДИТА
A12: Комиссия за рассмотрения кредитной заявки | C12: 30 000 тенге
A13: Комиссия за предоставление займа | C13: 0 тенге
A14: Досрочное погашение | C14: При сокращений суммы платежа-без комисий. При сокращении срока - 1 раз 10.000 тг,последующие 20.000 тг.
A15: Залогодатель | C15: Любое 3 лицо (до 63 лет должен закрыться кредит).
A20: Цифровая Стандарт
A21: Срок займа в месяцах | B21: Ставки вознаграждения от первоначального взноса (% годовых)
B22: от 71 | C22: от 61 до 70 | D22: от 51 до 60 | E22: от 41 до 50 | F22: от 31 до 40 | G22: от 20 до 30
A23: 12 мес. | B23: 0.1 | C23: 0.1 | D23: 0.1 | E23: 0.1 | F23: 0.1 | G23: 0.1
A24: от 13 мес. до 24 мес. | B24: 0.1 | C24: 0.1 | D24: 2.5 | E24: 6 | F24: 8.5 | G24: 10.5
A25: от 25 мес. до 36 мес. | B25: 0.1 | C25: 5 | D25: 8.5 | E25: 11 | F25: 12.5 | G25: 14
A26: от 37 мес. до 60 мес. | B26: 6.5 | C26: 11 | D26: 13.5 | E26: 15 | F26: 16 | G26: 17
A27: от 61 мес. до 120 мес. | B27: 12.5 | C27: 15.5 | D27: 17 | E27: 18 | F27: 18.5 | G27: 19
A28: от 121 до 180 мес. | B28: 14.5 | C28: 16.5 | D28: 18 | E28: 18.5 | F28: 19 | G28: 19.5
A29: от 181 до 240 мес. | B29: 15.5 | C29: 17 | D29: 18 | E29: 19 | F29: 19.5 | G29: 20
A33: Цифровая (Aкция )
A34: Срок займа в месяцах | B34: Ставки вознаграждения от первоначального взноса (% годовых)
B35: от 70 | C35: от 60 до 70 | D35: от 50 до 60 | E35: от 40 до 50 | F35: от 30 до 40 | G35: от 20 до 30
A36: 12 мес. | B36: 0.1 | C36: 0.1 | D36: 0.1 | E36: 0.1 | F36: 0.1 | G36: 0.1
A37: 13-24 | B37: 0.1 | C37: 0.1 | D37: 0.1 | E37: 0.1 | F37: 0.1 | G37: 0.1
A38: 25-36 | B38: 0.1 | C38: 0.1 | D38: 0.1 | E38: 0.5 | F38: 3 | G38: 5
A39: 37-60 | B39: 0.1 | C39: 0.1 | D39: 4 | E39: 6.5 | F39: 8.5 | G39: 10
A40: 61-120 | B40: 2.5 | C40: 7.5 | D40: 10 | E40: 12 | F40: 13 | G40: 13.5
A41: 121-180 | B41: 6.5 | C41: 10 | D41: 12 | E41: 12.5 | F41: 13 | G41: 13.5
A42: 181-240 | B42: 8 | C42: 11 | D42: 13 | E42: 14 | F42: 15 | G42: 15.5
A46: Таблица расходов
A48: Стоимость недвижимости | B48: 55000000
A49: Стоимость квартиры в ипотеку | B49: =B48*1.05 -> 57750000
A50: Первоначальный взнос, % | B50: 0.2
A51: Первоначальный взнос | B51: =B49*B50 -> 11550000
A52: Сумма Займа | B52: =B49-B51 -> 46200000
A53: Ставка вознаграждения годовая | B53: 0.195
A54: Срок кредита | B54: 180
A55: Ежемесячное погашение | B55: =ROUND(POWER((1+B53/12),B54)*B53/12/(POWER((1+B53/12),B54)-1)*B52,0) -> 794395
A56: Переплата за весь срок | B56: =B55*B54-B52 -> 96791100

Sheet БЦК - Super  ипотека
A1: Super Ипотека БЦК
A4: Условия программы: | C4: Срок / Взнос
A5: При полном подтверждении доходов | C5: до 15 лет / от 20%
A6: При частичном подтверждении доходов | C6: до 15 лет / от 30%
A7: Целевая группа | C7: Физические лица. Граждане РК, жители РК с Видом на Жительства НЕЛЬЗЯ
A8: Первоначальный взнос | C8: от 20%
A9: Стоимость квартиры | C9: ПВ от 20%: • для городов Астана Алматы – 50 млн тенге; • для городов Шымкент, Караганда, Актау, Атырау, Актобе, Усть-Каменогорск – 45 млн тенге; • для остальных регионов – 30 млн тенге; ПВ от 30% ограничения к стоимости жилья отсутствуют
A10: Возраст Заемщика | C10: От 21 года до 68 лет на момент завершения срока кредита
A11: Подтверждение доходов | C11: Рассматриваются любые варианты подтверждения доходов!
A12: Доп.информация: | C12: Максимальный срок финансирования с финансовым анализом (полное подтв-е доходов) при первоначальном взносе от 70% составляет 120 месяцев
A13: РАСХОДЫ, СВЯЗАННЫЕ С ОФОРМЛЕНИЕМ КРЕДИТА
A14: Комиссия за рассмотрения кредитной заявки | C14: 0 тенге
A15: Комиссия за предоставление займа | C15: 0 тенге
A16: Возможно доп расходы клиента: | C16: 0 тенге
A17: Досрочное погашение | C17: 1 % от суммы до 12 месяцев, свыше 12 месяцев 0 тенге. Разрешается полное/частичное досрочное погашение в любое время.
A18: Созаещик | C18: любое 3 лицо , не более 2 человек.
A20: Объекты с ДДУ/КЖК | I20: Объекты с АВВЭ
A21: Первоначальный взнос / срок | B21: с подтверждением доходов | E21: без подтверждения доходов | I21: Первоначальный взнос / срок | J21: с подтверждением доходов | M21: без подтверждения доходов
B22: от 20% | C22: от 50% | D22: от 70% | E22: от 30% | F22: от 50% | J22: от 20% | K22: от 50% | L22: от 70% | M22: от 50%
B23: ставка | C23: ставка | D23: ставка | E23: ставка | F23: ставка | J23: ставка | K23: ставка | L23: ставка | M23: ставка
A24: 12 мес. | B24: 0.07 | C24: 0.001 | D24: 0.001 | E24: 0.07 | F24: 0.04 | I24: 12 мес. | J24: 0.09 | K24: 0.07 | L24: 0.06 | M24: 0.075
A25: 13-24 мес. | B25: 0.085 | C25: 0.075 | D25: 0.05 | E25: 0.085 | F25: 0.085 | I25: 13-24 мес. | J25: 0.1 | K25: 0.09 | L25: 0.08 | M25: 0.1
A26: 25-36 мес. | B26: 0.115 | C26: 0.105 | D26: 0.07 | E26: 0.115 | F26: 0.11 | I26: 25-36 мес. | J26: 0.13 | K26: 0.12 | L26: 0.11 | M26: 0.125
A27: 37-60 мес. | B27: 0.14 | C27: 0.135 | D27: 0.12 | E27: 0.14 | F27: 0.14 | I27: 37-180 мес. | J27: 0.155 | K27: 0.15 | L27: 15,00%* | M27: 0.155
A28: 61-120 мес. | B28: 0.14 | C28: 0.135 | D28: 0.12 | E28: 0.14 | F28: 0.14
A29: 121-180 мес. | B29: 0.1425 | C29: 0.1375 | D29: - | E29: 0.1775 | F29: 0.1425
I30: * | J30: Максимальный срок финансирования с финансовым анализом (полное подтв-е доходов) при первоначальном взносе от 70% составляет 120 месяцев
A32: Таблица расходов
A34: Стоимость недвижимости | B34: 21382560
A35: Стоимость квартиры ипотеку | B35: =B34*1.05 -> 22451688
A36: Первоначальный взнос, % | B36: 0.2
A37: Первоначальный взнос | B37: =B35*B36 -> 4490337.6
A38: Сумма Займа | B38: =B35-B37 -> 17961350
A39: Ставка вознагражд годовая | B39: 0.14
A40: Срок кредита | B40: 120
A41: Ежемесячное погашение | B41: =ROUND(POWER((1+B39/12),B40)*B39/12/(POWER((1+B39/12),B40)-1)*B38,0) -> 278879
A42: Переплата за весь срок | B42: =B41*B40-B38 -> 15504130

Sheet 50-50
A1: Стоимость жилья,тг. | B1: 7000000
A2: Возможный платеж, тг. | B2: 250000
A3: Срок накопления, лет | B3: =IF(AND(B2>=N15,B2<M15),N14,IF(AND(B2>=M15,B2<L15),M14,IF(AND(B2>=L15,B2<K15),L14,IF(AND(B2>=K15,B2<J15),K14,IF(AND(B2>=J15,B2<I15),J14,IF(AND(B2>=I15,B2<H15),I14,IF(AND(B2>=H15,B2<G15),H14,IF(AND(B2>=G15,B2<F15),G14,IF(AND(B2>=F15,B2<E15),F14,IF(AND(B2>=E15,B2<D15),E14,IF(AND(B2>=D15,B2<C15),D14,IF(AND(B2>=C15,B2<B15),C14,IF(B2>=B15,B14,"Нет вариантов"))))))))))))) -> 3
A4: Срок жилищного займа, лет | B4: =IF(B3=B14,B17,IF(B3=C14,C17,IF(B3=D14,D17,IF(B3=E14,E17,IF(B3=F14,F17,IF(B3=G14,G17,IF(B3=H14,H17,IF(B3=I14,I17,IF(B3=J14,J17,IF(B3=K14,K17,IF(B3=L14,L17,IF(B3=M14,M17,IF(B3=N14,N17))))))))))))) -> 6
A5: Ежемесячный платеж по жилищному займ, тг. | B5: =IF(B4=B17,B19,IF(B4=C17,C19,IF(B4=D17,D19,IF(B4=E17,E19,IF(B4=F17,F19,IF(B4=G17,G19,IF(B4=H17,H19,IF(B4=I17,I19,IF(B4=J17,J19,IF(B4=K17,K19,IF(B4=L17,L19,IF(B4=M17,M19,IF(B4=N17,N19))))))))))))) -> 56700
A7: При консультации клиента необходимо заполнить поля, выделенные желтым цветом: стоимость жилья (договорная сумма) и возможный платеж (ежемесячный платеж). При этом, автоматически расчитаются поля, выленным красным шрифтом: (срок накполения, срок жилищного займа, ежемесячный платеж по жилишщному займу). В ниже приведенной таблице Вы можете посмотреть более подробную информацию, в том числе ставку вознаграждения по жилищному займу.
A13: Размер ежемесячного взноса, % от договорной суммы | B13: 1.5 | C13: 1.05 | D13: 0.83 | E13: 0.66 | F13: 0.58 | G13: 0.52 | H13: 0.44 | I13: 0.38 | J13: 0.34 | K13: 0.31 | L13: 0.28 | M13: 0.26 | N13: 0.25
A14: Срок накопления, лет | B14: 3 | C14: 4 | D14: 5 | E14: 6 | F14: 7 | G14: 8 | H14: 9 | I14: 10 | J14: 11 | K14: 12 | L14: 13 | M14: 14 | N14: 15
A15: Ежемесячный взнос, тг. | B15: =B13*$B$1/100 -> 105000 | C15: =C13*$B$1/100 -> 73500 | D15: =D13*$B$1/100 -> 58100 | E15: =E13*$B$1/100 -> 46200 | F15: =F13*$B$1/100 -> 40600 | G15: =G13*$B$1/100 -> 36400 | H15: =H13*$B$1/100 -> 30800 | I15: =I13*$B$1/100 -> 26600 | ... N15: =N13*$B$1/100 -> 17500
A16: Размер ежемесячного взноса по жил.займу, % от договорной суммы | B16: 0.81 | C16: 0.7 | D16: 0.62 | E16: 0.56 | F16: 0.51 | G16: 0.46 | H16: 0.43 | I16: 0.38 | J16: 0.34 | K16: 0.31 | L16: 0.28 | M16: 0.26 | N16: 0.25
A17: Срок жилищного займа, лет | B17: 6 | C17: 7 | D17: 8 | E17: 9 | F17: 10 | G17: 11 | H17: 12 | I17: 14 | J17: 16 | K17: 18 | L17: 21 | M17: 23 | N17: 25
A18: Ставка по жилищному займу, % | B18: 0.05 | C18: 0.048 | D18: 0.045 | E18: 0.042 | F18: 0.04 | G18: 0.038 | H18: 0.037 | I18: 0.035 | J18: 0.035 | K18: 0.035 | L18: 0.035 | M18: 0.035 | N18: 0.035
A19: Ежемесячный платеж по займу, тг. | B19: =B16*$B$1/100 -> 56700 | C19: =C16*$B$1/100 -> 49000 | D19: =D16*$B$1/100 -> 43400 | E19: =E16*$B$1/100 -> 39200 | F19: =F16*$B$1/100 -> 35700 | G19: =G16*$B$1/100 -> 32200 | H19: =H16*$B$1/100 -> 30100 | I19: =I16*$B$1/100 -> 26600 | ... N19: =N16*$B$1/100 -> 17500
A21: Комисии по оформлению займа: | C21: сумма,тг
A22: Комиссия за рассмотр. кред. заявки: | C22: 5000
A23: Страхование недвижимости (0,2%) | C23: =((B1*1.1)-B1/2)*0.2% -> 8400
A24: Титульное страхование (0,2%) | C24: =((B1*1.1)-B1/2)*0.2% -> 8400 | D24: В зависимости от срока владения недвижимостью
A25: Комисия за организацию кредита (0,5% от суммы займа), макс 100 000 тг. | C25: =IF(B1*0.005>100000,100000,B1*0.005) -> 35000
A26: Комиссия за выдачу наличными (0,5% от суммы займа), макс 50 000 тг. | C26: =IF(B1*0.005>50000,50000,B1*0.005) -> 35000 | D26: Комиссия за безналичный внешний перевод займа 0,3% от суммы займа, макс - 5 000 тг. | H26: =IF(B1*0.003<5000,B1*0.003,5000) -> 5000
A27: Итого | C27: =SUM(C22:C26) -> 91800 | D27: Итого | H27: =C22+C23+C24+C25+H26 -> 61800
A29: 50-50
A30: Дата оформления пром.займа | B30: =TODAY() -> 45971
A31: Дата открытия депозита | B31: 44960 | C31: если есть депозит
A32: Начисленное вознаграждение | B32: 0
A35: Стоимость жилья,тг. | B35: 25000000 | C35: Стоимость квартиры указываем здесь
A36: Первоначальный взнос, тг. | B36: =B35/2 -> 12500000 | E36: ,
A38: Промежуточный стандартный
A40: Срок промежуточного займа, МЕС | B40: =ROUNDUP(IF((1080-DAYS360(B31,B30,TRUE))/360<LOG((B35*16/1000-B32+B35/2)/(B35/2),1.02),LOG((B35*16/1000-B32+B35/2)/(B35/2),1.02)*12,(1080-DAYS360(B31,B30,TRUE))/30),0) -> 20 | C40: =ROUNDUP(IF((1080-DAYS360(B31,B30,TRUE))/360<LOG((B35*20/1000-B32+B35/2)/(B35/2),1.02),LOG((B35*20/1000-B32+B35/2)/(B35/2),1.02)*12,(1080-DAYS360(B31,B30,TRUE))/30),0) -> 24 | D40: =ROUNDUP(IF((1080-DAYS360(B31,B30,TRUE))/360<LOG((B35*25/1000-B32+B35/2)/(B35/2),1.02),LOG((B35*25/1000-B32+B35/2)/(B35/2),1.02)*12,(1080-DAYS360(B31,B30,TRUE))/30),0) -> 30 | E40: =ROUNDUP(IF((1080-DAYS360(B31,B30,TRUE))/360<LOG((B35*29/1000-B32+B35/2)/(B35/2),1.02),LOG((B35*29/1000-B32+B35/2)/(B35/2),1.02)*12,(1080-DAYS360(B31,B30,TRUE))/30),0) -> 35 | F40: =ROUNDUP(IF((1080-DAYS360(B31,B30,TRUE))/360<LOG((B35*35/1000-B32+B35/2)/(B35/2),1.02),LOG((B35*35/1000-B32+B35/2)/(B35/2),1.02)*12,(1080-DAYS360(B31,B30,TRUE))/30),0) -> 41 | G40: =ROUNDUP(IF((1080-DAYS360(B31,B30,TRUE))/360<LOG((B35*41/1000-B32+B35/2)/(B35/2),1.02),LOG((B35*41/1000-B32+B35/2)/(B35/2),1.02)*12,(1080-DAYS360(B31,B30,TRUE))/30),0) -> 48 | H40: =ROUNDUP(IF((1080-DAYS360(B31,B30,TRUE))/360<LOG((B35*45/1000-B32+B35/2)/(B35/2),1.02),LOG((B35*45/1000-B32+B35/2)/(B35/2),1.02)*12,(1080-DAYS360(B31,B30,TRUE))/30),0) -> 53 | I40: =ROUNDUP(IF((1080-DAYS360(B31,B30,TRUE))/360<LOG((B35*48/1000-B32+B35/2)/(B35/2),1.02),LOG((B35*48/1000-B32+B35/2)/(B35/2),1.02)*12,(1080-DAYS360(B31,B30,TRUE))/30),0) -> 56 | J40: =ROUNDUP(IF((1080-DAYS360(B31,B30,TRUE))/360<LOG((B35*53/1000-B32+B35/2)/(B35/2),1.02),LOG((B35*53/1000-B32+B35/2)/(B35/2),1.02)*12,(1080-DAYS360(B31,B30,TRUE))/30),0) -> 62 | K40: =ROUNDUP(IF((1080-DAYS360(B31,B30,TRUE))/360<LOG((B35*57/1000-B32+B35/2)/(B35/2),1.02),LOG((B35*57/1000-B32+B35/2)/(B35/2),1.02)*12,(1080-DAYS360(B31,B30,TRUE))/30),0) -> 66 | L40: =ROUNDUP(IF((1080-DAYS360(B31,B30,TRUE))/360<LOG((B35*61/1000-B32+B35/2)/(B35/2),1.02),LOG((B35*61/1000-B32+B35/2)/(B35/2),1.02)*12,(1080-DAYS360(B31,B30,TRUE))/30),0) -> 70 | M40: =ROUNDUP(IF((1080-DAYS360(B31,B30,TRUE))/360<LOG((B35*66/1000-B32+B35/2)/(B35/2),1.02),LOG((B35*66/1000-B32+B35/2)/(B35/2),1.02)*12,(1080-DAYS360(B31,B30,TRUE))/30),0) -> 76 | N40: =ROUNDUP(IF((1080-DAYS360(B31,B30,TRUE))/360<LOG((B35*74/1000-B32+B35/2)/(B35/2),1.02),LOG((B35*74/1000-B32+B35/2)/(B35/2),1.02)*12,(1080-DAYS360(B31,B30,TRUE))/30),0) -> 84
A41: Ставка по промежуточному займу, % | B41: 0.07
A42: Ежемесячный платеж по пром. займу, тг. | B42: =(B35*(B41/12))/(1-POWER(1/(1+B41/12),B43*12)) -> 426225.16 | C42: =(B35*(B41/12))/(1-POWER(1/(1+B41/12),C43*12)) -> 377317 | D42: =(B35*(B41/12))/(1-POWER(1/(1+B41/12),D43*12)) -> 340842.93 | E42: =(B35*(B41/12))/(1-POWER(1/(1+B41/12),E43*12)) -> 312656.91 | F42: =(B35*(B41/12))/(1-POWER(1/(1+B41/12),F43*12)) -> 290271.2 | G42: =(B35*(B41/12))/(1-POWER(1/(1+B41/12),G43*12)) -> 272102.52 | H42: =(B35*(B41/12))/(1-POWER(1/(1+B41/12),H43*12)) -> 257095.27 | I42: =(B35*(B41/12))/(1-POWER(1/(1+B41/12),I43*12)) -> 233850.14 | J42: =(B35*(B41/12))/(1-POWER(1/(1+B41/12),J43*12)) -> 216802.01 | K42: =(B35*(B41/12))/(1-POWER(1/(1+B41/12),K43*12)) -> 203875.54 | L42: =(B35*(B41/12))/(1-POWER(1/(1+B41/12),L43*12)) -> 189617.93 | M42: =(B35*(B41/12))/(1-POWER(1/(1+B41/12),M43*12)) -> 182479.81 | N42: =(B35*(B41/12))/(1-POWER(1/(1+B41/12),N43*12)) -> 176694.8
A43: Срок жилищного займа, лет | B43: 6 | C43: 7 | D43: 8 | E43: 9 | F43: 10 | G43: 11 | H43: 12 | I43: 14 | J43: 16 | K43: 18 | L43: 21 | M43: 23 | N43: 25
A44: Ставка по жилищному займу, % | B44: 0.05 | C44: 0.048 | D44: 0.045 | E44: 0.042 | F44: 0.04 | G44: 0.038 | H44: 0.037 | I44: 0.035 | J44: 0.035 | K44: 0.035 | L44: 0.035 | M44: 0.035 | N44: 0.035
A45: Ежемесячный платеж по жилищному займу, тг. | B45: =(B42*((1-1/POWER(1+B41/12,72-B40))/(B41/12))-$B$35/2-16*($B$35/1000)-IF(B40>12,50000,0))*(B44/12)/(1-POWER(1/(1+B44/12),B43*12)) -> 98566.121 | C45: =(C42*((1-1/POWER(1+B41/12,C43*12-C40))/(B41/12))-$B$35/2-20*($B$35/1000)-IF(C40>24,100000,0))*(C44/12)/(1-POWER(1/(1+C44/12),C43*12)) -> 85016.606 | D45: =(D42*((1-1/POWER(1+B41/12,D43*12-D40))/(B41/12))-$B$35/2-25*($B$35/1000)-IF(D40>24,100000,0))*(D44/12)/(1-POWER(1/(1+D44/12),D43*12)) -> 67108.33 | E45: =(E42*((1-1/POWER(1+B41/12,E43*12-E40))/(B41/12))-$B$35/2-29*($B$35/1000)-100000)*(E44/12)/(1-POWER(1/(1+E44/12),E43*12)) -> 58106.03 | F45: =(F42*((1-1/POWER(1+B41/12,F43*12-F40))/(B41/12))-$B$35/2-35*($B$35/1000)-IF(F40>24,100000,0))*(F44/12)/(1-POWER(1/(1+F44/12),F43*12)) -> 49171.999 | G45: =(G42*((1-1/POWER(1+B41/12,G43*12-G40))/(B41/12))-$B$35/2-41*($B$35/1000)-IF(G40>24,100000,0))*(G44/12)/(1-POWER(1/(1+G44/12),G43*12)) -> 40870.957 | H45: =(H42*((1-1/POWER(1+B41/12,H43*12-H40))/(B41/12))-$B$35/2-45*($B$35/1000)-IF(H40>24,100000,0))*(H44/12)/(1-POWER(1/(1+H44/12),H43*12)) -> 37784.025 | I45: =(I42*((1-1/POWER(1+B41/12,I43*12-I40))/(B41/12))-$B$35/2-48*($B$35/1000)-IF(I40>24,100000,0))*(I44/12)/(1-POWER(1/(1+I44/12),I43*12)) -> 40632.942 | J45: =(J42*((1-1/POWER(1+B41/12,J43*12-J40))/(B41/12))-$B$35/2-53*($B$35/1000)-IF(J40>24,100000,0))*(J44/12)/(1-POWER(1/(1+J44/12),J43*12)) -> 39442.797 | K45: =(K42*((1-1/POWER(1+B41/12,K43*12-K40))/(B41/12))-$B$35/2-57*($B$35/1000)-IF(K40>24,100000,0))*(K44/12)/(1-POWER(1/(1+K44/12),K43*12)) -> 39470.115 | L45: =(L42*((1-1/POWER(1+B41/12,L43*12-L40))/(B41/12))-$B$35/2-61*($B$35/1000)-IF(L40>24,100000,0))*(L44/12)/(1-POWER(1/(1+L44/12),L43*12)) -> 39842.443 | M45: =(M42*((1-1/POWER(1+B41/12,M43*12-M40))/(B41/12))-$B$35/2-66*($B$35/1000)-IF(M40>12,50000,0))*(M44/12)/(1-POWER(1/(1+M44/12),M43*12)) -> 38585.865 | N45: =(N42*((1-1/POWER(1+B41/12,N43*12-N40))/(B41/12))-$B$35/2-74*($B$35/1000)-IF(N40>12,50000,0))*(N44/12)/(1-POWER(1/(1+N44/12),N43*12)) -> 36380.28
A46: Переплата, тг | B46: =B42*B40+B45*B43*12+$B$35/2-$B$35 -> 3121263.9 | C46: =C42*C40+C45*C43*12+$B$35/2-$B$35 -> 3697002.9 | D46: =D42*D40+D45*D43*12+$B$35/2-$B$35 -> 4167687.5 | E46: =E42*E40+E45*E43*12+$B$35/2-$B$35 -> 4718443.3 | F46: =F42*F40+F45*F43*12+$B$35/2-$B$35 -> 5301759 | G46: =G42*G40+G45*G43*12+$B$35/2-$B$35 -> 5955887.5 | H46: =H42*H40+H45*H43*12+$B$35/2-$B$35 -> 6566949.2 | I46: =I42*I40+I45*I43*12+$B$35/2-$B$35 -> 7421941.8 | ... N46: =N42*N40+N45*N43*12+$B$35/2-$B$35 -> 13256447
B47: =B43*12 -> 72 | C47: =C43*12 -> 84 | D47: =D43*12 -> 96 | E47: =E43*12 -> 108 | F47: =F43*12 -> 120 | G47: =G43*12 -> 132 | H47: =H43*12 -> 144 | I47: =I43*12 -> 168 | ... N47: =N43*12 -> 300
A48: Промежуточный Женил
A50: Срок промежуточного займа, МЕС | B50: =B40 -> 20
A51: Ставка по промежуточному займу, % | B51: 0.085
A52: Ежемесячный платеж по пром. займу без погашения основного долга, тг. | B52: =B35*B51/12 -> 177083.33
A53: Ежемесячный платеж через три года по пром.займу с погашением основного долга, тг. | B53: -
A54: Срок жилищного займа, лет | B54: 6
A55: Ставка по жилищному займу, % | B55: 0.05
A56: Ежемесячный платеж по жилищному займу, тг. | B56: =B35*B16% -> 202500
A57: Переплата, тг | B57: =B52*B50+B56*B54*12+$B$35/2-$B$35 -> 5621666.7
A61: Комисии по оформлению займа: | C61: сумма,тг
A62: Комиссия за рассмотр. кред. заявки: | C62: 5000
A63: Страхование недвижимости (0,2%) | C63: =((B35*1.1)-B36)*0.2% -> 30000
A64: Титульное страхование (0,2%) | C64: =((B35*1.1)-B36)*0.2% -> 30000 | D64: В зависимости от срока владения недвижимостью
A65: Комисия за организацию кредита (0,5% от суммы займа), макс 100 000 тг. | C65: =IF(B35*0.005>100000,100000,B35*0.005) -> 100000
A66: Комиссия за выдачу наличными (0,5% от суммы займа), макс 50 000 тг. | C66: =IF(B35*0.005>50000,50000,B35*0.005) -> 50000 | D66: Комиссия за безналичный внешний перевод займа 0,3% от суммы займа, макс - 5 000 тг. | H66: =IF(B35*0.003<5000,B35*0.003,5000) -> 5000
A67: Итого | C67: =SUM(C62:C66) -> 215000 | D67: Итого: | H67: =C62+C63+C64+C65+H66 -> 170000
A71: Оценочный показатель | B71: 2,5-3,3 | C71: 3,3-4,2 | D71: 4,2-5,0 | E71: от 5,0 | F71: 7-10 | G71: от 10
A72: Ставка вознаграждения по займам на НОВОЕ ЖИЛЬЕ | B72: 0.1 | C72: 0.095 | D72: 0.09 | E72: 0.085 | F72: 0.08 | G72: 0.075

Sheet НИ 30-70
A1: Стоимость жилья,тг. | B1: 7000000
A2: Возможный платеж, тг. | B2: 250000
A3: Срок накопления, лет | B3: =IF(AND(B2>=N15,B2<M15),N14,IF(AND(B2>=M15,B2<L15),M14,IF(AND(B2>=L15,B2<K15),L14,IF(AND(B2>=K15,B2<J15),K14,IF(AND(B2>=J15,B2<I15),J14,IF(AND(B2>=I15,B2<H15),I14,IF(AND(B2>=H15,B2<G15),H14,IF(AND(B2>=G15,B2<F15),G14,IF(AND(B2>=F15,B2<E15),F14,IF(AND(B2>=E15,B2<D15),E14,IF(AND(B2>=D15,B2<C15),D14,IF(AND(B2>=C15,B2<B15),C14,IF(B2>=B15,B14,"Нет вариантов"))))))))))))) -> 3
A4: Срок жилищного займа, лет | B4: =IF(B3=B14,B17,IF(B3=C14,C17,IF(B3=D14,D17,IF(B3=E14,E17,IF(B3=F14,F17,IF(B3=G14,G17,IF(B3=H14,H17,IF(B3=I14,I17,IF(B3=J14,J17,IF(B3=K14,K17,IF(B3=L14,L17,IF(B3=M14,M17,IF(B3=N14,N17))))))))))))) -> 6
A5: Ежемесячный платеж по жилищному займ, тг. | B5: =IF(B4=B17,B19,IF(B4=C17,C19,IF(B4=D17,D19,IF(B4=E17,E19,IF(B4=F17,F19,IF(B4=G17,G19,IF(B4=H17,H19,IF(B4=I17,I19,IF(B4=J17,J19,IF(B4=K17,K19,IF(B4=L17,L19,IF(B4=M17,M19,IF(B4=N17,N19))))))))))))) -> 56700
A7: При консультации клиента необходимо заполнить поля, выделенные желтым цветом: стоимость жилья (договорная сумма) и возможный платеж (ежемесячный платеж). При этом, автоматически расчитаются поля, выленным красным шрифтом: (срок накполения, срок жилищного займа, ежемесячный платеж по жилишщному займу). В ниже приведенной таблице Вы можете посмотреть более подробную информацию, в том числе ставку вознаграждения по жилищному займу.
A13: Размер ежемесячного взноса, % от договорной суммы | B13: 1.5 | C13: 1.05 | D13: 0.83 | E13: 0.66 | F13: 0.58 | G13: 0.52 | H13: 0.44 | I13: 0.38 | J13: 0.34 | K13: 0.31 | L13: 0.28 | M13: 0.26 | N13: 0.25
A14: Срок накопления, лет | B14: 3 | C14: 4 | D14: 5 | E14: 6 | F14: 7 | G14: 8 | H14: 9 | I14: 10 | J14: 11 | K14: 12 | L14: 13 | M14: 14 | N14: 15
A15: Ежемесячный взнос, тг. | B15: =B13*$B$1/100 -> 105000 | C15: =C13*$B$1/100 -> 73500 | D15: =D13*$B$1/100 -> 58100 | E15: =E13*$B$1/100 -> 46200 | F15: =F13*$B$1/100 -> 40600 | G15: =G13*$B$1/100 -> 36400 | H15: =H13*$B$1/100 -> 30800 | I15: =I13*$B$1/100 -> 26600 | ... N15: =N13*$B$1/100 -> 17500
A16: Размер ежемесячного взноса по жил.займу, % от договорной суммы | B16: 0.81 | C16: 0.7 | D16: 0.62 | E16: 0.56 | F16: 0.51 | G16: 0.46 | H16: 0.43 | I16: 0.38 | J16: 0.34 | K16: 0.31 | L16: 0.28 | M16: 0.26 | N16: 0.25
A17: Срок жилищного займа, лет | B17: 6 | C17: 7 | D17: 8 | E17: 9 | F17: 10 | G17: 11 | H17: 12 | I17: 14 | J17: 16 | K17: 18 | L17: 21 | M17: 23 | N17: 25
A18: Ставка по жилищному займу, % | B18: 0.05 | C18: 0.048 | D18: 0.045 | E18: 0.042 | F18: 0.04 | G18: 0.038 | H18: 0.037 | I18: 0.035 | J18: 0.035 | K18: 0.035 | L18: 0.035 | M18: 0.035 | N18: 0.035
A19: Ежемесячный платеж по займу, тг. | B19: =B16*$B$1/100 -> 56700 | C19: =C16*$B$1/100 -> 49000 | D19: =D16*$B$1/100 -> 43400 | E19: =E16*$B$1/100 -> 39200 | F19: =F16*$B$1/100 -> 35700 | G19: =G16*$B$1/100 -> 32200 | H19: =H16*$B$1/100 -> 30100 | I19: =I16*$B$1/100 -> 26600 | ... N19: =N16*$B$1/100 -> 17500
A21: Комисии по оформлению займа: | C21: сумма,тг
A22: Комиссия за рассмотр. кред. заявки: | C22: 5000
A23: Страхование недвижимости (0,2%) | C23: =((B1*1.1)-B1/2)*0.2% -> 8400
A24: Титульное страхование (0,2%) | C24: =((B1*1.1)-B1/2)*0.2% -> 8400 | D24: В зависимости от срока владения недвижимостью
A25: Комисия за организацию кредита (0,5% от суммы займа), макс 100 000 тг. | C25: =IF(B1*0.005>100000,100000,B1*0.005) -> 35000
A26: Комиссия за выдачу наличными (0,5% от суммы займа), макс 50 000 тг. | C26: =IF(B1*0.005>50000,50000,B1*0.005) -> 35000 | D26: Комиссия за безналичный внешний перевод займа 0,3% от суммы займа, макс - 5 000 тг. | H26: =IF(B1*0.003<5000,B1*0.003,5000) -> 5000
A27: Итого | C27: =SUM(C22:C26) -> 91800 | D27: Итого | H27: =C22+C23+C24+C25+H26 -> 61800
A28: НИ 30-70
A31: Дата оформления пром.займа | B31: =TODAY() -> 45971
A32: Дата открытия депозита | B32: 44691 | H32: все расчеты без учета депозита!
A33: Начисленное вознаграждение | B33: 0 | K33: переплата ориентировочная
D34: 3 года | E34: =E53 -> 183750 | F34: =E119 -> 52500 | G34: =E34+F34 -> 236250 | L34: 12 лет | M34: =((36*G34)+(108*G38))/2.58831 -> 12118502
A35: Стоимость жилья,тг. | B35: 30000000 | C35: Стоимость квартиры указываем здесь | D35: 6 лет | E35: =B57 -> 255150 | F35: =B123 -> 51030 | G35: =F35+E35 -> 306180 | L35: 11 лет | M35: =((36*G34)+(96*G37))/2.6382699995 -> 11751474
A36: Стоимость с надбавкой 5% | B36: =B35*1.05 -> 31500000 | D36: 7 лет | E36: =C57 -> 220500 | F36: =C123 -> 44100 | G36: =F36+E36 -> 264600 | I36: ПВ 30% | J36: =B36*30% -> 9450000 | L36: 10 лет | M36: =((36*G34)+(84*G36))/2.677852 -> 11476138
A37: Первоначальный взнос, тг. | B37: =B36/2 -> 15750000 | D37: 8 лет | E37: =D57 -> 195300 | F37: =D123 -> 39060 | G37: =F37+E37 -> 234360 | I37: ПВ 20% | J37: =B36*20% -> 6300000 | L37: 9 лет | M37: =((36*G34)+(72*G35))/2.705321 -> 11292545
D38: 9 лет | E38: =E57 -> 176400 | F38: =E123 -> 35280 | G38: =E38+F38 -> 211680 | I38: стоимость залогово имущество | J38: =(B36+J37)/2/69.9% -> 27038627
A39: Промежуточный стандартный
B40: =B41/12+B44 -> 7.6666667 | C40: =C41/12+C44 -> 9 | D40: =D41/12+D44 -> 10.5 | E40: =E41/12+E44 -> 11.916667 | F40: =F41/12+F44 -> 13.416667 | G40: =G41/12+G44 -> 15 | H40: =H41/12+H44 -> 16.416667 | I40: =I41/12+I44 -> 18.666667 | ... N40: =N41/12+N44 -> 32
A41: Срок промежуточного займа, МЕС | B41: =ROUNDUP(IF((1080-DAYS360(B32,B31,TRUE))/360<LOG((B36*16/1000-B33+B36/2)/(B36/2),1.02),LOG((B36*16/1000-B33+B36/2)/(B36/2),1.02)*12,(1080-DAYS360(B32,B31,TRUE))/30),0) -> 20 | C41: =ROUNDUP(IF((1080-DAYS360(B32,B31,TRUE))/360<LOG((B36*20/1000-B33+B36/2)/(B36/2),1.02),LOG((B36*20/1000-B33+B36/2)/(B36/2),1.02)*12,(1080-DAYS360(B32,B31,TRUE))/30),0) -> 24 | D41: =ROUNDUP(IF((1080-DAYS360(B32,B31,TRUE))/360<LOG((B36*25/1000-B33+B36/2)/(B36/2),1.02),LOG((B36*25/1000-B33+B36/2)/(B36/2),1.02)*12,(1080-DAYS360(B32,B31,TRUE))/30),0) -> 30 | E41: =ROUNDUP(IF((1080-DAYS360(B32,B31,TRUE))/360<LOG((B36*29/1000-B33+B36/2)/(B36/2),1.02),LOG((B36*29/1000-B33+B36/2)/(B36/2),1.02)*12,(1080-DAYS360(B32,B31,TRUE))/30),0) -> 35 | F41: =ROUNDUP(IF((1080-DAYS360(B32,B31,TRUE))/360<LOG((B36*35/1000-B33+B36/2)/(B36/2),1.02),LOG((B36*35/1000-B33+B36/2)/(B36/2),1.02)*12,(1080-DAYS360(B32,B31,TRUE))/30),0) -> 41 | G41: =ROUNDUP(IF((1080-DAYS360(B32,B31,TRUE))/360<LOG((B36*41/1000-B33+B36/2)/(B36/2),1.02),LOG((B36*41/1000-B33+B36/2)/(B36/2),1.02)*12,(1080-DAYS360(B32,B31,TRUE))/30),0) -> 48 | H41: =ROUNDUP(IF((1080-DAYS360(B32,B31,TRUE))/360<LOG((B36*45/1000-B33+B36/2)/(B36/2),1.02),LOG((B36*45/1000-B33+B36/2)/(B36/2),1.02)*12,(1080-DAYS360(B32,B31,TRUE))/30),0) -> 53 | I41: =ROUNDUP(IF((1080-DAYS360(B32,B31,TRUE))/360<LOG((B36*48/1000-B33+B36/2)/(B36/2),1.02),LOG((B36*48/1000-B33+B36/2)/(B36/2),1.02)*12,(1080-DAYS360(B32,B31,TRUE))/30),0) -> 56 | J41: =ROUNDUP(IF((1080-DAYS360(B32,B31,TRUE))/360<LOG((B36*53/1000-B33+B36/2)/(B36/2),1.02),LOG((B36*53/1000-B33+B36/2)/(B36/2),1.02)*12,(1080-DAYS360(B32,B31,TRUE))/30),0) -> 62 | K41: =ROUNDUP(IF((1080-DAYS360(B32,B31,TRUE))/360<LOG((B36*57/1000-B33+B36/2)/(B36/2),1.02),LOG((B36*57/1000-B33+B36/2)/(B36/2),1.02)*12,(1080-DAYS360(B32,B31,TRUE))/30),0) -> 66 | L41: =ROUNDUP(IF((1080-DAYS360(B32,B31,TRUE))/360<LOG((B36*61/1000-B33+B36/2)/(B36/2),1.02),LOG((B36*61/1000-B33+B36/2)/(B36/2),1.02)*12,(1080-DAYS360(B32,B31,TRUE))/30),0) -> 70 | M41: =ROUNDUP(IF((1080-DAYS360(B32,B31,TRUE))/360<LOG((B36*66/1000-B33+B36/2)/(B36/2),1.02),LOG((B36*66/1000-B33+B36/2)/(B36/2),1.02)*12,(1080-DAYS360(B32,B31,TRUE))/30),0) -> 76 | N41: =ROUNDUP(IF((1080-DAYS360(B32,B31,TRUE))/360<LOG((B36*74/1000-B33+B36/2)/(B36/2),1.02),LOG((B36*74/1000-B33+B36/2)/(B36/2),1.02)*12,(1080-DAYS360(B32,B31,TRUE))/30),0) -> 84
A42: Ставка по промежуточному займу, % | B42: 0.07
A43: Ежемесячный платеж по пром. займу, тг. | B43: =(B36*(B42/12))/(1-POWER(1/(1+B42/12),B44*12)) -> 537043.7 | C43: =(B36*(B42/12))/(1-POWER(1/(1+B42/12),C44*12)) -> 475419.42 | D43: =(B36*(B42/12))/(1-POWER(1/(1+B42/12),D44*12)) -> 429462.09 | E43: =(B36*(B42/12))/(1-POWER(1/(1+B42/12),E44*12)) -> 393947.71 | F43: =(B36*(B42/12))/(1-POWER(1/(1+B42/12),F44*12)) -> 365741.71 | G43: =(B36*(B42/12))/(1-POWER(1/(1+B42/12),G44*12)) -> 342849.18 | H43: =(B36*(B42/12))/(1-POWER(1/(1+B42/12),H44*12)) -> 323940.04 | I43: =(B36*(B42/12))/(1-POWER(1/(1+B42/12),I44*12)) -> 294651.17 | J43: =(B36*(B42/12))/(1-POWER(1/(1+B42/12),J44*12)) -> 273170.53 | K43: =(B36*(B42/12))/(1-POWER(1/(1+B42/12),K44*12)) -> 256883.18 | L43: =(B36*(B42/12))/(1-POWER(1/(1+B42/12),L44*12)) -> 238918.59 | M43: =(B36*(B42/12))/(1-POWER(1/(1+B42/12),M44*12)) -> 229924.55 | N43: =(B36*(B42/12))/(1-POWER(1/(1+B42/12),N44*12)) -> 222635.45
A44: Срок жилищного займа, лет | B44: 6 | C44: 7 | D44: 8 | E44: 9 | F44: 10 | G44: 11 | H44: 12 | I44: 14 | J44: 16 | K44: 18 | L44: 21 | M44: 23 | N44: 25
A45: Ставка по жилищному займу, % | B45: 0.05 | C45: 0.048 | D45: 0.045 | E45: 0.042 | F45: 0.04 | G45: 0.038 | H45: 0.037 | I45: 0.035 | J45: 0.035 | K45: 0.035 | L45: 0.035 | M45: 0.035 | N45: 0.035
A46: Ежемесячный платеж по жилищному займу, тг. | B46: =(B43*((1-1/POWER(1+B42/12,72-B41))/(B42/12))-$B$36/2-16*($B$36/1000)-IF(B41>12,50000,0))*(B45/12)/(1-POWER(1/(1+B45/12),B44*12)) -> 124402.68 | C46: =(C43*((1-1/POWER(1+B42/12,C44*12-C41))/(B42/12))-$B$36/2-20*($B$36/1000)-IF(C41>24,100000,0))*(C45/12)/(1-POWER(1/(1+C45/12),C44*12)) -> 107120.92 | D46: =(D43*((1-1/POWER(1+B42/12,D44*12-D41))/(B42/12))-$B$36/2-25*($B$36/1000)-IF(D41>24,100000,0))*(D45/12)/(1-POWER(1/(1+D45/12),D44*12)) -> 84879.5 | E46: =(E43*((1-1/POWER(1+B42/12,E44*12-E41))/(B42/12))-$B$36/2-29*($B$36/1000)-100000)*(E45/12)/(1-POWER(1/(1+E45/12),E44*12)) -> 73503.114 | F46: =(F43*((1-1/POWER(1+B42/12,F44*12-F41))/(B42/12))-$B$36/2-35*($B$36/1000)-IF(F41>24,100000,0))*(F45/12)/(1-POWER(1/(1+F45/12),F44*12)) -> 62219.957 | G46: =(G43*((1-1/POWER(1+B42/12,G44*12-G41))/(B42/12))-$B$36/2-41*($B$36/1000)-IF(G41>24,100000,0))*(G45/12)/(1-POWER(1/(1+G45/12),G44*12)) -> 51738.709 | H46: =(H43*((1-1/POWER(1+B42/12,H44*12-H41))/(B42/12))-$B$36/2-45*($B$36/1000)-IF(H41>24,100000,0))*(H45/12)/(1-POWER(1/(1+H45/12),H44*12)) -> 47831.741 | I46: =(I43*((1-1/POWER(1+B42/12,I44*12-I41))/(B42/12))-$B$36/2-48*($B$36/1000)-IF(I41>24,100000,0))*(I45/12)/(1-POWER(1/(1+I45/12),I44*12)) -> 51393.491 | J46: =(J43*((1-1/POWER(1+B42/12,J44*12-J41))/(B42/12))-$B$36/2-53*($B$36/1000)-IF(J41>24,100000,0))*(J45/12)/(1-POWER(1/(1+J45/12),J44*12)) -> 49874.971 | K46: =(K43*((1-1/POWER(1+B42/12,K44*12-K41))/(B42/12))-$B$36/2-57*($B$36/1000)-IF(K41>24,100000,0))*(K45/12)/(1-POWER(1/(1+K45/12),K44*12)) -> 49894.756 | L46: =(L43*((1-1/POWER(1+B42/12,L44*12-L41))/(B42/12))-$B$36/2-61*($B$36/1000)-IF(L41>24,100000,0))*(L45/12)/(1-POWER(1/(1+L45/12),L44*12)) -> 50347.317 | M46: =(M43*((1-1/POWER(1+B42/12,M44*12-M41))/(B42/12))-$B$36/2-66*($B$36/1000)-IF(M41>12,50000,0))*(M45/12)/(1-POWER(1/(1+M45/12),M44*12)) -> 48686.832 | N46: =(N43*((1-1/POWER(1+B42/12,N44*12-N41))/(B42/12))-$B$36/2-74*($B$36/1000)-IF(N41>12,50000,0))*(N45/12)/(1-POWER(1/(1+N45/12),N44*12)) -> 45904.234
A47: Переплата, тг | B47: =B43*B41+B46*B44*12+$B$36/2-$B$36 -> 3947866.8 | C47: =C43*C41+C46*C44*12+$B$36/2-$B$36 -> 4658223.6 | D47: =D43*D41+D46*D44*12+$B$36/2-$B$36 -> 5282294.7 | E47: =E43*E41+E46*E44*12+$B$36/2-$B$36 -> 5976506.3 | F47: =F43*F41+F46*F44*12+$B$36/2-$B$36 -> 6711804.9 | G47: =G43*G41+G46*G44*12+$B$36/2-$B$36 -> 7536270.2 | H47: =H43*H41+H46*H44*12+$B$36/2-$B$36 -> 8306593.1 | I47: =I43*I41+I46*I44*12+$B$36/2-$B$36 -> 9384572 | ... N47: =N43*N41+N46*N44*12+$B$36/2-$B$36 -> 16722648
B48: =B44*12 -> 72 | C48: =C44*12 -> 84 | D48: =D44*12 -> 96 | E48: =E44*12 -> 108 | F48: =F44*12 -> 120 | G48: =G44*12 -> 132 | H48: =H44*12 -> 144 | I48: =I44*12 -> 168 | ... N48: =N44*12 -> 300
A49: Промежуточный Женил
A51: Срок промежуточного займа, МЕС | B51: =B41 -> 20 | C51: =C41 -> 24 | D51: =D41 -> 30 | E51: =E41 -> 35
A52: Ставка по промежуточному займу, % | B52: 0.07
A53: Ежемесячный платеж по пром. займу без погашения основного долга, тг. | B53: =B36*B52/12 -> 183750 | C53: =B53 -> 183750 | D53: =B53 -> 183750 | E53: =D53 -> 183750
A54: Ежемесячный платеж через три года по пром.займу с погашением основного долга, тг. | B54: - | C54: - | D54: - | E54: -
A55: Срок жилищного займа, лет | B55: 6 | C55: 7 | D55: 8 | E55: 9
A56: Ставка по жилищному займу, % | B56: 0.05 | C56: 0.048 | D56: 0.045 | E56: 0.042
A57: Ежемесячный платеж по жилищному займу, тг. | B57: =B36*B16% -> 255150 | C57: =B36*C16% -> 220500 | D57: =B36*D16% -> 195300 | E57: =B36*E16% -> 176400
A58: Переплата, тг | B58: =B53*B51+B57*B55*12+$B$36/2-$B$36 -> 6295800 | C58: =C53*C51+C57*C55*12+$B$36/2-$B$36 -> 7182000 | D58: =D53*D51+D57*D55*12+$B$36/2-$B$36 -> 8511300 | E58: =E53*E51+E57*E55*12+$B$36/2-$B$36 -> 9732450
A61: Комисии по оформлению первого займа: | C61: сумма,тг | E61: Комисии по оформлению второго займа: | G61: сумма,тг
A62: Комиссия за рассмотр. кред. заявки: | C62: 10000 | E62: Комиссия за рассмотр. кред. заявки: | G62: 10000
A63: Комисия за организацию кредита (0,5% от суммы займа), макс 100 000 тг. | C63: =IF(B36*0.005>100000,100000,B36*0.005) -> 100000 | E63: Комисия за организацию кредита (0,5% от суммы займа), макс 100 000 тг. | G63: =IF(B102*0.005>100000,100000,B102*0.005) -> 31500
A64: Комиссия за перевод | C64: 5000 | E64: Комиссия за перевод | G64: 5000 | H64: =IF(B36*0.003<5000,B36*0.003,5000) -> 5000
A65: Итого | C65: =SUM(C62:C64) -> 115000 | E65: Итого | G65: =SUM(G62:G64) -> 46500 | H65: =C62+#REF!+#REF!+C63+H64 -> #REF!
A69: Стоимость жилья,тг. | B69: 7000000
A70: Возможный платеж, тг. | B70: 250000
A71: Срок накопления, лет | B71: =IF(AND(B70>=N83,B70<M83),N82,IF(AND(B70>=M83,B70<L83),M82,IF(AND(B70>=L83,B70<K83),L82,IF(AND(B70>=K83,B70<J83),K82,IF(AND(B70>=J83,B70<I83),J82,IF(AND(B70>=I83,B70<H83),I82,IF(AND(B70>=H83,B70<G83),H82,IF(AND(B70>=G83,B70<F83),G82,IF(AND(B70>=F83,B70<E83),F82,IF(AND(B70>=E83,B70<D83),E82,IF(AND(B70>=D83,B70<C83),D82,IF(AND(B70>=C83,B70<B83),C82,IF(B70>=B83,B82,"Нет вариантов"))))))))))))) -> 3
A72: Срок жилищного займа, лет | B72: =IF(B71=B82,B85,IF(B71=C82,C85,IF(B71=D82,D85,IF(B71=E82,E85,IF(B71=F82,F85,IF(B71=G82,G85,IF(B71=H82,H85,IF(B71=I82,I85,IF(B71=J82,J85,IF(B71=K82,K85,IF(B71=L82,L85,IF(B71=M82,M85,IF(B71=N82,N85))))))))))))) -> 6
A73: Ежемесячный платеж по жилищному займ, тг. | B73: =IF(B72=B85,B87,IF(B72=C85,C87,IF(B72=D85,D87,IF(B72=E85,E87,IF(B72=F85,F87,IF(B72=G85,G87,IF(B72=H85,H87,IF(B72=I85,I87,IF(B72=J85,J87,IF(B72=K85,K87,IF(B72=L85,L87,IF(B72=M85,M87,IF(B72=N85,N87))))))))))))) -> 56700
A75: При консультации клиента необходимо заполнить поля, выделенные желтым цветом: стоимость жилья (договорная сумма) и возможный платеж (ежемесячный платеж). При этом, автоматически расчитаются поля, выленным красным шрифтом: (срок накполения, срок жилищного займа, ежемесячный платеж по жилишщному займу). В ниже приведенной таблице Вы можете посмотреть более подробную информацию, в том числе ставку вознаграждения по жилищному займу.
A81: Размер ежемесячного взноса, % от договорной суммы | B81: 1.5 | C81: 1.05 | D81: 0.83 | E81: 0.66 | F81: 0.58 | G81: 0.52 | H81: 0.44 | I81: 0.38 | J81: 0.34 | K81: 0.31 | L81: 0.28 | M81: 0.26 | N81: 0.25
A82: Срок накопления, лет | B82: 3 | C82: 4 | D82: 5 | E82: 6 | F82: 7 | G82: 8 | H82: 9 | I82: 10 | J82: 11 | K82: 12 | L82: 13 | M82: 14 | N82: 15
A83: Ежемесячный взнос, тг. | B83: =B81*$B$1/100 -> 105000 | C83: =C81*$B$1/100 -> 73500 | D83: =D81*$B$1/100 -> 58100 | E83: =E81*$B$1/100 -> 46200 | F83: =F81*$B$1/100 -> 40600 | G83: =G81*$B$1/100 -> 36400 | H83: =H81*$B$1/100 -> 30800 | I83: =I81*$B$1/100 -> 26600 | ... N83: =N81*$B$1/100 -> 17500
A84: Размер ежемесячного взноса по жил.займу, % от договорной суммы | B84: 0.81 | C84: 0.7 | D84: 0.62 | E84: 0.56 | F84: 0.51 | G84: 0.46 | H84: 0.43 | I84: 0.38 | J84: 0.34 | K84: 0.31 | L84: 0.28 | M84: 0.26 | N84: 0.25
A85: Срок жилищного займа, лет | B85: 6 | C85: 7 | D85: 8 | E85: 9 | F85: 10 | G85: 11 | H85: 12 | I85: 14 | J85: 16 | K85: 18 | L85: 21 | M85: 23 | N85: 25
A86: Ставка по жилищному займу, % | B86: 0.05 | C86: 0.048 | D86: 0.045 | E86: 0.042 | F86: 0.04 | G86: 0.038 | H86: 0.037 | I86: 0.035 | J86: 0.035 | K86: 0.035 | L86: 0.035 | M86: 0.035 | N86: 0.035
A87: Ежемесячный платеж по займу, тг. | B87: =B84*$B$1/100 -> 56700 | C87: =C84*$B$1/100 -> 49000 | D87: =D84*$B$1/100 -> 43400 | E87: =E84*$B$1/100 -> 39200 | F87: =F84*$B$1/100 -> 35700 | G87: =G84*$B$1/100 -> 32200 | H87: =H84*$B$1/100 -> 30100 | I87: =I84*$B$1/100 -> 26600 | ... N87: =N84*$B$1/100 -> 17500
A89: Комисии по оформлению займа: | C89: сумма,тг
A90: Комиссия за рассмотр. кред. заявки: | C90: 5000
A91: Страхование недвижимости (0,2%) | C91: =((B69*1.1)-B69/2)*0.2% -> 8400
A92: Титульное страхование (0,2%) | C92: =((B69*1.1)-B69/2)*0.2% -> 8400 | D92: В зависимости от срока владения недвижимостью
A93: Комисия за организацию кредита (0,5% от суммы займа), макс 100 000 тг. | C93: =IF(B69*0.005>100000,100000,B69*0.005) -> 35000
A94: Комиссия за выдачу наличными (0,5% от суммы займа), макс 50 000 тг. | C94: =IF(B69*0.005>50000,50000,B69*0.005) -> 35000 | D94: Комиссия за безналичный внешний перевод займа 0,3% от суммы займа, макс - 5 000 тг. | H94: =IF(B69*0.003<5000,B69*0.003,5000) -> 5000
A95: Итого | C95: =SUM(C90:C94) -> 91800 | D95: Итого | H95: =C90+C91+C92+C93+H94 -> 61800
A97: ДАТА ОФОРМЛЕНИЯ ПРОМ ЗАЙМА | C97: =TODAY() -> 45971
A98: ДАТА ОТКРЫТИЯ ДЕПОЗИТА | C98: 44297 | E98: если есть депозит
A99: НАЧИСЛЕННОЕ ВОЗНАГРАЖДЕНИЕ
A102: Стоимость жилья,тг. | B102: =B36*20% -> 6300000
A103: Первоначальный взнос, тг. | B103: =B102/2 -> 3150000
A105: Промежуточный стандартный
B106: =B107/12+B110 -> 7.6666667 | C106: =C107/12+C110 -> 9 | D106: =D107/12+D110 -> 10.5 | E106: =E107/12+E110 -> 11.916667 | F106: =F107/12+F110 -> 13.416667 | G106: =G107/12+G110 -> 15 | H106: =H107/12+H110 -> 16.416667 | I106: =I107/12+I110 -> 18.666667 | ... N106: =N107/12+N110 -> 32
A107: Срок промежуточного займа, МЕС | B107: =ROUNDUP(IF((1080-DAYS360(C98,C97,TRUE))/360<LOG((B102*16/1000-C99+B102/2)/(B102/2),1.02),LOG((B102*16/1000-C99+B102/2)/(B102/2),1.02)*12,(1080-DAYS360(C98,C97,TRUE))/30),0) -> 20 | C107: =ROUNDUP(IF((1080-DAYS360(C98,C97,TRUE))/360<LOG((B102*20/1000-C99+B102/2)/(B102/2),1.02),LOG((B102*20/1000-C99+B102/2)/(B102/2),1.02)*12,(1080-DAYS360(C98,C97,TRUE))/30),0) -> 24 | D107: =ROUNDUP(IF((1080-DAYS360(C98,C97,TRUE))/360<LOG((B102*25/1000-C99+B102/2)/(B102/2),1.02),LOG((B102*25/1000-C99+B102/2)/(B102/2),1.02)*12,(1080-DAYS360(C98,C97,TRUE))/30),0) -> 30 | E107: =ROUNDUP(IF((1080-DAYS360(C98,C97,TRUE))/360<LOG((B102*29/1000-C99+B102/2)/(B102/2),1.02),LOG((B102*29/1000-C99+B102/2)/(B102/2),1.02)*12,(1080-DAYS360(C98,C97,TRUE))/30),0) -> 35 | F107: =ROUNDUP(IF((1080-DAYS360(C98,C97,TRUE))/360<LOG((B102*35/1000-C99+B102/2)/(B102/2),1.02),LOG((B102*35/1000-C99+B102/2)/(B102/2),1.02)*12,(1080-DAYS360(C98,C97,TRUE))/30),0) -> 41 | G107: =ROUNDUP(IF((1080-DAYS360(C98,C97,TRUE))/360<LOG((B102*41/1000-C99+B102/2)/(B102/2),1.02),LOG((B102*41/1000-C99+B102/2)/(B102/2),1.02)*12,(1080-DAYS360(C98,C97,TRUE))/30),0) -> 48 | H107: =ROUNDUP(IF((1080-DAYS360(C98,C97,TRUE))/360<LOG((B102*45/1000-C99+B102/2)/(B102/2),1.02),LOG((B102*45/1000-C99+B102/2)/(B102/2),1.02)*12,(1080-DAYS360(C98,C97,TRUE))/30),0) -> 53 | I107: =ROUNDUP(IF((1080-DAYS360(C98,C97,TRUE))/360<LOG((B102*48/1000-C99+B102/2)/(B102/2),1.02),LOG((B102*48/1000-C99+B102/2)/(B102/2),1.02)*12,(1080-DAYS360(C98,C97,TRUE))/30),0) -> 56 | J107: =ROUNDUP(IF((1080-DAYS360(C98,C97,TRUE))/360<LOG((B102*53/1000-C99+B102/2)/(B102/2),1.02),LOG((B102*53/1000-C99+B102/2)/(B102/2),1.02)*12,(1080-DAYS360(C98,C97,TRUE))/30),0) -> 62 | K107: =ROUNDUP(IF((1080-DAYS360(C98,C97,TRUE))/360<LOG((B102*57/1000-C99+B102/2)/(B102/2),1.02),LOG((B102*57/1000-C99+B102/2)/(B102/2),1.02)*12,(1080-DAYS360(C98,C97,TRUE))/30),0) -> 66 | L107: =ROUNDUP(IF((1080-DAYS360(C98,C97,TRUE))/360<LOG((B102*61/1000-C99+B102/2)/(B102/2),1.02),LOG((B102*61/1000-C99+B102/2)/(B102/2),1.02)*12,(1080-DAYS360(C98,C97,TRUE))/30),0) -> 70 | M107: =ROUNDUP(IF((1080-DAYS360(C98,C97,TRUE))/360<LOG((B102*66/1000-C99+B102/2)/(B102/2),1.02),LOG((B102*66/1000-C99+B102/2)/(B102/2),1.02)*12,(1080-DAYS360(C98,C97,TRUE))/30),0) -> 76 | N107: =ROUNDUP(IF((1080-DAYS360(C98,C97,TRUE))/360<LOG((B102*74/1000-C99+B102/2)/(B102/2),1.02),LOG((B102*74/1000-C99+B102/2)/(B102/2),1.02)*12,(1080-DAYS360(C98,C97,TRUE))/30),0) -> 84
A108: Ставка по промежуточному займу, % | B108: 0.1
A109: Ежемесячный платеж по пром. займу, тг. | B109: =(B102*(B108/12))/(1-POWER(1/(1+B108/12),B110*12)) -> 116712.78 | C109: =(B102*(B108/12))/(1-POWER(1/(1+B108/12),C110*12)) -> 104587.46 | D109: =(B102*(B108/12))/(1-POWER(1/(1+B108/12),D110*12)) -> 95597.234 | E109: =(B102*(B108/12))/(1-POWER(1/(1+B108/12),E110*12)) -> 88695.723 | F109: =(B102*(B108/12))/(1-POWER(1/(1+B108/12),F110*12)) -> 83254.964 | G109: =(B102*(B108/12))/(1-POWER(1/(1+B108/12),G110*12)) -> 78875.228 | H109: =(B102*(B108/12))/(1-POWER(1/(1+B108/12),H110*12)) -> 75289.931 | I109: =(B102*(B108/12))/(1-POWER(1/(1+B108/12),I110*12)) -> 69816.769 | J109: =(B102*(B108/12))/(1-POWER(1/(1+B108/12),J110*12)) -> 65891.822 | K109: =(B102*(B108/12))/(1-POWER(1/(1+B108/12),K110*12)) -> 62990.153 | L109: =(B102*(B108/12))/(1-POWER(1/(1+B108/12),L110*12)) -> 59899.141 | M109: =(B102*(B108/12))/(1-POWER(1/(1+B108/12),M110*12)) -> 58412.445 | N109: =(B102*(B108/12))/(1-POWER(1/(1+B108/12),N110*12)) -> 57248.147
A110: Срок жилищного займа, лет | B110: 6 | C110: 7 | D110: 8 | E110: 9 | F110: 10 | G110: 11 | H110: 12 | I110: 14 | J110: 16 | K110: 18 | L110: 21 | M110: 23 | N110: 25
A111: Ставка по жилищному займу, % | B111: 0.05 | C111: 0.048 | D111: 0.045 | E111: 0.042 | F111: 0.04 | G111: 0.038 | H111: 0.037 | I111: 0.035 | J111: 0.035 | K111: 0.035 | L111: 0.035 | M111: 0.035 | N111: 0.035
A112: Ежемесячный платеж по жилищному займу, тг. | B112: =(B109*((1-1/POWER(1+B108/12,72-B107))/(B108/12))-$B$36/2-16*($B$36/1000)-IF(B107>12,50000,0))*(B111/12)/(1-POWER(1/(1+B111/12),B110*12)) -> -183518.84 | C112: =(C109*((1-1/POWER(1+B108/12,C110*12-C107))/(B108/12))-$B$36/2-20*($B$36/1000)-IF(C107>24,100000,0))*(C111/12)/(1-POWER(1/(1+C111/12),C110*12)) -> -160865.45 | D112: =(D109*((1-1/POWER(1+B108/12,D110*12-D107))/(B108/12))-$B$36/2-25*($B$36/1000)-IF(D107>24,100000,0))*(D111/12)/(1-POWER(1/(1+D111/12),D110*12)) -> -146588.07 | E112: =(E109*((1-1/POWER(1+B108/12,E110*12-E107))/(B108/12))-$B$36/2-29*($B$36/1000)-100000)*(E111/12)/(1-POWER(1/(1+E111/12),E110*12)) -> -132814.9 | F112: =(F109*((1-1/POWER(1+B108/12,F110*12-F107))/(B108/12))-$B$36/2-35*($B$36/1000)-IF(F107>24,100000,0))*(F111/12)/(1-POWER(1/(1+F111/12),F110*12)) -> -122995.62 | G112: =(G109*((1-1/POWER(1+B108/12,G110*12-G107))/(B108/12))-$B$36/2-41*($B$36/1000)-IF(G107>24,100000,0))*(G111/12)/(1-POWER(1/(1+G111/12),G110*12)) -> -114993.22 | H112: =(H109*((1-1/POWER(1+B108/12,H110*12-H107))/(B108/12))-$B$36/2-45*($B$36/1000)-IF(H107>24,100000,0))*(H111/12)/(1-POWER(1/(1+H111/12),H110*12)) -> -107442.89 | I112: =(I109*((1-1/POWER(1+B108/12,I110*12-I107))/(B108/12))-$B$36/2-48*($B$36/1000)-IF(I107>24,100000,0))*(I111/12)/(1-POWER(1/(1+I111/12),I110*12)) -> -92650.108 | J112: =(J109*((1-1/POWER(1+B108/12,J110*12-J107))/(B108/12))-$B$36/2-53*($B$36/1000)-IF(J107>24,100000,0))*(J111/12)/(1-POWER(1/(1+J111/12),J110*12)) -> -83761.735 | K112: =(K109*((1-1/POWER(1+B108/12,K110*12-K107))/(B108/12))-$B$36/2-57*($B$36/1000)-IF(K107>24,100000,0))*(K111/12)/(1-POWER(1/(1+K111/12),K110*12)) -> -76605.763 | L112: =(L109*((1-1/POWER(1+B108/12,L110*12-L107))/(B108/12))-$B$36/2-61*($B$36/1000)-IF(L107>24,100000,0))*(L111/12)/(1-POWER(1/(1+L111/12),L110*12)) -> -68268.58 | M112: =(M109*((1-1/POWER(1+B108/12,M110*12-M107))/(B108/12))-$B$36/2-66*($B$36/1000)-IF(M107>12,50000,0))*(M111/12)/(1-POWER(1/(1+M111/12),M110*12)) -> -64431.039 | N112: =(N109*((1-1/POWER(1+B108/12,N110*12-N107))/(B108/12))-$B$36/2-74*($B$36/1000)-IF(N107>12,50000,0))*(N111/12)/(1-POWER(1/(1+N111/12),N110*12)) -> -62103.808
A113: Переплата, тг | B113: =B109*B107+B112*B110*12+$B$36/2-$B$36 -> -26629101 | C113: =C109*C107+C112*C110*12+$B$36/2-$B$36 -> -26752599 | D113: =D109*D107+D112*D110*12+$B$36/2-$B$36 -> -26954538 | E113: =E109*E107+E112*E110*12+$B$36/2-$B$36 -> -26989659 | F113: =F109*F107+F112*F110*12+$B$36/2-$B$36 -> -27096021 | G113: =G109*G107+G112*G110*12+$B$36/2-$B$36 -> -27143094 | H113: =H109*H107+H112*H110*12+$B$36/2-$B$36 -> -27231411 | I113: =I109*I107+I112*I110*12+$B$36/2-$B$36 -> -27405479 | ... N113: =N109*N107+N112*N110*12+$B$36/2-$B$36 -> -29572298
A115: Промежуточный Женил
A117: Срок промежуточного займа, МЕС | B117: =B107 -> 20 | C117: =C107 -> 24 | D117: =D107 -> 30 | E117: =E107 -> 35
A118: Ставка по промежуточному займу, % | B118: 0.1
A119: Ежемесячный платеж по пром. займу без погашения основного долга, тг. | B119: =B102*B118/12 -> 52500 | C119: =B119 -> 52500 | D119: =B119 -> 52500 | E119: =D119 -> 52500
A120: Ежемесячный платеж через три года по пром.займу с погашением основного долга, тг. | B120: - | C120: - | D120: - | E120: -
A121: Срок жилищного займа, лет | B121: 6 | C121: 7 | D121: 8 | E121: 9
A122: Ставка по жилищному займу, % | B122: 0.05 | C122: 0.048 | D122: 0.045 | E122: 0.042
A123: Ежемесячный платеж по жилищному займу, тг. | B123: =B102*B84% -> 51030 | C123: =B102*C84% -> 44100 | D123: =B102*D84% -> 39060 | E123: =B102*E84% -> 35280
A124: Переплата, тг | B124: =B119*B117+B123*B121*12+$B$36/2-$B$36 -> -11025840 | C124: =C119*C117+C123*C121*12+$B$36/2-$B$36 -> -10785600 | D124: =D119*D117+D123*D121*12+$B$36/2-$B$36 -> -10425240 | E124: =E119*E117+E123*E121*12+$B$36/2-$B$36 -> -10102260
A126: Комисии по оформлению займа: | C126: сумма,тг
A127: Комиссия за рассмотр. кред. заявки: | C127: 5000
A128: Страхование недвижимости (0,2%) | C128: =((B102*1.1)-B103)*0.2% -> 7560
A129: Титульное страхование (0,2%) | C129: =((B102*1.1)-B103)*0.2% -> 7560
...

Sheet Народный банк-Halyk ипотека
A1: Halyk ипотека
A3: При полном подтверждении доходов | B3: От 1 года до 20 лет
A4: Целевая группа | B4: Физические лица – резиденты РК, независимо от их участия/ не участия в зарплатном проекте Банка
A6: Первоначальный взнос | B6: от 20%
B7: от 50%
A8: Сумма кредита | B8: Без ограничения, в зависимости от платежеспособности
A9: Возраст Заемщика | B9: От 21 года до 63 лет на момент завершения срока кредита
A10: Подтверждение доходов | B10: По отчислениям ЕНПФ
A11: Дополнительная информация
A12: РАСХОДЫ, СВЯЗАННЫЕ С ОФОРМЛЕНИЕМ КРЕДИТА
A13: Комиссия за рассмотрения кредитной заявки | B13: 0 тенге
A14: Комиссия за предоставление займа | B14: 0 тенге
A15: Возможно доп расходы клиента: | B15: регистрация Договоров Залога 3 тыс. тг (ЦОН), согласие заверенное нотариусом 5 тыс. тг, страхование залога от 0% .
A16: Частичное/Досрочное погашение | B16: • 0,1% от остатка ссудной задолженности, но не менее 30 000 тенге • В мобильном приложении «Halyk Homebank» -0 тенге
A19: Залогодатель | B19: Залогодатель и заемщик одно лицо
A20: Созаещик | B20: нет
A21: Дополнительная информация | B21: • Для военнослужащих: справка с места работы за последние 6 месяцев и справка о жилищных выплатах. • Для индивидуальных предпринимателей: упрощенная налоговая декларация за 24 месяца и 910 форма налоговой отчетности. По заявкам военнослужащих/индивидуальных предпринимателей требуется обращение в отделение Банка. • Заявки принимаются без участия созаемщиков, заемщик-залогодатель одно лицо. • В залог принимается только приобретаемое имущество. • Клиент будет заводить заявку в приложении после получения консультации от Застройщика.
A23: Первоначальный взнос | B23: от 20 до 50% | C23: от 51%
A24: 12 мес. | B24: 0.011 | C24: 0.011
A25: 13 - 24 мес. | B25: 0.08 | C25: 0.04
A26: 25 - 36 мес. | B26: 0.12 | C26: 0.11
A27: 37-60 мес. | B27: 0.15 | C27: 0.12
A28: 61-120 мес. | B28: 0.17 | C28: 0.15
A29: 121-180 мес. | B29: 0.18 | C29: 0.16
A30: 181-240 мес. | B30: 0.18 | C30: 0.165
A32: Первый график (выгодный): по выбору клиента
A33: Стоимость недвижимости | C33: 30000000
A34: Стоимость квартиры в ипотеку | C34: =C33*1.05 -> 31500000
A35: Первоначальный взнос - % | C35: 0.2
A36: Первоначальный взнос | C36: =C34*C35 -> 6300000
A37: Сумма Займа | C37: =C34-C36 -> 25200000
A38: Ставка вознагражд годовая | C38: 0.18
A39: Срок кредита | C39: 180
A40: Ежемесячное погашение | C40: =ROUND(POWER((1+C38/12),C39)*C38/12/(POWER((1+C38/12),C39)-1)*C37,0) -> 405826
A41: Переплата за весь срок | C41: =C40*C39-C37 -> 47848680

Sheet Халык Банк Стандарт
A1: ХАЛЫК БАНК СТАНДАРТ
A2: При полном подтверждении доходов | B2: От 1 года до 20 лет
A3: Целевая группа | B3: Физические лица – резиденты РК, независимо от их участия/ не участия в зарплатном проекте Банка
A5: Первоначальный взнос | B5: от 20%
A7: Сумма кредита | B7: Без ограничения, в зависимости от платежеспособности
A8: Возраст Заемщика | B8: От 21 года до 63 лет на момент завершения срока кредита
A9: Подтверждение доходов | B9: По отчислениям ЕНПФ
A11: Дополнительная информация
A12: РАСХОДЫ, СВЯЗАННЫЕ С ОФОРМЛЕНИЕМ КРЕДИТА
A13: Комиссия за рассмотрения кредитной заявки | B13: 0 тенге
A14: Возможно доп расходы клиента: | B14: регистрация Договоров Залога 3 тыс. тг (ЦОН), согласие заверенное нотариусом 5 тыс. тг, страхование залога от 0% .
A15: Частичное/Досрочное погашение | B15: • 0,1% от остатка ссудной задолженности, но не менее 30 000 тенге • В мобильном приложении «Halyk Homebank» -0 тенге
A18: Залогодатель | B18: Залогодатель и заемщик одно лицо
A19: Созаещик | B19: нет
A20: Дополнительная информация | B20: • Для военнослужащих: справка с места работы за последние 6 месяцев и справка о жилищных выплатах. • Для индивидуальных предпринимателей: упрощенная налоговая декларация за 24 месяца и 910 форма налоговой отчетности. По заявкам военнослужащих/индивидуальных предпринимателей требуется обращение в отделение Банка. • Заявки принимаются без участия созаемщиков, заемщик-залогодатель одно лицо. • В залог принимается только приобретаемое имущество. • Клиент будет заводить заявку в приложении после получения консультации от Застройщика.
A22: Комиссия за организацию займа | F22: Без комиссии
A23: 0.01 | F23: 0
C24: С подтверждением | D24: Без подтверждения | F24: С подтверждением | H24: Без подтверждения
A25: Первоначальный взнос / срок | C25: от 20% | D25: - | F25: от 20% | H25: -
A26: 12 мес. | C26: 17,5% | D26: - | F26: 18,5% | H26: -
A27: 13-23 мес. | C27: 17,5% | D27: - | F27: 18,5% | H27: -
A28: 24-36 мес. | C28: 17,5% | D28: - | F28: 18,5% | H28: -
A29: 37-120 мес. | C29: 17,5% | D29: - | F29: 18,5% | H29: -
A30: 121-180 мес. | C30: 17,5% | D30: - | F30: 18,5% | H30: -
A31: 181-240 мес | C31: 17,5% | D31: - | F31: 18,5% | H31: -
A35: Стоимость недвижимости | C35: 30000000
A36: Стоимость квартиры в ипотеку | C36: =C35*1.05 -> 31500000
A37: Первоначальный взнос - % | C37: 0.2
A38: Первоначальный взнос | C38: =C36*C37 -> 6300000
A39: Сумма Займа | C39: =C36-C38 -> 25200000
A40: Ставка вознагражд годовая | C40: 0.175
A41: Срок кредита | C41: 180
A42: Ежемесячное погашение | C42: =ROUND(POWER((1+C40/12),C41)*C40/12/(POWER((1+C40/12),C41)-1)*C39,0) -> 396794
A43: Переплата за весь срок | C43: =C42*C41-C39 -> 46222920

Sheet Алтын банк Стандарт 
A1: АЛТЫН БАНК СТАНДАРТ
A2: Условия программы | D2: Срок / Взнос
A3: При полном подтверждении доходов | D3: до 20 лет / от 20%
A4: Без подтверждения доходов | D4: до 15 лет / от 50%
A5: Целевая группа | D5: Физические лица. Граждане РК, жители РК с Видом на Жительства до срока окончания, в случае стажа работы свыше 5 лет в КЗ то можно на мах срок займа
A6: Сумма кредита | D6: Минимум 1 млн – максимум 80 млн онлайн, 175 млн оффлайн
A7: Возраст Заемщика | D7: От 21 года до 65 лет на момент завершения срока кредита
A8: Подтверждение доходов | D8: При оформлении займа с подтверждением доходов 6 месяцев пенсионных отчислений в ЕНПФ обязательны, выписка с БВУ
A9: РАСХОДЫ, СВЯЗАННЫЕ С ОФОРМЛЕНИЕМ КРЕДИТА
A10: Возможно доп расходы клиента: | D10: Стоимость оценки 12-15 тыс. тг , регистрация Договоров Залога 3 тыс. тг (ЦОН), согласие завереное нотариусом 5 тыс. тг.
A11: Досрочное погашение | D11: 25 000 тенге до 12 месяцев, свыше 12 месяцев 0 тенге. Разрешается полное/частичное досрочное погашение в любое время. При частичном досрочном погашении сумма частичного погашения должна быть не менее суммы трех (очередных) ежемесячных платежей.
A12: Залогодатель | D12: Любое 3 лицо (до 70 лет должен закрыться кредит).
A13: Созаещик | D13: любое 3 лицо , не более 2 человек.
A16: Комиссия за организацию займа | G16: Без комиссии
A17: 0.0199 | G17: 0
C18: С подтверждением | E18: Без подтверждения | G18: С подтверждением | I18: Без подтверждения
A19: Срок/первоначальный взнос | C19: от 20% | E19: от 50% | G19: от 20% | I19: от 50%
A20: 12 мес. | C20: 14,0% | E20: 17,0% | G20: 20% | I20: 21,5%
A21: 13-23 мес. | C21: 18,5% | E21: 17,0% | G21: 20% | I21: 21,5%
A22: 24-36 мес. | C22: 18,5% | E22: 19,5% | G22: 20% | I22: 21,5%
A23: 37-120 мес. | C23: 18,5% | E23: 20,5% | G23: 20% | I23: 21,5%
A24: 121-180 мес. | C24: 19,0% | E24: 20,5% | G24: 20% | I24: 21,5%
A25: 181-240 мес | C25: 19,0% | E25: - | G25: 20% | I25: -
A29: Стоимость квартиры | C29: 25000000
A30: Стоимость квартиры в ипотеку | C30: =29:29 -> 25000000
A31: Первоначальный взнос, % | C31: 0.2
A32: Первоначальный взнос | C32: =C30*C31 -> 5000000
A33: Сумма Займа | C33: =C30-C32 -> 20000000
A34: Ставка вознагражд годовая | C34: 0.19 | G34: 7
A35: Срок кредита | C35: 180
A36: Ежемесячное погашение | C36: =ROUND(POWER((1+C34/12),C35)*C34/12/(POWER((1+C34/12),C35)-1)*C33,0) -> 336575
A37: Переплата за весь срок | C37: =C36*C35-C33 -> 40583500

Sheet БЦК Стандарт
A1: БЦК Стандарт
A2: Размер первоначального взноса | C2: Срок / Взнос
A3: При полном подтверждении доходов | C3: до 15 лет / от 20%
A4: Без подтверждения дохода | C4: до 15 лет / от 50%
A5: Целевая группа | C5: физические лица резиденты РК – от 21 года до 68 лет (на момент окончания кредита)
A6: Стоимость квартиры | C6: для сегмента с подтверждением доходов и первоначальным взносом от 20% до 30%: • для городов Астана, Алматы, Шымкент, Караганда, Актау, Атырау, Актобе, Усть-Каменогорск – 40 млн. тенге; • для остальных регионов – 25 млн.тенге Отсутствуют ограничения к стоимости жилья при первоначальном взносе от 30%
A7: Дополнительное преимущество | C7: Клиент вправе в качестве первоначального взноса, предоставить в залог дополнительный объект обеспечения (жилая недвижимость (дома, квартиры))
A8: Возраст Заемщика | C8: от 21 года до 68 лет (на момент окончания кредита)
A9: Подтверждение доходов | C9: Рассматриваются любые варианты подтверждения доходов
A10: РАСХОДЫ, СВЯЗАННЫЕ С ОФОРМЛЕНИЕМ КРЕДИТА
A11: Комиссия за рассмотрения кредитной заявки | C11: 5000 тенге
A12: Возможно доп расходы клиента: | C12: регистрация Договоров Залога 3 тыс. тг (ЦОН), согласие заверенное нотариусом 5 тыс. тг, страхование залога от 0%
A13: Досрочное погашение | C13: 1 % от суммы до 12 месяцев, свыше 12 месяцев 0 тенге. Разрешается полное/частичное досрочное погашение в любое время.
A14: Созаещик | C14: любое 3 лицо , не более 2 человек.
A16: Подтверждение дохода | B16: Размер ПВ | C16: Комиссия | D16: 120 мес. | E16: 180мес.
D17: Ставки вознаграждения
A19: С подтверждением дохода | B19: 0.2 | C19: 0.02 | D19: 0.195 | E19: 0.2
B20: 0.5 | C20: 0.02 | D20: 0.185 | E20: 0.195
A21: Без подтверждения дохода | B21: 0.5 | C21: 0.02 | D21: 0.215 | E21: 0.2175
A22: Для клиентов ЗП проектов
A23: С подтверждением дохода | B23: 0.2 | C23: 0.01 | D23: 0.195 | E23: 0.2
B24: 0.5 | C24: 0.01 | D24: 0.185 | E24: 0.195
A25: Без подтверждения дохода | B25: 0.5 | C25: 0.01 | D25: 0.215 | E25: 0.2175
A29: Стоимость квартиры | B29: 25000000
A30: Стоимость квартиры ипотеку | B30: =B29 -> 25000000
A31: Первоначальный взнос, % | B31: 0.2
A32: Первоначальный взнос | B32: =B30*B31 -> 5000000
A33: Сумма Займа | B33: =B30-B32 -> 20000000
A34: Ставка вознагражд годовая | B34: 0.195
A35: Срок кредита | B35: 120
A36: Ежемесячное погашение | B36: =ROUND(POWER((1+B34/12),B35)*B34/12/(POWER((1+B34/12),B35)-1)*B33,0) -> 379904
A37: Переплата за весь срок | B37: =B36*B35-B33 -> 25588480

Sheet БЦК  Залоговый Кредит
A1: Условия продукта
A2: Целевая группа | B2: Физические лица
A3: Цель финансирования | B3: На любые потребительские нужды
A4: Валюта финансирования | B4: Тенге
A5: Максимальная сумма кредита | B5: До 70% - от стоимости квартиры с подтверждением дохода;
B6: До 60% - от стоимости жилого дома/коммерческого встроенного помещения в чистовой отделке;
B7: До 50% - без подтверждения (косвенное подтверждение) дохода от стоимости квартиры;
B8: До 30% от рыночной от стоимости квартиры/жилого дома, если сумма займа свыше 100 000 000 тг.
B9: До 30% от рыночной от стоимости (мах до 30 млн.тг) жилого дома в черновой/предчистовой отделке. Срок эксплуатации не более 3 лет
A10: Обеспечение | B10: Квартиры;
B11: Жилой дом;
B12: Коммерческая недвижимость
A13: Возраст | B13: От 21 года до 68 лет
A14: Требование по квартире | B14: Допускается (материал стен): Бетон, Блочный, Кирпич, Монолит, Панель, Пеноблочный, Ракушечный, Газоблок/газобетон;
A15: Требование по жилым домам | B15: Допускается (материал стен): Бетон, Блочный, Брусчатый, бревенчатый, Деревянные, шпальные, Кирпич, Монолит, Панель, Пеноблочный, Ракушечный, Шлак, Газоблок/газобетон. Так же по городам Шымкент, Кызылорда, Тараз, Туркестан: Глинобитные, Саманные, Сырцовые;
B16: Запрещено принятие жилых домов с земельным участком менее 0.04 га. Исключением являются дома, расположенные в коттеджных городках (таунхаусы), где площадь земельного участка должна составлять от 0.02 га
B17: Запрещено принятие жилых домов с ЗУ на праве временного (возмездного) землепользования (аренды)
B18: Не рассматриваются объекты в черновой отделке а так же с наличием расхождений по техническому паспорту
B19: Срок эксплуатации превышающие 20 лет, кредитование возможно только С ПОДТВЕРЖДЕНИЕМ дохода
A20: Требование по Коммерческой недвижимости | B20: В черновой отделке не рассматривается
B21: В цокольном этаже не рассматривается
A22: Ограничения срок возникновения права собственности на недвижимость (передаваемую в обеспечение) | B22: · 1. Вид права собственности (правоустанавливающие документы): договор дарения и купли-продажи;
B23: · 2. Срок правоустанавливающего документа на момент подачи кредитной заявки должен быть не менее 3-х месяцев за исключением следующих случаев:
B24: · - продавец/даритель недвижимости, принимаемой в залог Банком выступает гарантом либо заемщиком;
B25: · - продавцом недвижимости, принимаемой в залог Банком является застройщик;
B26: · - продавцом/дарителем недвижимости, принимаемой в залог Банком является физическое лицо возрастом менее 21 года и более 65 лет на момент подачи заявлении на получение кредита.
A27: Максимальный срок кредита | B27: От 3-х месяцев до 120 месяцев.
A28: Ставка вознаграждения (залог КВАРТИРА) | B28: 21 % годовых
A29: Ставка вознаграждения (залог Жилые дома в черновой/предчистовой отделке) | B29: 23 % годовых
A30: РАСХОДЫ, СВЯЗАННЫЕ С ОФОРМЛЕНИЕМ КРЕДИТА
A31: Открытие счета | B31: · 0 тенге
A32: Комиссия за рассмотрения кредитной заявки | B32: 0 тенге
A33: Оценка недвижимости | B33: В зависимости от площади недвижимости по тарифам оценочной компании.
A34: ПОСЛЕ ОДОБРЕНИЯ О ПРЕДОСТАВЛЕНИИ КРЕДИТА
A35: Комиссия за предоставление займа | B35: 0 тенге
A36: Страхование | B36: 1,5 % от суммы займа (оплачивается отдельно перед выдачей кредита)
A37: Досрочное погашение | B37: Без штрафных санкций после 12 месяцев
B38: До 12 месяцев штраф 1% от суммы погашения
A39: РАСЧЕТЫ и РАСХОДЫ ПО ОФОРМЛЕНИЮ КРЕДИТА
A40: Таблица расходов
A42: Сумма Займа | B42: 10000000
A43: Ставка вознагражд годовая | B43: 0.21
A44: Срок кредита | B44: 120
A45: Ежемесячное погашение | B45: =ROUND(POWER((1+B43/12),B44)*B43/12/(POWER((1+B43/12),B44)-1)*B42,0) -> 199932
A46: Переплата за весь срок | B46: =B45*B44-B42 -> 13991840
A47: Комиссия за организацию займа | B47: 0
A48: Страхование | B48: =B42*1.5% -> 150000
A49: Регистрация договора залога | B49: По тарифам нотариуса
A50: Нотариальное согласие на залог | B50: По тарифам нотариуса

Sheet Наурыз Отбасы банк
A1: Ипотека "Наурыз"
A2: Условия программы
A3: Срок кредитования | D3: до 19 лет
A4: Размер первоначального взноса | D4: от 10% при покупке квартиры в чистовой отделке, от 20% при покупке квартиры в черновой отделке
A5: Сумма кредита | D5: до 36 млн. для городов Астана, Алматы. До 30 млн - другие регионы
A6: Ставкпо займу | D6: для лиц, состоящих на учете в качестве нуждающихся в жилье по категории социально-уязвимые слои населения | E6: для лиц, состоящих на учете в качестве нуждающихся в жилье и иных граждан Республики Казахстан и кандасов
D7: 7% (ГЭСВ от 7,3% до 8,9%); | E7: 9% (ГЭСВ от 9,3% до 11,8%)
A8: Участники программы | D8: граждане Республики Казахстан или граждане со статусом "Кандас"
A9: Требования к участникам | D9: Возраст участника от 18 до 63 лет включительно; Отсутствие жилья и фактов отчуждения за последние 5 лет на территории РК; Наличие официального дохода в течение последних 6 месяцев;
A10: Созаемщики | D10: Можно привлечь до двух созаемщиков
A11: Минимальная сумма накопления на депозите | D11: от 2 000 000 тг (сумму можно внести единовременно перед подачей заявления)
A12: Целевое использование | D12: Приобретение первичного жилья, а также приобретение и ремонт приобретенного первичного жилья (в рамках одного договора банковского займа), введенного в эксплуатацию или реализуемого по договору долевого участия, при условии наличия гарантии единого оператора жилищного строительства, либо с использованием инструмента страхования. В городах Астана, Алматы, Шымкент и областных центрах допускается приобретение только первичного жилья.
A13: Дополнительная информация | D13: Отсутствие у участника и членов его семьи в собственности жилья и операций с жильем в течение последних 5 лет. Члены семьи – это муж, жена и их несовершеннолетние дети. В программе может участвовать только один из супругов. Если человек не состоит в браке, то отсутствие жилья проверяется только у него. Родителей совершеннолетних казахстанцев не проверяют на наличие жилья. Также в рамках одного кредита можно будет взять деньги на ремонт приобретаемого первичного жилья. Сумма займа на ремонт не должна быть более 20 % от общей суммы кредита на покупку жилья, но в пределах максимальной суммы займа. При этом, заем на ремонт предоставляется исключительно при приобретении первичного жилья в черновой отделке. Жилье участник сможет выбрать, забронировать и купить на портале Баспана маркет (https://otbasybank.kz/)

Sheet Наурыз жұмыскер Отбасы банк
C1: Ипотека "Наурыз жұмыскер"
C2: Условия программы
C3: Срок кредитования | F3: до 19 лет | J3: ОБЩИЙ КЛАССИФИКАТОР ВИДОВ ЭКОНОМИЧЕСКОЙ ДЕЯТЕЛЬНОСТИ (ОКЭД)
C4: Размер первоначального взноса | F4: от 10% при покупке квартиры в чистовой отделке, от 20% при покупке квартиры в черновой отделке | J4: Код ОКЭД | M4: Наименование
C5: Сумма кредита | F5: до 36 млн. для городов Астана, Алматы. До 30 млн - другие регионы | J5: A | M5: Сельское, лесное и рыбное хозяйство
C6: Ставкпо займу | F6: для лиц, состоящих на учете в качестве нуждающихся в жилье по категории социально-уязвимые слои населения | G6: для лиц, состоящих на учете в качестве нуждающихся в жилье и иных граждан Республики Казахстан и кандасов | J6: B | M6: Горнодобывающая промышленность и разработка карьеров
F7: 7% (ГЭСВ от 7,3% до 8,9%); | G7: 9% (ГЭСВ от 9,3% до 11,8%) | J7: C | M7: Обрабатывающая промышленность
C8: Участники программы | F8: граждане Республики Казахстан или граждане со статусом "Кандас" | J8: D | M8: Снабжение электроэнергией, газом, паром, горячей водой и кондиционированным воздухом
